Workbook
Name B.E: #REF!
Name B_Capex__Infrastructure: [2]Assumptions!$Q$19
Name B_Capping_Cost_per_tonne: [2]Assumptions!$T$19
Name B_Cell_Cost: [2]Assumptions!$S$19
Name B_Change_in_Working_Capital: [2]DCF!$E$269:$U$269
Name B_Construction_start_date: [2]Assumptions!$F$19
Name B_Depletion_Charge: [2]DCF!$E$165:$U$165
Name B_End_of_Life_Cost: [2]Assumptions!$Z$19
Name B_Fixed_Opex: [2]Assumptions!$P$19
Name B_Leachate_Logistics_and_Freight_Cost: [2]Assumptions!$W$19
Name B_Market_Share_in_Silverberry_Closes_Scenario: [2]Assumptions!$K$19
Name B_Market_Share_with_Competition: [2]Assumptions!$J$19
Name B_Market_share_without_Competition: [2]Assumptions!$I$19
Name B_Max_Throughput: [2]DCF!$E$127:$U$127
Name B_Op_days_before_Competition: [2]Assumptions!$U$19
Name B_Op_days_with_Competition: [2]Assumptions!$V$19
Name B_Opex_Costs: [2]DCF!$E$360:$U$360
Name B_Rate___Increase_in_Silverberry_Close_Scenario___No_Competition: [2]Assumptions!$O$19
Name B_Rate___Increase_in_Silverberry_Close_Scenario_Competition: [2]Assumptions!$N$19
Name B_Rate___Increase_with_Competition: [2]Assumptions!$M$19
Name B_Rate___Increase_without_Competition: [2]Assumptions!$L$19
Name B_Remediation: [2]Assumptions!$Y$19
Name B_Remediation_Year: [2]Assumptions!$X$19
Name B_Total_Waste_Revenue: [2]DCF!$E$255:$U$255
Name base: [3]Model!#REF!
Name BASE_CONDENSATE_VOLUME: '[4]C5+'!$C$17
Name BASE_SW_VOLUME: [4]SW!$E$17
Name basediff: [3]Assumptions!#REF!
Name basefreight: [3]Assumptions!#REF!
Name basesales: [3]Assumptions!#REF!
Name basis: [3]Assumptions!#REF!
Name BlackPEARLHeavyOil: '[5]BLEND MODEL'!$D$22
Name BlackSPURHeavyOil: '[5]BLEND MODEL'!#REF!
Name BlendDensity: '[5]BLEND MODEL'!$I$40
Name BlendSulphurPercent: '[5]BLEND MODEL'!$I$41
Name BOY: '[6]Inputs & Assumptions'!#REF!
Name brown: [3]Model!#REF!
Name browndiff: [3]Assumptions!#REF!
Name brownfreight: [3]Assumptions!#REF!
Name BrownIRR: [3]DCF!#REF!
Name brownprod: [3]Model!$A$10:$IV$10,[3]Model!#REF!
Name brownsales: [3]Assumptions!#REF!
Name Budget: [7]Input!$B$11
Name ButaneInjected: '[5]BLEND MODEL'!$H$22
Name Calendar_Year: '[2]Fixed Assumptions'!$E$1:$AF$1
Name capex: [8]Assumptions!$C$29
Name Capex_Type: [9]Tables!$B$4:$B$17
Name case: [3]Model!#REF!
Name Current_Forecast: [10]Inputs!$B$3
Name Current_Period: [7]Input!$B$5
Name Current_QTD: [10]Inputs!$B$9
Name Current_YTD: [7]Input!$B$7
Name days: [8]Assumptions!$C$5
Name DCFIRR: [3]DCF!$F$34
Name DEEMED_BUTANE: '[4]C5+'!$K$40
Name Depre: [8]Assumptions!$C$7
Name deptid: '[11]Inputs & Assumptions'!$B$4
Name Discount_Factor: '[2]Fixed Assumptions'!$E$4:$AF$4
Name discount_rate: #REF!
Name Division: [9]Tables!$H$4:$H$15

Sheet Inputs
C3: INPUTS
B4: Pricing Month | C4: 45413
B5: Producer Raw Crude Volume | C5: 21147 | D5: M3/M
B6: Producer Raw Crude TAN | C6: 0.65 | D6: mgOH
B7: FSK Condensate Density | C7: 660 | D7: KG/M3
B8: FSK Condensate Sulphur | C8: 0.00015 | D8: %Swt
B9: FSK Condensate Truck Unload | C9: 8.5 | D9: CAD/M3
B10: FSK Condensate Transport (UtikumaNorth) | C10: ='Spur-Netback'!I9 -> 32.586207 | D10: CAD/M3
B11: FSK Condensate Transport (Utikuma/Nipisi-South) | C11: ='Spur-Netback'!I11 -> 29.689655 | D11: CAD/M3
B12: FSK Condensate Transport (Mitsue) | C12: ='Spur-Netback'!I12 -> 25.344828 | D12: CAD/M3
B13: CRW Condensate Density | C13: 730 | D13: KG/M3
B14: RP2 Condensate Density | C14: 737 | D14: KG/M3
B15: C4 Landed Price (not included Transportation) | C15: ='UtikuSouthTT DilFee Nipisi'!B10 -> 0.475 | D15: % WTI
B16: Spur Raw Crude Density | C16: 965 | D16: KG/M3
B17: Spur Historical Monthly Blend Density Target (Actual Physical) | C17: =_xlfn.XLOOKUP($C$4,MonthlyData!$B:$B,MonthlyData!$CB:$CB) -> 924.2 | D17: KG/M3
B18: Spur Monthly Paper Blend Density (350cSt) | C18: =_xlfn.XLOOKUP($C$4,MonthlyData!$B:$B,MonthlyData!$CC:$CC) -> 924.4 | D18: KG/M3
B19: Utikuma North Terminal Fee | C19: 5.25 | D19: CAD/M3
B20: Utikuma South Terminal Fee | C20: 4.7 | D20: CAD/M3
B21: Utikuma North Terminal Pembina Power Surcharge | C21: 0.1 | D21: CAD/M3
B22: Utikuma Diluent Sharing | C22: 0.9 | D22: %
B23: Mitsue Diluent Sharing | C23: 0.85 | D23: %
B24: Producer | C24: Spur
B25: Butane Injection | C25: 0.0319 | D25: C4/Raw %
B26: Nipisi Pipeline L/A | C26: 0.002
B27: Rainbow Pipeline L/A | C27: 0.002
B28: Utikuma North TT Location Factor | C28: 1.1
B30: Customer Producers
B31: Spur
B32: Tamarack
B33: Obsidian
B34: Baytex
B35: Headwater
B37: Month of the Year
B38: January
B39: February
B40: March
B41: April
B42: May
... B49: December
B51: Pricing Month | C51: 45200 | D51: 45231 | E51: 45261 | F51: 45292 | G51: 45323 | H51: 45352 | I51: 45383 | J51: 45413 | K51: 45444 | L51: 45474 | M51: 45505 | N51: 45536 | O51: 45566 | P51: 45597 | Q51: 45627 | R51: 45658 | S51: 45689 | T51: 45717 | U51: 45748 | V51: 45778

Sheet Spur-Netback
B2: Butane Trucking (KeyeraFortSask) | C2: Length (hrs) | D2: Round Trip | E2: Loading & Unloading | F2: Total Truck Hours | G2: Truck Rate (CAD/HR) | H2: Truck Volume (M3 Raw/Load) | I2: Trucking Cost (CAD/M3 C4)
B3: Utikuma North Truck Terminal (Nipisi P/L) | C3: 3.5 | D3: =C3*2 -> 7 | E3: =IF(C3>0, 2, 0) -> 2 | F3: =E3+D3 -> 9 | G3: 210 | H3: 62 | I3: =(F3*G3)/H3 -> 30.483871
B4: Nipisi South Truck Terminal (Nipisi P/L) | C4: 3.1 | D4: =C4*2 -> 6.2 | E4: =IF(C4>0, 2, 0) -> 2 | F4: =E4+D4 -> 8.2 | G4: =$G$15 -> 210 | H4: =H$3 -> 62 | I4: =(F4*G4)/H4 -> 27.774194
B5: Utikuma South Truck Terminal (Nipisi P/L) | C5: 3.1 | D5: =C5*2 -> 6.2 | E5: =IF(C5>0, 2, 0) -> 2 | F5: =E5+D5 -> 8.2 | G5: =$G$15 -> 210 | H5: =H$3 -> 62 | I5: =(F5*G5)/H5 -> 27.774194
B6: Mitsue Truck Terminal (Nipisi P/L) | C6: 2.5 | D6: =C6*2 -> 5 | E6: =IF(C6>0, 2, 0) -> 2 | F6: =E6+D6 -> 7 | G6: =$G$15 -> 210 | H6: =H$3 -> 62 | I6: =(F6*G6)/H6 -> 23.709677
B8: Condensate Trucking (KeyeraFortSask) | C8: Length (hrs) | D8: Round Trip | E8: Loading & Unloading | F8: Total Truck Hours | G8: Truck Rate (CAD/HR) | H8: Truck Volume (M3 Raw/Load) | I8: Trucking Cost (CAD/M3 C5+)
B9: Utikuma North Truck Terminal (Nipisi P/L) | C9: 3.5 | D9: =C9*2 -> 7 | E9: =IF(C9>0, 2, 0) -> 2 | F9: =E9+D9 -> 9 | G9: 210 | H9: 58 | I9: =(F9*G9)/H9 -> 32.586207
B10: Nipisi South Truck Terminal (Nipisi P/L) | C10: 3.1 | D10: =C10*2 -> 6.2 | E10: =IF(C10>0, 2, 0) -> 2 | F10: =E10+D10 -> 8.2 | G10: =$G$15 -> 210 | H10: =H$9 -> 58 | I10: =(F10*G10)/H10 -> 29.689655
B11: Utikuma South Truck Terminal (Nipisi P/L) | C11: 3.1 | D11: =C11*2 -> 6.2 | E11: =IF(C11>0, 2, 0) -> 2 | F11: =E11+D11 -> 8.2 | G11: =$G$15 -> 210 | H11: =H$9 -> 58 | I11: =(F11*G11)/H11 -> 29.689655
B12: Mitsue Truck Terminal (Nipisi P/L) | C12: 2.5 | D12: =C12*2 -> 5 | E12: =IF(C12>0, 2, 0) -> 2 | F12: =E12+D12 -> 7 | G12: =$G$15 -> 210 | H12: =H$9 -> 58 | I12: =(F12*G12)/H12 -> 25.344828
B14: Spur Raw Crude (Clean Only) Trucking (NipisiNorthHwy88) | C14: Length (hrs) | D14: Round Trip | E14: Loading & Unloading | F14: Total Truck Hours | G14: Truck Rate (CAD/HR) | H14: Truck Volume (M3 Raw/Load) | I14: Trucking Cost (CAD/M3 Raw) | W14: CHV Stream Blended Density Historicals | X14: Jan | Y14: Feb | Z14: Mar | AA14: Apr | AB14: May | AC14: June | AD14: July | AE14: Aug | AF14: Sept | AG14: Oct | AH14: Nov | AI14: Dec
B15: Nipisi North Truck Terminal (Rainbow P/L) | C15: 0 | D15: =C15*2 -> 0 | E15: 2 | F15: =E15+D15 -> 2 | G15: 210 | H15: 35 | I15: =(F15*G15)/H15 -> 12 | W15: 2023 CHV Blended Density | X15: 923.8 | Y15: 924.8 | Z15: 927.9 | AA15: 922 | AB15: 922.4 | AC15: 919.2 | AD15: 927 | AE15: 929.4 | AF15: 936.5 | AG15: 936.3 | AH15: 925.9 | AI15: 923.5
B16: Utikuma North Truck Terminal (Nipisi P/L) | C16: 0.1 | D16: =C16*2 -> 0.2 | E16: =IF(C16>0, 2, 0) -> 2 | F16: =E16+D16 -> 2.2 | G16: =$G$15 -> 210 | H16: 35 | I16: =(F16*G16)/H16 -> 13.2
B17: Nipisi South Truck Terminal (Nipisi P/L) | C17: 0.4 | D17: =C17*2 -> 0.8 | E17: =IF(C17>0, 2, 0) -> 2 | F17: =E17+D17 -> 2.8 | G17: =$G$15 -> 210 | H17: 35 | I17: =(F17*G17)/H17 -> 16.8 | W17: 2024 CHV Blended Density | X17: 926.4 | Y17: 920.1 | Z17: 920.2 | AA17: 921.2 | AB17: 924.1 | AC17: 924.6 | AD17: 931.3 | AE17: 932.9 | AF17: 934 | AG17: 934.4 | AH17: 930.6 | AI17: 925.3
B18: Utikuma South Truck Terminal (Nipisi P/L) | C18: 0.4 | D18: =C18*2 -> 0.8 | E18: =IF(C18>0, 2, 0) -> 2 | F18: =E18+D18 -> 2.8 | G18: =$G$15 -> 210 | H18: 35 | I18: =(F18*G18)/H18 -> 16.8
B19: Mitsue Truck Terminal (Nipisi P/L) | C19: 1 | D19: =C19*2 -> 2 | E19: =IF(C19>0, 2, 0) -> 2 | F19: =E19+D19 -> 4 | G19: =$G$15 -> 210 | H19: 35 | I19: =(F19*G19)/H19 -> 24 | W19: 2025 CWH Blended Density | X19: 921.6 | Y19: 921.9 | Z19: 920.6 | AA19: 921.6 | AB19: 922.8 | AC19: 927.1
B20: Spur MH Battery (Rainbow P/L) | C20: 1.8 | D20: =C20*2 -> 3.6 | E20: =IF(C20>0, 2, 0) -> 2 | F20: =E20+D20 -> 5.6 | G20: =$G$15 -> 210 | H20: 35 | I20: =(F20*G20)/H20 -> 33.6
B21: Gibsons Edmonton (CHV Pricing) | C21: 4.4 | D21: =C21*2 -> 8.8 | E21: =IF(C21>0, 2, 0) -> 2 | F21: =E21+D21 -> 10.8 | G21: =$G$15 -> 210 | H21: 35 | I21: =(F21*G21)/H21 -> 64.8
B22: Flint Hills Hardisty (WCS Pricing) | C22: 5.85 | D22: =C22*2 -> 11.7 | E22: =IF(C22>0, 2, 0) -> 2 | F22: =E22+D22 -> 13.7 | G22: =$G$15 -> 210 | H22: 35 | I22: =(F22*G22)/H22 -> 82.2 | W22: WCS Blend Density History | X22: Jan | Y22: Feb | Z22: Mar | AA22: Apr | AB22: May | AC22: June | AD22: July | AE22: Aug | AF22: Sept | AG22: Oct | AH22: Nov | AI22: Dec
W23: 2023 WCS Blended Density | X23: 918 | Y23: 922.1 | Z23: 923.1 | AA23: 921.9 | AB23: 924.7 | AC23: 926.9 | AD23: 931.4 | AE23: 932 | AF23: 935.5 | AG23: 928.3 | AH23: 926.3 | AI23: 923.1
W24: 2024 WCS Blended Density | X24: 922.3 | Y24: 922.1 | Z24: 924.4 | AA24: 921.1 | AB24: 924.8 | AC24: 928.6 | AD24: 933.6 | AE24: 931.2 | AF24: 936.1 | AG24: 930.8 | AH24: 926.2 | AI24: 921.4
B25: Blended Crude Netback Comparison | C25: =Inputs!C4 -> 45413 | W25: 2025 WCS Blended Density | X25: 920.4 | Y25: 919.7 | Z25: 922.3 | AA25: 921.8 | AB25: 923.8 | AC25: 928
B27: Receipt Location - Blended Crude | C27: =B15 -> Nipisi North Truck Terminal (Rainbow P/L) | D27: =B17 -> Nipisi South Truck Terminal (Nipisi P/L) | E27: =B16 -> Utikuma North Truck Terminal (Nipisi P/L) | F27: =B18 -> Utikuma South Truck Terminal (Nipisi P/L) | G27: =B19 -> Mitsue Truck Terminal (Nipisi P/L) | H27: Marten Hills P/L (Rainbow P/L) | I27: =B21 -> Gibsons Edmonton (CHV Pricing) | J27: =B22 -> Flint Hills Hardisty (WCS Pricing) | X27: Blended Crude Density to get to 350cSt (Paper Blend Target)
W28: Customer Producers | X28: 45200 | Y28: 45231 | Z28: 45261 | AA28: 45292 | AB28: 45323 | AC28: 45352 | AD28: 45383 | AE28: 45413 | AF28: 45444 | AG28: 45474 | AH28: 45505 | AI28: 45536
B29: Raw Crude Volume (M3/M) | C29: =Inputs!$C$5 -> 21147 | D29: =Inputs!$C$5 -> 21147 | E29: =Inputs!$C$5 -> 21147 | F29: =Inputs!$C$5 -> 21147 | G29: =Inputs!$C$5 -> 21147 | H29: =Inputs!$C$5 -> 21147 | I29: =Inputs!$C$5 -> 21147 | J29: =Inputs!$C$5 -> 21147 | W29: Spur | X29: 925.6 | Y29: 923 | Z29: 921.8 | AA29: 921.2 | AB29: 921.2 | AC29: 918.1 | AD29: 921.5 | AE29: 924.4 | AF29: 931 | AG29: 934.8 | AH29: 930.9 | AI29: 927.8
B30: Raw Crude Density (KG/M3) | C30: =Inputs!C16 -> 965 | D30: =$C$30 -> 965 | E30: =$C$30 -> 965 | F30: =$C$30 -> 965 | G30: =$C$30 -> 965 | H30: =$C$30 -> 965 | I30: =$C$30 -> 965 | J30: =$C$30 -> 965 | W30: Tamarack | X30: 925.6 | Y30: 923 | Z30: 921.1 | AA30: 921.3 | AB30: 920.9 | AC30: 923 | AD30: 923.1 | AE30: 926.2 | AF30: 930.6 | AG30: 935 | AH30: 931 | AI30: 928
B31: Blended Crude Target Density (KG/M3) | C31: =Inputs!$C$18 -> 924.4 | D31: =Inputs!$C$18 -> 924.4 | E31: =Inputs!$C$18 -> 924.4 | F31: =Inputs!$C$18 -> 924.4 | G31: =Inputs!$C$18 -> 924.4 | H31: =Inputs!$C$18 -> 924.4 | I31: =Inputs!$C$18 -> 924.4 | J31: =Inputs!$C$18 -> 924.4 | W31: Obsidian | X31: 917.9 | Y31: 914.6 | Z31: 912.3 | AA31: 912.9 | AB31: 915.3 | AC31: 915.8 | AD31: 914.8 | AE31: 916.4 | AF31: 919.7 | AG31: 929.2 | AH31: 925.3 | AI31: 921.6
B32: Raw Crude Sulphur (%) | C32: 4 | D32: 4 | E32: 4 | F32: 4 | G32: 4 | H32: =C32 -> 4 | I32: 4 | J32: 4 | W32: Baytex | AB32: 921 | AC32: 921.5 | AD32: 916.1 | AE32: 917.9 | AF32: 920.7 | AG32: 929.8
B33: Raw Crude TAN | C33: =Inputs!$C$6 -> 0.65 | D33: =Inputs!$C$6 -> 0.65 | E33: =Inputs!$C$6 -> 0.65 | F33: =Inputs!$C$6 -> 0.65 | G33: =Inputs!$C$6 -> 0.65 | H33: =Inputs!$C$6 -> 0.65 | I33: =Inputs!$C$6 -> 0.65 | J33: =Inputs!$C$6 -> 0.65 | W33: Headwater | AD33: 913.4 | AE33: 926.5 | AF33: 928.5 | AG33: 932.5
B34: Condensate Density (KG/M3) | C34: =Inputs!C14 -> 737 | D34: =Inputs!C7 -> 660 | E34: =Inputs!$C$7 -> 660 | F34: =Inputs!$C$7 -> 660 | G34: =Inputs!C7 -> 660 | H34: =C34 -> 737 | I34: =Inputs!C13 -> 730 | J34: =Inputs!C13 -> 730
B36: Stream | C36: CHV | D36: CWH | E36: CHV | F36: CHV | G36: CHV | H36: CHV | I36: CHV | J36: WCS
B37: Month | C37: =Inputs!$C$4 -> 45413 | D37: =Inputs!$C$4 -> 45413 | E37: =Inputs!$C$4 -> 45413 | F37: =Inputs!$C$4 -> 45413 | G37: =Inputs!$C$4 -> 45413 | H37: =Inputs!$C$4 -> 45413 | I37: =Inputs!$C$4 -> 45413 | J37: =Inputs!$C$4 -> 45413
B38: WTI (USD/BBL) | C38: =_xlfn.XLOOKUP(C$37, MonthlyData!$B:$B, MonthlyData!$D:$D) -> 78.62 | D38: =$C$38 -> 78.62 | E38: =$C$38 -> 78.62 | F38: =$C$38 -> 78.62 | G38: =$C$38 -> 78.62 | H38: =$C$38 -> 78.62 | I38: =$C$38 -> 78.62 | J38: =$C$38 -> 78.62
B39: WCS Diff (USD/BBL) | C39: 0 | D39: 0 | E39: 0 | F39: 0 | G39: 0 | H39: 0 | I39: 0 | J39: =_xlfn.XLOOKUP(C25, MonthlyData!$B:$B, MonthlyData!$AA:$AA) -> -13.07
B40: CHV Diff (USD/BBL) | C40: =_xlfn.XLOOKUP(C$37, MonthlyData!$B:$B, MonthlyData!$BP:$BP) -> -12.82 | D40: =C40 -> -12.82 | E40: =$C$40 -> -12.82 | F40: =$C$40 -> -12.82 | G40: =D40 -> -12.82 | H40: =C40 -> -12.82 | I40: =C40 -> -12.82 | J40: 0
B41: Premium/Discount (USD/BBL) | C41: 0 | D41: 0.15 | E41: 0 | F41: 0 | G41: 0 | H41: 0 | I41: 0 | J41: 0.4
B42: FX | C42: =_xlfn.XLOOKUP(C$37, MonthlyData!$B:$B, MonthlyData!$E:$E) -> 1.36695 | D42: =$C$42 -> 1.36695 | E42: =$C$42 -> 1.36695 | F42: =$C$42 -> 1.36695 | G42: =$C$42 -> 1.36695 | H42: =$C$42 -> 1.36695 | I42: =$C$42 -> 1.36695 | J42: =$C$42 -> 1.36695
B43: Reference Price | C43: =(C38+C39+C40+C41)*6.2898105*C42 -> 565.73896 | D43: =(D38+D39+D40+D41)*6.2898105*D42 -> 567.02863 | E43: =(E38+E39+E40+E41)*6.2898105*E42 -> 565.73896 | F43: =(F38+F39+F40+F41)*6.2898105*F42 -> 565.73896 | G43: =(G38+G39+G40+G41)*6.2898105*G42 -> 565.73896 | H43: =(H38+H39+H40+H41)*6.2898105*H42 -> 565.73896 | I43: =(I38+I39+I40+I41)*6.2898105*I42 -> 565.73896 | J43: =(J38+J39+J40+J41)*6.2898105*J42 -> 567.02863
B44: Terminal Fee (2025$) | C44: ='NipNorthTT Novacor Rainbow'!B47 -> -5 | D44: =-D106 -> -4.7 | E44: =-Inputs!C19 -> -5.25 | F44: =-Inputs!$C$20 -> -4.7 | G44: =-G106 -> -4.75 | H44: 0 | I44: =-H106 -> 0 | J44: =-I106 -> -5
B45: Raw Crude Trucking Cost | C45: =-(I15*'NipNorthTT Novacor Rainbow'!F8)/'NipNorthTT Novacor Rainbow'!F12 -> -9.7174148 | D45: =-(I17*'UtikuSouthTT DilFee Nipisi'!C101)/'UtikuSouthTT DilFee Nipisi'!C106 -> -14.76637 | E45: =-(I16*'UtikuNorthTT DilFee Nipisi'!C101)/'UtikuNorthTT DilFee Nipisi'!C106 -> -11.602148 | F45: =-(I18*'UtikuSouthTT DilFee Nipisi'!C101)/'UtikuSouthTT DilFee Nipisi'!C106 -> -14.76637 | G45: =-(I19*'KINGMitsueTT Dil Fee Nipisi'!C100)/'KINGMitsueTT Dil Fee Nipisi'!C105 -> -21.094814 | H45: =-(I20*'KingMH-Plains Novacor Rainbow'!B9)/'KingMH-Plains Novacor Rainbow'!F12 -> -27.208762 | I45: =-(I21*'Gibsons Novacor Edm'!B9)/'Gibsons Novacor Edm'!F12 -> -52.86423 | J45: =-(I22*'FlintHills Novacor Hardisty'!B9)/'FlintHills Novacor Hardisty'!F12 -> -67.20519
B46: Diluent Cost | C46: ='NipNorthTT Novacor Rainbow'!$B$63 -> -128.12669 | D46: ='UtikuSouthTT DilFee Nipisi'!$E$126 -> -77.204617 | E46: ='UtikuNorthTT DilFee Nipisi'!$E$126 -> -78.388939 | F46: ='UtikuSouthTT DilFee Nipisi'!$E$126 -> -77.204617 | G46: ='KINGMitsueTT Dil Fee Nipisi'!E125 -> -76.779193 | H46: ='KingMH-Plains Novacor Rainbow'!B63 -> -127.94047 | I46: ='Gibsons Novacor Edm'!B63 -> -121.39401 | J46: ='FlintHills Novacor Hardisty'!B63 -> -120.23161
B47: Financial Benefit from Physical Diluent Optimization | C47: 0 | D47: ='UtikuSouthTT DilFee Nipisi'!E136*0.9 -> 10.165685 | E47: ='UtikuNorthTT DilFee Nipisi'!E136*0.9 -> 9.4628539 | F47: =D47 -> 10.165685 | G47: ='KINGMitsueTT Dil Fee Nipisi'!E135*'KINGMitsueTT Dil Fee Nipisi'!E136 -> 9.4917691 | H47: 0 | I47: 0 | J47: 0
B48: TAN Blend Value | C48: 0 | D48: 0 | E48: 0 | F48: 0 | G48: 0 | H48: 0 | I48: 0 | J48: 0
B49: Linefill Cost | C49: =-(C117+C118) -> 0 | D49: =-(D117+D118) -> -1.23 | E49: =-($E$117+$E$118) -> -1 | F49: =-($F$117+$F$118) -> -0.8 | G49: =-(G117+G118) -> -0.8 | H49: ='KingMH-Plains Novacor Rainbow'!B49 -> -1.5784156 | I49: =-(H117+H118) -> 0 | J49: =-(I117+I118) -> 0
B50: Feeder P/L Tariff (2025$) | C50: =-C107 -> -19.078416 | D50: =-($D107+$D109+$D114) -> -16.76 | E50: =-($E$107+$E$108+$E$109+$E$110+$E$111+$E$112+$E$113+$E$114) -> -19.17 | F50: =-($F$107+$F$108+$F$109+$F$110+$F$111+$F$112+$F$113+$F$114) -> -18.5379 | G50: =-($G107+$G108+$G109+$G110+$F111+$G112+$G113+$G114) -> -17.57 | H50: =((P88*'KingMH-Plains Novacor Rainbow'!B9)/'KingMH-Plains Novacor Rainbow'!F12)+'KingMH-Plains Novacor Rainbow'!B48 -> -19.774792 | I50: 0 | J50: 0
B51: Infield Storage/Tank Costs (2025$) | C51: =-(C110+C111+C112+C113) -> 0 | D51: =-($D110+$D111+$D112+$D113) -> -1.96 | E51: =-($E$110+$E$111+$E$112+$E$113) -> 0 | F51: =-($E$110+$E$111+$E$112+$E$113) -> 0 | G51: =-(F110+F111+F112+F113) -> 0 | H51: =-(G110+G111+G112+G113) -> 0 | I51: =-(H110+H111+H112+H113) -> 0 | J51: =-(I110+I111+I112+I113) -> 0
B52: EDI/COLC | C52: =-(C115+C116) -> -0.11 | D52: =-(D115+D116) -> -0.11 | E52: =-($E$115+$E$116) -> -0.11 | F52: =-($E$115+$E$116) -> -0.11 | G52: =-(F115+F116) -> -0.11 | H52: =-(G115+G116) -> -0.11 | I52: =-(H115+H116) -> -0.11 | J52: =-(I115+I116) -> -0.11
B53: Pipeline L/A | C53: =-C43*Inputs!$C$27 -> -1.1314779 | D53: =-D119 -> -1.1370268 | E53: =-$E$119 -> -1.1370268 | F53: =-$E$119 -> -1.1370268 | G53: =-F119 -> -1.1370268 | H53: =-H43*Inputs!$C$27 -> -1.1314779 | I53: 0 | J53: 0
B54: Edm Storage L/A | C54: 0 | D54: =-D120 -> -0.1 | E54: 0 | F54: 0 | G54: 0 | H54: 0 | I54: 0 | J54: 0
B55: Netback (CAD/M3 Blend) | C55: =SUM(C43:C54) -> 402.57496 | D55: =SUM(D43:D54) -> 459.22631 | E55: =SUM(E43:E54) -> 458.5437 | F55: =SUM(F43:F54) -> 458.64873 | G55: =SUM(G43:G54) -> 452.98969 | H55: =SUM(H43:H54) -> 387.99504 | I55: =SUM(I43:I54) -> 391.37072 | J55: =SUM(J43:J54) -> 374.48183
B56: Netback (CAD/M3 Raw) | E56: =E55*'UtikuNorthTT DilFee Nipisi'!C106/'UtikuNorthTT DilFee Nipisi'!C101 -> 521.69452 | F56: =F55*'UtikuSouthTT DilFee Nipisi'!C106/'UtikuSouthTT DilFee Nipisi'!C101 -> 521.81402
B58: Netback Summary (CAD/M3 Blended Volume) | C58: The difference between the Netback Summary and the Model Summary of Physical Netback CAD per M3 Raw Crude, is that the Netback Summary includes the Raw Crude Trucking - from the point of reference - and the financial benefit for the purpose of comparison only and is not a true measure of the actual financial netback during ops. | L58: Utikuma Difference (CAD/M3)
B59: 45292 | C59: 283.99027 | D59: 335.29921 | E59: 334.4786 | F59: 334.74472 | G59: 329.25394 | H59: 269.8839 | I59: 273.54945 | J59: 265.89899 | L59: =F59-E59 -> 0.26612293
B60: 45323 | C60: =SUM(C46:C59) -> 538.11865 | D60: =SUM(D46:D59) -> 706.18956 | E60: =SUM(E46:E59) -> 1224.3737 | F60: =SUM(F46:F59) -> 1227.5836 | G60: =SUM(G46:G59) -> 695.33918 | H60: =SUM(H46:H59) -> 507.34377 | I60: =SUM(I46:I59) -> 543.41617 | J60: =SUM(J46:J59) -> 520.0392 | L60: =F60-E60 -> 3.2099049
B61: 45352 | C61: 341.29001 | D61: 400.1186 | E61: 399.28802 | F61: 399.55348 | G61: 394.151 | H61: 327.64094 | I61: 332.23779 | J61: 330.86137 | L61: =F61-E61 -> 0.26545686
B62: 45383 | C62: 406.85791 | D62: 471.27497 | E62: 470.46973 | F62: 470.69684 | G62: 465.08107 | H62: 392.7072 | I62: 397.18395 | J62: 378.37159 | L62: =F62-E62 -> 0.22710305
B63: 45413 | C63: 402.85783 | D63: 459.22631 | E63: 458.66008 | F63: 458.64873 | G63: 452.98969 | H63: 388.27791 | I63: 391.37072 | J63: 374.48183 | L63: =F63-E63 -> -0.011351112
B64: 45444 | C64: 427.53829 | D64: 479.79354 | E64: 479.26708 | F64: 479.21239 | G64: 473.29203 | H64: 411.97664 | I64: 413.61466 | J64: 394.49871 | L64: =F64-E64 -> -0.054693242
B65: 45474 | C65: 444.05979 | D65: 493.54346 | E65: 492.92786 | F65: 492.96207 | G65: 486.9024 | H65: 427.9297 | I65: 428.73228 | J65: 412.34267 | L65: =F65-E65 -> 0.034209624
B66: 45505 | C66: 385.65287 | D66: 432.5403 | E66: 431.89229 | F66: 431.96475 | G66: 426.12574 | H66: 370.10615 | I66: 371.6386 | J66: 358.93326 | L66: =F66-E66 -> 0.072458516
B67: 45536 | C67: 334.01017 | D67: 380.58714 | E67: 380.12448 | F67: 380.02095 | G67: 374.29123 | H67: 318.92537 | I67: 320.90866 | J67: 325.30428 | L67: =F67-E67 -> -0.10352254
B68: 45566 | C68: 342.88323 | D68: 396.59508 | E68: 396.01095 | F68: 396.00918 | G68: 390.29127 | H68: 328.12532 | I68: 331.08447 | J68: 329.4454 | L68: =F68-E68 -> -0.0017734632
B69: 45597 | C69: 341.64723 | D69: 396.67467 | E69: 396.0472 | F69: 396.06817 | G69: 390.46223 | H69: 327.27467 | I69: 330.61301 | J69: 323.69023 | L69: =F69-E69 -> 0.020967684
B70: 45627 | C70: 346.95737 | D70: 404.2688 | E70: 403.56684 | F70: 403.63733 | G70: 398.06399 | H70: 332.76233 | I70: 336.23262 | J70: 320.17101 | L70: =F70-E70 -> 0.070495092
B72: HWX Marten Hills | C72: 45292 | D72: 45323 | E72: 44986 | F72: 45383 | G72: 45413 | H72: 45444 | I72: 45474 | J72: 45505 | K72: 45170 | L72: 45200 | M72: 45231 | N72: 45261 | O72: 2024 | P72: 2025
B73: Raw Crude Volume (M3/M)
B74: Condensate Volume (M3/M)
B75: C4 Volume (M3/M)
B76: Shrinkage
B77: Total
B79: C4 Transportation
B81: ENB C5+ Tariff (CAD/M3) | C81: -2.91 | D81: -2.91 | E81: -2.91 | F81: -2.91 | G81: -2.91 | H81: -2.91 | I81: -2.91 | J81: -2.91 | K81: -2.91 | L81: -2.91 | M81: -2.91 | N81: -2.91 | O81: =N81*1.02 -> -2.9682 | P81: =O81*1.02 -> -3.027564
B82: ENB C5+ Tank Fee (CAD/M3) | C82: -0.43 | D82: -0.43 | E82: -0.43 | F82: -0.43 | G82: -0.43 | H82: -0.43 | I82: -0.43 | J82: -0.43 | K82: -0.43 | L82: -0.43 | M82: -0.43 | N82: -0.43 | O82: =N82*1.02 -> -0.4386 | P82: =O82*1.02 -> -0.447372
B84: PMC RP2 Tariff (CAD/M3) | C84: -15.74 | D84: -15.74 | E84: -15.74 | F84: -15.74 | G84: -15.74 | H84: -15.74 | I84: -15.74 | J84: -15.74 | K84: -15.74 | L84: -15.74 | M84: -15.74 | N84: -15.74 | O84: =N84*1.025 -> -16.1335 | P84: =O84*1.025 -> -16.536837
B85: PMC RP2 L/A (CAD/M3) - 0.15% | C85: 0 | D85: 0 | E85: 0 | F85: 0 | G85: 0 | H85: 0 | I85: 0 | J85: 0 | K85: 0 | L85: 0 | M85: 0 | N85: 0
B86: PMC Rebate | C86: 5.16 | D86: 5.16 | E86: 5.16 | F86: 5.16 | G86: 5.16 | H86: 5.16 | I86: 5.16 | J86: 5.16 | K86: 5.16 | L86: 5.16 | M86: 5.16 | N86: 5.16
B88: Marten Hills Blend Tariff (CAD/M3) | C88: -9.35 | D88: -9.35 | E88: -9.35 | F88: -9.35 | G88: -9.35 | H88: -9.35 | I88: -9.35 | J88: -9.35 | K88: -9.35 | L88: -9.35 | M88: -9.35 | N88: -9.35 | O88: =N88*1.025 -> -9.58375 | P88: =O88*1.025 -> -9.8233437 | R88: 2% increase Y/Y
B89: Marten Hills C5 Tariff (CAD/M3) | C89: -21.58 | D89: -21.58 | E89: -21.58 | F89: -21.58 | G89: -21.58 | H89: -21.58 | I89: -21.58 | J89: -21.58 | K89: -21.58 | L89: -21.58 | M89: -21.58 | N89: -21.58 | R89: Assume no C5
B90: Marten Hills L/A (CAD/M3) - 0.2% | C90: -0.9 | D90: -0.97 | E90: -0.9 | F90: -1.17 | G90: -1.12 | H90: -1.15 | I90: -1.16 | J90: -1.05 | K90: -1.05 | L90: -1.15 | M90: -1.15 | N90: -0.76 | O90: =AVERAGE(C90:N90) -> -1.0441667 | P90: =AVERAGE(D90:O90) -> -1.0561806
B92: PMC Rainbow Blend Tariff (CAD/M3) 2.25% increase Y/Y | C92: -11.25 | D92: -11.25 | E92: -11.25 | F92: -11.25 | G92: -11.25 | H92: -11.25 | I92: -11.25 | J92: -11.25 | K92: -11.25 | L92: -11.25 | M92: -11.25 | N92: -11.25 | O92: =N92*1.025 -> -11.53125 | P92: =O92*1.025 -> -11.819531 | R92: 2.25% increase Y/Y
B93: PMC Rainbow L/A (CAD/M3) - 0.15% | C93: -0.67 | D93: -0.73 | E93: -0.67 | F93: -0.88 | G93: -0.84 | H93: -0.86 | I93: -0.87 | J93: -0.78 | K93: -0.78 | L93: -0.86 | M93: -0.86 | N93: -0.57 | O93: =AVERAGE(C93:N93) -> -0.78083333
B95: Net Benefit (CAD/M3 Blend) | C95: 6.7 | D95: 6.68 | E95: 8.48 | F95: 8.36 | G95: 7.12 | H95: 4.7 | I95: 3.71 | J95: 2.75 | K95: 2.75 | L95: 2.85 | M95: 2.85 | N95: 7.14 | O95: =AVERAGE(C95:N95) -> 5.3408333 | R95: Average annual Benefit to HWX
B96: Gross Benefit (CAD/M3 Blend) | C96: =C95/0.75 -> 8.9333333 | D96: =D95/0.75 -> 8.9066667 | E96: =E95/0.75 -> 11.306667 | F96: =F95/0.75 -> 11.146667 | G96: =G95/0.75 -> 9.4933333 | H96: =H95/0.75 -> 6.2666667 | I96: =I95/0.75 -> 4.9466667 | J96: =J95/0.75 -> 3.6666667 | ... N96: =N95/0.75 -> 9.52 | O96: =AVERAGE(C96:N96) -> 7.1211111
B98: Total Transportation | C98: =C88+C90+C92+C93+C95 -> -15.47 | D98: =D88+D90+D92+D93+D95 -> -15.62 | E98: =E88+E90+E92+E93+E95 -> -13.69 | F98: =F88+F90+F92+F93+F95 -> -14.29 | G98: =G88+G90+G92+G93+G95 -> -15.44 | H98: =H88+H90+H92+H93+H95 -> -17.91 | I98: =I88+I90+I92+I93+I95 -> -18.92 | J98: =J88+J90+J92+J93+J95 -> -19.68 | ... N98: =N88+N90+N92+N93+N95 -> -14.79 | O98: =AVERAGE(C98:N98) -> -17.084167 | R98: Annualized | X98: Actual Blended Crude Density (Actual Blend Target)
W99: Customer Producers | X99: 45200 | Y99: 45231 | Z99: 45261 | AA99: 45292 | AB99: 45323 | AC99: 45352 | AD99: 45383 | AE99: 45413 | AF99: 45444 | AG99: 45474 | AH99: 45505 | AI99: 45536 | AJ99: 45566 | AK99: 45597 | AL99: 45627 | AM99: 45658 | AN99: 45689 | AO99: 45717 | AP99: 45748 | AQ99: 45778
B100: Blend Density (Marten Hills) | C100: 925.2 | D100: 925.6 | E100: 936.4 | F100: 925.9 | G100: 926.1 | H100: 926.1 | I100: 926 | J100: 925.4 | K100: 927.6 | L100: 926.4 | M100: 926.2 | N100: 926.1 | O100: =AVERAGE(C100:N100) -> 926.91667 | W100: Spur | X100: 924.7 | Y100: 922.7 | Z100: 921.6 | AA100: 920.6 | AB100: 921.7 | AC100: 918.4 | AD100: 921.6 | AE100: 924.2 | AF100: 930.1 | AG100: 936.4 | AH100: 929.4 | AI100: 928.7 | AJ100: 929.6 | AK100: 924.2 | AL100: 921.8 | AM100: 921.2 | AN100: 920.2 | AO100: 920.3 | AP100: 921.4 | AQ100: 924.3
W101: Tamarack
W102: Obsidian
W103: Baytex
B104: Transportation Charges Summary | C104: =C27 -> Nipisi North Truck Terminal (Rainbow P/L) | D104: =D27 -> Nipisi South Truck Terminal (Nipisi P/L) | E104: =E27 -> Utikuma North Truck Terminal (Nipisi P/L) | F104: =F27 -> Utikuma South Truck Terminal (Nipisi P/L) | G104: =G27 -> Mitsue Truck Terminal (Nipisi P/L) | H104: =H27 -> Marten Hills P/L (Rainbow P/L) | I104: =I27 -> Gibsons Edmonton (CHV Pricing) | J104: =J27 -> Flint Hills Hardisty (WCS Pricing) | W104: Headwater
B105: Nipisi Pipeline Charges | C105: CAD/M3 | D105: CAD/M3 | E105: CAD/M3 | F105: CAD/M3 | G105: CAD/M3 | H105: CAD/M3 | I105: CAD/M3 | J105: CAD/M3
B106: Terminal Fee (2025$) | C106: =-'NipNorthTT Novacor Rainbow'!B47 -> 5 | D106: 4.7 | E106: =Inputs!$C$19 -> 5.25 | F106: =Inputs!$C$20 -> 4.7 | G106: 4.75 | H106: ='KingMH-Plains Novacor Rainbow'!B47 -> 0 | I106: 5 | J106: 2.5
B107: Mainline Toll (2025$) | C107: =-('NipNorthTT Novacor Rainbow'!B48+'NipNorthTT Novacor Rainbow'!B49) -> 19.078416 | D107: 14.59 | E107: 18 | F107: 17.5 | G107: 16.6 | H107: =-('KingMH-Plains Novacor Rainbow'!B48+'KingMH-Plains Novacor Rainbow'!B49) -> 13.398416 | I107: 0 | J107: 0
B108: DRA Surcharge | C108: 0 | D108: 0 | E108: 0 | F108: 0 | G108: 0 | H108: 0 | I108: 0 | J108: 0
B109: Mainline Surcharge | C109: 0 | D109: 1.1 | E109: 0 | F109: 0 | G109: 0 | H109: 0 | I109: 0 | J109: 0
B110: N40 Surcharge | C110: 0 | D110: 0.98 | E110: 0 | F110: 0 | G110: 0 | H110: 0 | I110: 0 | J110: 0
B111: N40 Fee | C111: 0 | D111: 0.86 | E111: 0 | F111: 0 | G111: 0 | H111: 0 | I111: 0 | J111: 0
B112: N40 Additional | C112: 0 | D112: 0 | E112: 0 | F112: 0 | G112: 0 | H112: 0 | I112: 0 | J112: 0
B113: N40 Tank Bottoms | C113: 0 | D113: 0.12 | E113: 0 | F113: 0 | G113: 0 | H113: 0 | I113: 0 | J113: 0
B114: VOF (Power+Extra) | C114: 0 | D114: 1.07 | E114: =D114+Inputs!C21 -> 1.17 | F114: =D114*0.97 -> 1.0379 | G114: =D114-0.1 -> 0.97 | H114: 0 | I114: 0 | J114: 0
...

Sheet NipNorthTT Novacor Rainbow
A3: NOVACOR: Condensate Addition & Shrinkage Calculations
F7: RESULTS | J7: Rainbow SW (Interface) | K7: RP2 C5+ | L7: CHV
A8: Date | B8: ='Spur-Netback'!C37 -> 45413 | E8: Volume of Dry Crude = | F8: =B9 -> 21147 | G8: m3 | I8: Density (KG/M3) | J8: 815 | K8: =Inputs!C14 -> 737 | L8: =Inputs!C18 -> 924.4
A9: Volume of Raw Crude = | B9: =Inputs!C5 -> 21147 | C9: M3 | E9: % C5+ in Total Blend (Fc) = | F9: =B36 -> 19.324663 | G9: % | I9: Sulfur (%Swt) | J9: 0.35 | K9: 0.1 | L9: 4
A10: Density of Raw Crude = | B10: =Inputs!C16 -> 965 | C10: KG/M3 | E10: Condensate Required in Blend= | F10: =((F9/100)*B9)/(1-F9/100) -> 5065.4719 | G10: m3 | I10: WTI (USD/BBL) | J10: =_xlfn.XLOOKUP($B$8,MonthlyData!$B:$B,MonthlyData!$D:$D) -> 78.62 | K10: =J10 -> 78.62 | L10: =J10 -> 78.62
A11: Density of Condensate (RP2 C5+) = | B11: =K8 -> 737 | C11: KG/M3 | E11: Shrinkage Volume = | F11: =(B9+F10)*B37/100 -> 98.119075 | G11: m3 | I11: FX (CAD/USD) | J11: =_xlfn.XLOOKUP($B$8,MonthlyData!$B:$B,MonthlyData!$E:$E) -> 1.36695 | K11: =J11 -> 1.36695 | L11: =K11 -> 1.36695
A12: Density of Target Blend = | B12: =L8 -> 924.4 | C12: KG/M3 | E12: Volume of Blend = | F12: =B9+F10-F11 -> 26114.353 | G12: m3 | I12: Diff (USD/BBL) | J12: =_xlfn.XLOOKUP($B$8,MonthlyData!$B:$B,MonthlyData!$F:$F) -> -3.78 | K12: =_xlfn.XLOOKUP($B$8,MonthlyData!$B:$B,MonthlyData!$M:$M) -> -4.19 | L12: =_xlfn.XLOOKUP($B$8,MonthlyData!$B:$B,MonthlyData!$BP:$BP) -> -12.82
I13: WADF (CAD/M3) | J13: =_xlfn.XLOOKUP($B$8,MonthlyData!$B:$B,MonthlyData!$G:$G) -> 0.015 | K13: =_xlfn.XLOOKUP($B$8,MonthlyData!$B:$B,MonthlyData!$X:$X) -> -4.27 | L13: 0
A14: Raw Crude Density - as measured by Producer or at Truck Unload or Oil Analysis. | I14: Ref Price | J14: =J13+(J10+J12)*6.29287*J11 -> 643.79157 | K14: =K13+(K10+K12)*6.29287*K11 -> 635.97974 | L14: =L13+(L10+L12)*6.2898105*L11 -> 565.73896
A15: Condensate Density - as reported by CM or Plains or Producer/Customer deliveries in the delivery month. | E15: Apparent Condensate | F15: =F10-F11 -> 4967.3529 | I15: EQ | J15: =IF(J8>825,(825-J8)*0.49,IF(J8<800,(J8-800)*0.49,0))+(0.5-J9)*13.8 -> 2.07 | K15: =(750-K8)*$B$18+(0.2-$K$9)*13.8 -> 3.59 | L15: 0
A16: Target Blend Density - CHV density, as reported by CM or Plains or Producer/Customer, in the delivery month | E16: Shrinkage as: %C5+ | F16: =F11/F10*100 -> 1.9370174 | I16: Tariff on Purchase
E17: Shrinkage as: %Blend | F17: =(F19-F12)/F19*100 -> 0.3743221 | I17: Trucking on Purchase
A18: C5 Density Slope | B18: =_xlfn.XLOOKUP($B$8,MonthlyData!$B:$B,MonthlyData!$Y:$Y) -> 0.17 | E18: Shrinkage as: % Shrunk Blend | F18: =(F19-F12)/F12*100 -> 0.37572853 | I18: Other
A19: Rainbow Interface % | B19: 0.0197 | E19: vol blend w/o shrinkage | F19: =F8+F10 -> 26212.472 | I19: Netback | J19: =SUM(J14:J18) -> 645.86157 | K19: =SUM(K14:K18) -> 639.56974 | L19: =SUM(L14:L18) -> 565.73896
E20: C5+ as % of dry crude | F20: =F10/F8*100 -> 23.95362
E21: C5+ as % of blend | F21: =F10/F12*100 -> 19.397272
A24: NovaCor Eqn
A25: ITERATIONS: | D25: vol C5+ | E25: Density Blend
A26: % C5+ in Total Blend (Fc) = | B26: =((B10-B12)/(B10-B11))*100 -> 17.807018 | C26: % | D26: =(B26/100*$B$9)/(1-B26/100) -> 4581.4739 | E26: =(D26*$B$11+$B$9*$B$10)/(D26+$B$9)/(1-B27/100) -> 927.68764
A27: Blend Shrinkage Factor (Sf) = | B27: =(0.0266*B26)-(0.0004*(POWER(B26,2)))+(0.000001339*(POWER(B26,3))) -> 0.35439128 | C27: % | D27: =(B9/(1-B26/100))*(B26/100) -> 4581.4739
A28: % C5+ in Total Blend (Fc) = | B28: =(((($B$10-$B$12)/($B$10-$B$11))+((B27/100)*$B$12)/($B$10-$B$11)))*100 -> 19.243857 | C28: % | D28: =(B28/100*$B$9)/(1-B28/100) -> 5039.2431 | E28: =(D28*$B$11+$B$9*$B$10)/(D28+$B$9)/(1-B29/100) -> 924.57543
A29: Blend Shrinkage Factor (Sf) = | B29: =(0.0266*B28)-(0.0004*(POWER(B28,2)))+(0.000001339*(POWER(B28,3))) -> 0.37329856 | C29: %
A30: % C5+ in Total Blend (Fc) = | B30: =(((($B$10-$B$12)/($B$10-$B$11))+((B29/100)*$B$12)/($B$10-$B$11)))*100 -> 19.320514 | C30: % | D30: =(B30/100*$B$9)/(1-B30/100) -> 5064.1239 | E30: =(D30*$B$11+$B$9*$B$10)/(D30+$B$9)/(1-B31/100) -> 924.40901
A31: Blend Shrinkage Factor (Sf) = | B31: =(0.0266*B30)-(0.0004*(POWER(B30,2)))+(0.000001339*(POWER(B30,3))) -> 0.37426964 | C31: %
A32: % C5+ in Total Blend (Fc) = | B32: =(((($B$10-$B$12)/($B$10-$B$11))+((B31/100)*$B$12)/($B$10-$B$11)))*100 -> 19.324451 | C32: % | D32: =(B32/100*$B$9)/(1-B32/100) -> 5065.403 | E32: =(D32*$B$11+$B$9*$B$10)/(D32+$B$9)/(1-B33/100) -> 924.40046
A33: Blend Shrinkage Factor (Sf) = | B33: =(0.0266*B32)-(0.0004*(POWER(B32,2)))+(0.000001339*(POWER(B32,3))) -> 0.37431942 | C33: %
A34: % C5+ in Total Blend (Fc) = | B34: =(((($B$10-$B$12)/($B$10-$B$11))+((B33/100)*$B$12)/($B$10-$B$11)))*100 -> 19.324653 | C34: % | D34: =(B34/100*$B$9)/(1-B34/100) -> 5065.4686 | E34: =(D34*$B$11+$B$9*$B$10)/(D34+$B$9)/(1-B35/100) -> 924.40002
A35: Blend Shrinkage Factor (Sf) = | B35: =(0.0266*B34)-(0.0004*(POWER(B34,2)))+(0.000001339*(POWER(B34,3))) -> 0.37432197 | C35: %
A36: % C5+ in Total Blend (Fc) = | B36: =(((($B$10-$B$12)/($B$10-$B$11))+((B35/100)*$B$12)/($B$10-$B$11)))*100 -> 19.324663 | C36: % | D36: =(B36/100*$B$9)/(1-B36/100) -> 5065.4719 | E36: =(D36*$B$11+$B$9*$B$10)/(D36+$B$9)/(1-B37/100) -> 924.4
A37: Blend Shrinkage Factor (Sf) = | B37: =(0.0266*B36)-(0.0004*(POWER(B36,2)))+(0.000001339*(POWER(B36,3))) -> 0.3743221 | C37: %
A39: Pricing | E39: =1/1.3378 -> 0.74749589
A41: Condensate price @ Edmonton | B41: =$K$19 -> 639.56974 | C41: CAD/M3
A42: C5 RP2 Edm-Nipisi Toll: | B42: 17.5 | C42: CAD/M3
A43: C5 ENB/PMC Terminalling | B43: 3.47 | C43: CAD/M3
A44: Total Condensate price: | B44: =SUM(B41:B43) -> 660.53974 | C44: CAD/M3
A46: CHV Price (Edmonton) | B46: =$L$19 -> 565.73896 | C46: CAD/M3
A47: Rainbow Pipeline Terminal Fee | B47: -5 | C47: CAD/M3
A48: Rainbow Pipeline Tariff | B48: -17.5 | C48: CAD/M3
A49: Rainbow Inferface Fee | B49: =($L$19-$J$19)*$B$19 -> -1.5784156 | C49: CAD/M3
A50: Heavy Blend in Rainbow Nipisi Storage | B50: =SUM(B46:B49) -> 541.66054 | C50: CAD/M3
A52: Value of Heavy Blend: | B52: =B50*F12 -> 14145114 | C52: CAD | D52: =+B50*(F11/B9) -> 2.5132279 | E52: Shrinkage
A53: Value of Condensate: | B53: =F10*B44 -> 3345945.5 | C53: CAD | D53: =+(B44-B50)*F10/F8 -> 28.475871 | E53: Cond
A54: Value of Raw Crude | B54: =(B52-B53)/B9 -> 510.67144 | C54: CAD/M3
A55: Rainbow Loss Allowance | B55: =-0.15%*B46 -> -0.84860843 | C55: CAD/M3
A57: Raw Heavy Price | B57: =SUM(B54:B55) -> 509.82283 | C57: CAD/M3
B58: =B57/6.29287/$J$11 -> 59.267675 | C58: USD/BBL
B59: =B58-$J$10 -> -19.352325 | C59: Diff to WTI
A61: Diluent Fee per M3 of Raw Crude | B61: =-(B46-(B57-B49-B48-B47-B55)) -> -30.989098 | C61: CAD/M3
A62: Diluent Fee per M3 of Blended Crude | B62: =(B61*F8)/F12 -> -25.094494 | C62: CAD/M3
A63: Diluent Cost per M3 of Blended Crude | B63: =-(B44*F10)/F12 -> -128.12669 | C63: CAD/M3

Sheet UtikuNorthTT DilFee Nipisi
A1: Diluent Optimization Benefit - ESTIMATED (NO CRUDE VISCOSITY DATA)
A4: PRICING ASSUMPTIONS: | C4: WADF | D4: PAR | E4: STREAM
A5: MONTH: | B5: ='Spur-Netback'!C37 -> 45413 | C5: $Cdn/m3 | D5: $Cdn/m3 | E5: $Cdn/m3 | G5: =B5 -> 45413 | H5: CONDENSATE EQ: | I5: $/m3 | J5: C4 Content | K5: Penalty $/m3 | L5: Penalty $/m3 /.1%
A6: WTI: | B6: =_xlfn.XLOOKUP($B$5,MonthlyData!$B:$B,MonthlyData!$D:$D) -> 78.62 | H6: C5+ Allow Price | I6: =_xlfn.XLOOKUP($B$5,MonthlyData!$B:$B,MonthlyData!$Z:$Z) -> 636.91 | J6: <=5.0% | K6: 0 | L6: 0
A7: FX: | B7: =_xlfn.XLOOKUP($B$5,MonthlyData!$B:$B,MonthlyData!$E:$E) -> 1.36695 | H7: Butane Price | I7: 0 | J7: >5.0%-7.0% | K7: =ROUND(I6-I8,2) -> 636.91 | L7: =ROUND(K7/1000,6) -> 0.63691
A8: CHV INDEX ($US/bbl): | B8: =_xlfn.XLOOKUP($B$5,MonthlyData!$B:$B,MonthlyData!$BP:$BP) -> -12.82 | E8: =(B6+B8)*6.2898105*B7 -> 565.73896 | H8: 50% of Butane Value | I8: =ROUND(I7/2,2) -> 0 | J8: > 7.0% | K8: =ROUND(I6,2) -> 636.91 | L8: =ROUND(K8/1000,6) -> 0.63691
A9: C5+ INDEX ($US/bbl): | B9: =_xlfn.XLOOKUP($B$5,MonthlyData!$B:$B,MonthlyData!$M:$M) -> -4.19 | C9: =_xlfn.XLOOKUP($B$5,MonthlyData!$B:$B,MonthlyData!$X:$X) -> -4.27 | D9: =(($B$6+B9)*6.29287*$B$7)+C9 -> 635.97974 | E9: =D9-C9 -> 640.24974 | H9: Density Slope (C5+) | I9: =_xlfn.XLOOKUP($B$5,MonthlyData!$B:$B,MonthlyData!$Y:$Y) -> 0.17 | J9: $ / m3 per kg / m3 | L9: 750 kg/m3
A10: C4 Price %WTI (Landed): | B10: =_xlfn.XLOOKUP($B$5,MonthlyData!$B:$B,MonthlyData!$AM:$AM)*Inputs!C28 -> 0.5225 | E10: =(B6*B10)*6.29287*B7+D10 -> 353.36272 | H10: Sulphur | I10: =I13 -> 1.38 | J10: $ / m3 per .1 wt% | L10: .2% wt
A11: \ | B11: =B10 -> 0.5225 | H11: CRUDE (INDUSTRY) EQ:
A12: C4 Diff: | B12: =1-B11 -> 0.4775 | C12: (1 - 62.4%) | H12: Density Slope (Crude) | I12: 0.49 | J12: $ / m3 per kg / m3 | K12: Heavy Allow Price: | L12: =_xlfn.XLOOKUP($B$5,MonthlyData!$B:$B,MonthlyData!$AE:$AE) -> 0
A13: C4 Purchase Price ($US/bbl): | B13: =B6*B11 -> 41.07895 | H13: Sulphur | I13: 1.38 | J13: $ / m3 per .1 wt% | K13: Enb. Ref Temp: | L13: =_xlfn.XLOOKUP($B$5,MonthlyData!$B:$B,MonthlyData!$AF:$AF) -> 0
A14: C4 Diff to WTI ($US/bbl): | B14: =B13-B6 -> -37.54105 | D14: C4 vs. C5+: | E14: =E10-I15 -> -304.94495 | H14: Calculated EQ CREDIT: | I14: =(750-$L$14)*$I$9+(0.2-$L$15)*$I$10*10 -> 18.05793 | K14: C5+ Density: | L14: =Inputs!C7 -> 660
H15: C5+ Price after EQ: | I15: =E9+I14 -> 658.30767 | K15: C5+ Sulfur: | L15: =Inputs!C8 -> 0.00015
A18: Condensate Only - Paper Blend | N18: SCENARIO #1 - IF C5+ ONLY:
A19: API 12.3 Sec.5.3
B20: TEMP CORR. VOLUMES & DENSITY INPUTS | H20: RESULTS | O20: Value | R20: Result
B21: m3 | C21: Dens @ 15C | D21: % of Blend | H21: Shrinkage Percent | I21: SHRINKAGE | J21: Sum of Volumes | K21: Resultant Volume | N21: Raw Heavy Volume | O21: =B22 -> 21147 | Q21: Raw (m3) | R21: =O32 -> 21147
A22: RAW CRUDE OIL: | B22: =Inputs!C5 -> 21147 | C22: =Inputs!C16 -> 965 | D22: =B22/B26 -> 0.86688525 | H22: % | I22: m3 | N22: Raw Heavy Density | O22: =C22 -> 965 | Q22: C5 (m3) | R22: =SUM(O34:S34) -> 3666.2356
A23: Butane: | B23: 0 | C23: 575 | D23: =B23/B26 -> 0 | H23: =IFERROR(26900*F36*(100-F36)^0.819*(I36-J36)^2.28,0) -> 0 | I23: =IFERROR(H23/100*(B36+D36),0) -> 0 | J23: =B36+D36 -> 21147 | K23: =B36+D36-I23 -> 21147 | N23: C5 Density | O23: =C24 -> 660 | Q23: Delivered (m3) | R23: =S40 -> 24693.378
A24: Condensate: | B24: =(C22-B28)/(B28-C24)*B22 -> 3247.2322 | C24: =L14 -> 660 | D24: =B24/B26 -> 0.13311475 | H24: =IFERROR(26900*F37*(100-F37)^0.819*(I37-J37)^2.28,0) -> 0.3733277 | I24: =IFERROR(H24/100*(B37+D37),0) -> 91.070427 | J24: =B37+D37 -> 24394.232 | K24: =B37+D37-I24 -> 24303.162 | N24: Target Density | O24: =B28 -> 924.4 | Q24: Shrinkage (m3) | R24: =R23-SUM(R21:R22) -> -119.8572
H25: =IFERROR(26900*F38*(100-F38)^0.819*(I38-J38)^2.28,0) -> 0 | I25: =IFERROR(H25/100*(B38+D38),0) -> 0 | J25: =B38+D38 -> 24303.162 | K25: =B38+D38-I25 -> 24303.162
A26: Total Receipts: | B26: =SUM(B22:B25) -> 24394.232 | D26: =SUM(D22:D25) -> 1 | H26: =IF(I26=0,"",(I26/K26)) -> 0.0037472666 | I26: =(SUM(I23:I25))*1 -> 91.070427 | K26: =K25 -> 24303.162 | N26: API 12.3 Heavy Oil Adjusted
A27: Wt.Avg. Kg/m3: | B27: =SUMPRODUCT(B22:B25,C22:C25)/SUM(B22:B25) -> 924.4 | J27: Total Receipts: | K27: =B26 -> 24394.232 | O27: Iteration 1 | P27: Iteration 2 | Q27: Iteration 3 | R27: Iteration 4 | S27: Iteration 5
A28: Target Density | B28: =Inputs!C18 -> 924.4 | J28: Total Shrinkage: | K28: =I26*-1 -> -91.070427 | N28: Target Density | O28: =$B$28 -> 924.4 | P28: =O28 -> 924.4 | Q28: =P28 -> 924.4 | R28: =Q28 -> 924.4 | S28: =R28 -> 924.4
B29: =D49 -> 924.4 | J29: Net Volume: | K29: =K27+K28 -> 24303.162 | N29: Diluent Density | O29: =$C$24 -> 660 | P29: =O29 -> 660 | Q29: =P29 -> 660 | R29: =Q29 -> 660 | S29: =R29 -> 660
J30: Total Shrinkage as % of Total Receipts: | K30: =I26/B26 -> 0.003733277 | N30: Raw Crude Density | O30: =$C$22 -> 965 | P30: =O41 -> 928.48481 | Q30: =P41 -> 924.82147 | R30: =Q41 -> 924.44359 | S30: =R41 -> 924.40451
A31: API 12.3 Sec.5.3
A32: --- Linked to INPUT values above --- | N32: Raw Heavy Volume (m3) | O32: =$B$22 -> 21147 | P32: =O40 -> 24286.911 | Q32: =P40 -> 24650.889 | R32: =Q40 -> 24689.02 | S32: =R40 -> 24692.97
B33: LIGHT | D33: RAW CRUDE OIL | N33: Raw Heavy Mass (kg) | O33: =O32*O30 -> 20406855 | P33: =P32*P30 -> 22550028 | Q33: =Q32*Q30 -> 22797672 | R33: =R32*R30 -> 22823606 | S33: =S32*S30 -> 22826293
B34: Diluent Volume | C34: Average Density | D34: Volume | E34: Average Density | F34: X = DILUENT Volume/(Crude Volume + DILUENT Volume) | G34: XX = CRUDE Volume/(CRUDE Volume + Diluent Volume) | H34: CRUDE + DILUENT BLEND | I34: 1/dL | J34: 1/dH | N34: Diluent Required (m3) | O34: =(O28*O32-O30*O32)/(O29-O28) -> 3247.2322 | P34: =(P28*P32-P30*P32)/(P29-P28) -> 375.21729 | Q34: =(Q28*Q32-Q30*Q32)/(Q29-Q28) -> 39.295037 | R34: =(R28*R32-R30*R32)/(R29-R28) -> 4.0699587 | S34: =(S28*S32-S30*S32)/(S29-S28) -> 0.42105704
B35: m3 | C35: kg/m3 | D35: m3 | E35: kg/m3 | F35: % | G35: % | H35: % | N35: Diluent Mass (kg) | O35: =O34*O29 -> 2143173.3 | P35: =P34*P29 -> 247643.41 | Q35: =Q34*Q29 -> 25934.725 | R35: =R34*R29 -> 2686.1728 | S35: =S34*S29 -> 277.89765
A36: Butane: | B36: =B23 -> 0 | C36: =C23 -> 575 | D36: =B22 -> 21147 | E36: =C22 -> 965 | F36: =IFERROR(B36/(B36+D36)*100,"") -> 0 | G36: =IFERROR(D36/(B36+D36)*100,"") -> 100 | H36: =F36+G36 -> 100 | I36: =IFERROR(1/C36,"") -> 0.0017391304 | J36: =IFERROR(1/E36,"") -> 0.0010362694
A37: Condensate: | B37: =B24 -> 3247.2322 | C37: =C24 -> 660 | D37: =K23 -> 21147 | E37: =E36 -> 965 | F37: =IFERROR(B37/(B37+D37)*100,"") -> 13.311475 | G37: =IFERROR(D37/(B37+D37)*100,"") -> 86.688525 | H37: =F37+G37 -> 100 | I37: =IFERROR(1/C37,"") -> 0.0015151515 | J37: =IFERROR(1/E37,"") -> 0.0010362694 | N37: Diluent as % of Blend | O37: =O34/(O32+O34) -> 0.13311475 | P37: =P34/(P32+P34) -> 0.015214311 | Q37: =Q34/(Q32+Q34) -> 0.0015915247 | R37: =R34/(R32+R34) -> 0.00016482177 | S37: =S34/(S32+S34) -> 1.7051406e-05
A38: OIL: | B38: =K24 -> 24303.162 | C38: =E37 -> 965 | D38: =B25 -> 0 | E38: =C25 -> 0 | F38: =IFERROR(B38/(B38+D38)*100,"") -> 100 | G38: =IFERROR(D38/(B38+D38)*100,"") -> 0 | H38: =F38+G38 -> 100 | I38: =IFERROR(1/C38,"") -> 0.0010362694 | J38: =IFERROR(1/E38,"") | N38: Shrinkage as % of Blend | O38: =31700*O37*(100-O37*100)^0.819*(1/O29-1/O30)^2.28 -> 0.004399438 | P38: =31700*P37*(100-P37*100)^0.819*(1/P29-1/P30)^2.28 -> 0.0004557311 | Q38: =31700*Q37*(100-Q37*100)^0.819*(1/Q29-1/Q30)^2.28 -> 4.7148425e-05 | R38: =31700*R37*(100-R37*100)^0.819*(1/R29-1/R30)^2.28 -> 4.87716e-06 | S38: =31700*S37*(100-S37*100)^0.819*(1/S29-1/S30)^2.28 -> 5.0449949e-07
A39: dL | B39: = Density of Light | N39: Shrinkage (m3) | O39: =-O38*(O32+O34) -> -107.32091 | P39: =-P38*(P32+P34) -> -11.239299 | Q39: =-Q38*(Q32+Q34) -> -1.1641033 | R39: =-R38*(R32+R34) -> -0.12043215 | S39: =-S38*(S32+S34) -> -0.012457803
A40: dH | B40: = Density of Heavy | N40: Volume After Shrinkage | O40: =O32+O34+O39 -> 24286.911 | P40: =P32+P34+P39 -> 24650.889 | Q40: =Q32+Q34+Q39 -> 24689.02 | R40: =R32+R34+R39 -> 24692.97 | S40: =S32+S34+S39 -> 24693.378
A41: X | B41: = % concentraion of Diluent. (i.e., Diluent percentage of total blend). | N41: Density After Shrinkage | O41: =(O33+O35)/O40 -> 928.48481 | P41: =(P33+P35)/P40 -> 924.82147 | Q41: =(Q33+Q35)/Q40 -> 924.44359 | R41: =(R33+R35)/R40 -> 924.40451 | S41: =(S33+S35)/S40 -> 924.40047
A42: XX | B42: = % concentraion of Crude. (i.e., Crude percentage of total blend).
A44: Condensate Only - Net Sales Calculation | N44: SCENARIO #1 - FINANCIAL RESULTS:
C45: m3 | D45: kg/m3 | E45: % Inject | F45: % of Blend | P45: m3 | Q45: kg/m3 | R45: % Inject | S45: % of Blend
B46: Raw Crude: | C46: =$B$22 -> 21147 | D46: =$C$22 -> 965 | F46: =C46/C49 -> 0.86688525 | O46: Raw Crude: | P46: =$B$22 -> 21147 | Q46: =$C$22 -> 965 | S46: =P46/P49 -> 0.85224678
B47: C5+: | C47: =$B$24 -> 3247.2322 | D47: =C24 -> 660 | E47: =C47/C46 -> 0.15355522 | F47: =C47/C49 -> 0.13311475 | O47: C5+: | P47: =$R$22 -> 3666.2356 | Q47: =$O$29 -> 660 | R47: =P47/P46 -> 0.17336906 | S47: =P47/P49 -> 0.14775322
B48: C4: | C48: =$B$23 -> 0 | D48: =$C$23 -> 575 | E48: =C48/C46 -> 0 | F48: =C48/C49 -> 0 | O48: C4: | P48: 0 | Q48: =$C$23 -> 575 | R48: =P48/P46 -> 0 | S48: =P48/P49 -> 0
B49: Blend (pre-Shrinkage): | C49: =SUM(C46:C48) -> 24394.232 | D49: =SUMPRODUCT(C46:C48,D46:D48)/SUM(C46:C48) -> 924.4 | F49: =SUM(F46:F48) -> 1 | O49: Blend (B4 Shrinkage): | P49: =SUM(P46:P48) -> 24813.236 | Q49: =SUMPRODUCT(P46:P48,Q46:Q48)/SUM(P46:P48) -> 919.93527 | S49: =SUM(S46:S48) -> 1
B50: Estimated Shrinkage: | C50: =I26 -> 91.070427 | O50: Estimated Shrinkage: | P50: =-R24 -> 119.8572
B51: NET BLEND: | C51: =C49-C50 -> 24303.162 | O51: NET BLEND: | P51: =P49-P50 -> 24693.378
C53: m3 | D53: $Cdn/m3 | E53: $Cdn | P53: m3 | Q53: $Cdn/m3 | R53: $Cdn
B54: SALE OF NET BLEND: | C54: =C51 -> 24303.162 | D54: =E8 -> 565.73896 | E54: =C54*D54 -> 13749245 | O54: SALE OF NET BLEND: | P54: =P51 -> 24693.378 | Q54: =D54 -> 565.73896 | R54: =P54*Q54 -> 13970006
B55: C5+Cost: | C55: =C47 -> 3247.2322 | D55: =I15*-1 -> -658.30767 | E55: =C55*D55 -> -2137677.9 | O55: C5+Cost: | P55: =P47 -> 3666.2356 | Q55: =D55 -> -658.30767 | R55: =P55*Q55 -> -2413511
B56: C4 Cost: | C56: =C48 -> 0 | D56: 0 | E56: =C56*D56 -> 0 | O56: C4 Cost: | P56: =P48 -> 0 | Q56: =D56 -> 0 | R56: =P56*Q56 -> 0
B57: C5+ Transportation: | C57: =C55 -> 3247.2322 | D57: =-(Inputs!C9+Inputs!C10) -> -41.086207 | E57: =C57*D57 -> -133416.45 | O57: C5+ Transportation: | P57: =P55 -> 3666.2356 | Q57: =D57 -> -41.086207 | R57: =P57*Q57 -> -150631.71
B58: Blend Transportation: | C58: =C49 -> 24394.232 | D58: =-('Spur-Netback'!E106+'Spur-Netback'!E107+'Spur-Netback'!E114+'Spur-Netback'!E115+'Spur-Netback'!E116+'Spur-Netback'!E117+'Spur-Netback'!E118) -> -25.53 | E58: =C58*D58 -> -622784.75 | I58: Blend Revenue: | J58: =E54 -> 13749245 | K58: =J58/$C$46 -> 650.17475 | O58: Blend Transportation: | P58: =P51 -> 24693.378 | Q58: =D58 -> -25.53 | R58: =P58*Q58 -> -630421.95
B59: Loss Allowance: | C59: =C49*Inputs!C26 -> 48.788464 | D59: =D54*-1 -> -565.73896 | E59: =C59*D59 -> -27601.535 | I59: Total Diluent Costs: | J59: =E55+E56 -> -2137677.9 | K59: =J59/$C$46 -> -101.08658 | O59: Loss Allowance: | P59: =P51*0.001 -> 24.693378 | Q59: =D59 -> -565.73896 | R59: =P59*Q59 -> -13970.006
B60: Transportation: | C60: 0 | D60: 0 | E60: =C60*D60 -> 0 | I60: C5+ Transporation Costs: | J60: =E57 -> -133416.45 | K60: =J60/$C$46 -> -6.3090015 | O60: Transportation: | P60: 0 | Q60: =D60 -> 0 | R60: =P60*Q60 -> 0
B61: Loss Allowance: | C61: 0 | D61: 0 | E61: =C61*D61 -> 0 | I61: BLEND Tariff & L/A Costs: | J61: =E58+E59+E60+E61 -> -650386.28 | K61: =J61/$C$46 -> -30.755487 | O61: Loss Allowance: | P61: 0 | Q61: =D61 -> 0 | R61: =P61*Q61 -> 0
D62: NET: | E62: =SUM(E54:E61) -> 10827765 | J62: =SUM(J58:J61) -> 10827765 | K62: =SUM(K58:K61) -> 512.02368 | Q62: NET: | R62: =SUM(R54:R61) -> 10761471
D63: m3 Raw Crude Production: | E63: =C46 -> 21147 | F63: m3 | K63: =E64 -> 512.02368 | Q63: m3 Raw Crude Production: | R63: =P46 -> 21147 | S63: m3
D64: Net Price Recived per m3 Raw Crude: | E64: =E62/E63 -> 512.02368 | F64: $Cdn/m3 | K64: =K62-K63 -> 0 | L64: Check | Q64: Net Price Recived per m3 Raw Heavy Crude: | R64: =R62/R63 -> 508.8888 | S64: $Cdn/m3
E65: =E64/6.29287 -> 81.365685 | F65: $Cdn/bbl | R65: =R64/6.29287 -> 80.867521 | S65: $Cdn/bbl
E66: =E65/B7 -> 59.523527 | F66: $US/bbl
D67: Raw Crude Net Price EXPRESSED AS Diff to WTI: | E67: =E66-B6 -> -19.096473 | F67: $US/bbl
D68: Raw Crude Net Price EXPRESSED AS DIFF to WCS: | E68: =E67-B8 -> -6.276473 | F68: $US/bbl
D69: Diluent Fee per m3 of Raw Crude: | E69: =E64-(D54+D58+(C59/C54)*D59) -> -27.049558 | F69: $Cdn/m3 | Q69: Diluent Fee per m3 of Raw Heavy: | R69: =R64-(Q54+Q58+P59/P54*Q59) -> -30.754418
D70: Diluent Fee per m3 of Raw Crude: | E70: =(((C55-C50-C59)*D54)-(C55*I15))/C46 -> -17.956009 | F70: $Cdn/m3 | G70: Alternative Formula
D71: Diluent COST per m3 of Blended Crude: | E71: =(E55+E56+E57)/C51 -> -93.448513 | F71: $Cdn/m3 | G71: Measured as a function of product cost plus transportation cost divided by Net Blend
A74: Butane (Primary) & Condensate (Secondary) - Physical Blend
A75: API 12.3 Sec.5.3
B76: TEMP CORR. VOLUMES & DENSITY INPUTS | H76: RESULTS
B77: m3 | C77: Dens @ 15C | D77: % of Blend | H77: Shrinkage Percent | I77: SHRINKAGE | J77: Sum of Volumes | K77: Resultant Volume
A78: RAW CRUDE OIL: | B78: =$B$22 -> 21147 | C78: =$C$22 -> 965 | D78: =B78/B82 -> 0.87466113 | H78: % | I78: m3
A79: Butane: | B79: =$B$78*$E$79 -> 674.5893 | C79: 575 | D79: =B79/B82 -> 0.02790169 | E79: =Inputs!C25 -> 0.0319 | F79: % of Raw | H79: =IFERROR(26900*F91*(100-F91)^0.819*(I91-J91)^2.28,0) -> 0.22782348 | I79: =IFERROR(H79/100*(B91+D91),0) -> 49.714705 | J79: =B91+D91 -> 21821.589 | K79: =B91+D91-I79 -> 21771.875
A80: Condensate: | B80: =MAX(0,($B$78*$C$78+$B$79*$C$79-$D$49*$B$78-$D$49*$B$79)/($D$49-C80)) -> 2355.7742 | C80: =$C$24 -> 660 | D80: =B80/B82 -> 0.097437183 | E80: =D49 -> 924.4 | F80: C5 Only Target Blend 350cSt | H80: =IFERROR(26900*F92*(100-F92)^0.819*(I92-J92)^2.28,0) -> 0.28297562 | I80: =IFERROR(H80/100*(B92+D92),0) -> 68.275363 | J80: =B92+D92 -> 24127.649 | K80: =B92+D92-I80 -> 24059.373
H81: =IFERROR(26900*F93*(100-F93)^0.819*(I93-J93)^2.28,0) -> 0 | I81: =IFERROR(H81/100*(B93+D93),0) -> 0 | J81: =B93+D93 -> 24059.373 | K81: =B93+D93-I81 -> 24059.373
A82: Total Receipts: | B82: =SUM(B78:B81) -> 24177.364 | D82: =SUM(D78:D81) -> 1 | H82: =IF(I82=0,"",(I82/K82)) -> 0.0049041206 | I82: =(SUM(I79:I81))*1 -> 117.99007 | K82: =K81 -> 24059.373
A83: Wt.Avg. Kg/m3: | B83: =SUMPRODUCT(B78:B81,C78:C81)/SUM(B78:B81) -> 924.4 | C83: =IF(B83>E83, "Okay", "Check Overblending!") -> Okay | E83: =Inputs!C17 -> 924.2 | F83: Historical Actual Blend | J83: Total Receipts: | K83: =B82 -> 24177.364
B84: =D104 -> 924.4 | J84: Total Shrinkage: | K84: =I82*-1 -> -117.99007
J85: Net Volume: | K85: =K83+K84 -> 24059.373
A86: API 12.3 Sec.5.3 | J86: Total Shrinkage as % of Total Receipts: | K86: =I82/B82 -> 0.0048801876
A87: --- Linked to INPUT values above ---
B88: LIGHT | D88: RAW CRUDE OIL
B89: Diluent Volume | C89: Average Density | D89: Volume | E89: Average Density | F89: X = DILUENT Volume/(Crude Volume + DILUENT Volume) | G89: XX = CRUDE Volume/(CRUDE Volume + Diluent Volume) | H89: CRUDE + DILUENT BLEND | I89: 1/dL | J89: 1/dH
B90: m3 | C90: kg/m3 | D90: m3 | E90: kg/m3 | F90: % | G90: % | H90: %
A91: Butane: | B91: =B79 -> 674.5893 | C91: =C79 -> 575 | D91: =B78 -> 21147 | E91: =C78 -> 965 | F91: =IFERROR(B91/(B91+D91)*100,"") -> 3.0913848 | G91: =IFERROR(D91/(B91+D91)*100,"") -> 96.908615 | H91: =F91+G91 -> 100 | I91: =IFERROR(1/C91,"") -> 0.0017391304 | J91: =IFERROR(1/E91,"") -> 0.0010362694
A92: Condensate: | B92: =B80 -> 2355.7742 | C92: =C80 -> 660 | D92: =K79 -> 21771.875 | E92: =E91 -> 965 | F92: =IFERROR(B92/(B92+D92)*100,"") -> 9.7637951 | G92: =IFERROR(D92/(B92+D92)*100,"") -> 90.236205 | H92: =F92+G92 -> 100 | I92: =IFERROR(1/C92,"") -> 0.0015151515 | J92: =IFERROR(1/E92,"") -> 0.0010362694
A93: OIL: | B93: =K80 -> 24059.373 | C93: =E92 -> 965 | D93: =B81 -> 0 | E93: =C81 -> 0 | F93: =IFERROR(B93/(B93+D93)*100,"") -> 100 | G93: =IFERROR(D93/(B93+D93)*100,"") -> 0 | H93: =F93+G93 -> 100 | I93: =IFERROR(1/C93,"") -> 0.0010362694 | J93: =IFERROR(1/E93,"")
A94: dL | B94: = Density of Light
A95: dH | B95: = Density of Heavy
A96: X | B96: = % concentraion of Diluent. (i.e., Diluent percentage of total blend).
A97: XX | B97: = % concentraion of Crude. (i.e., Crude percentage of total blend).
A99: Butane & Condensate - Net Sales Calculation
C100: m3 | D100: kg/m3 | E100: % Inject | F100: % of Blend
B101: Raw Crude: | C101: =$B$78 -> 21147 | D101: =$C$78 -> 965 | F101: =C101/C104 -> 0.87466113
B102: C5+: | C102: =$B$80 -> 2355.7742 | D102: =$C$80 -> 660 | E102: =C102/C101 -> 0.11139992 | F102: =C102/C104 -> 0.097437183
B103: C4: | C103: =$B$79 -> 674.5893 | D103: =C79 -> 575 | E103: =C103/C101 -> 0.0319 | F103: =C103/C104 -> 0.02790169
B104: Blend (B4 Shrinkage): | C104: =SUM(C101:C103) -> 24177.364 | D104: =SUMPRODUCT(C101:C103,D101:D103)/SUM(C101:C103) -> 924.4 | F104: =SUM(F101:F103) -> 1
B105: Estimated Shrinkage: | C105: =I82 -> 117.99007
B106: NET BLEND: | C106: =C104-C105 -> 24059.373
C108: m3 | D108: $Cdn/m3 | E108: $Cdn
B109: SALE OF NET BLEND: | C109: =C106 -> 24059.373 | D109: =E8 -> 565.73896 | E109: =C109*D109 -> 13611325
B110: C5+Cost: | C110: =C102 -> 2355.7742 | D110: =I15*-1 -> -658.30767 | E110: =C110*D110 -> -1550824.2
...

Sheet UtikuSouthTT DilFee Nipisi
A1: Diluent Optimization Benefit - ESTIMATED (NO CRUDE VISCOSITY DATA)
A4: PRICING ASSUMPTIONS: | C4: WADF | D4: PAR | E4: STREAM
A5: MONTH: | B5: ='Spur-Netback'!C37 -> 45413 | C5: $Cdn/m3 | D5: $Cdn/m3 | E5: $Cdn/m3 | G5: =B5 -> 45413 | H5: CONDENSATE EQ: | I5: $/m3 | J5: C4 Content | K5: Penalty $/m3 | L5: Penalty $/m3 /.1%
A6: WTI: | B6: =_xlfn.XLOOKUP($B$5,MonthlyData!$B:$B,MonthlyData!$D:$D) -> 78.62 | H6: C5+ Allow Price | I6: =_xlfn.XLOOKUP($B$5,MonthlyData!$B:$B,MonthlyData!$Z:$Z) -> 636.91 | J6: <=5.0% | K6: 0 | L6: 0
A7: FX: | B7: =_xlfn.XLOOKUP($B$5,MonthlyData!$B:$B,MonthlyData!$E:$E) -> 1.36695 | H7: Butane Price | I7: 0 | J7: >5.0%-7.0% | K7: =ROUND(I6-I8,2) -> 636.91 | L7: =ROUND(K7/1000,6) -> 0.63691
A8: CHV INDEX ($US/bbl): | B8: =_xlfn.XLOOKUP($B$5,MonthlyData!$B:$B,MonthlyData!$BP:$BP) -> -12.82 | E8: =(B6+B8)*6.2898105*B7 -> 565.73896 | H8: 50% of Butane Value | I8: =ROUND(I7/2,2) -> 0 | J8: > 7.0% | K8: =ROUND(I6,2) -> 636.91 | L8: =ROUND(K8/1000,6) -> 0.63691
A9: C5+ INDEX ($US/bbl): | B9: =_xlfn.XLOOKUP($B$5,MonthlyData!$B:$B,MonthlyData!$M:$M) -> -4.19 | C9: =_xlfn.XLOOKUP($B$5,MonthlyData!$B:$B,MonthlyData!$X:$X) -> -4.27 | D9: =(($B$6+B9)*6.29287*$B$7)+C9 -> 635.97974 | E9: =D9-C9 -> 640.24974 | H9: Density Slope (C5+) | I9: =_xlfn.XLOOKUP($B$5,MonthlyData!$B:$B,MonthlyData!$Y:$Y) -> 0.17 | J9: $ / m3 per kg / m3 | L9: 750 kg/m3
A10: C4 Price %WTI (Landed): | B10: =_xlfn.XLOOKUP($B$5,MonthlyData!$B:$B,MonthlyData!$AM:$AM) -> 0.475 | E10: =(B6*B10)*6.29287*B7+D10 -> 321.23883 | H10: Sulphur | I10: =I13 -> 1.38 | J10: $ / m3 per .1 wt% | L10: .2% wt
A11: \ | B11: =B10 -> 0.475 | H11: CRUDE (INDUSTRY) EQ:
A12: C4 Diff: | B12: =1-B11 -> 0.525 | C12: (1 - 62.4%) | H12: Density Slope (Crude) | I12: 0.49 | J12: $ / m3 per kg / m3 | K12: Heavy Allow Price: | L12: =_xlfn.XLOOKUP($B$5,MonthlyData!$B:$B,MonthlyData!$AE:$AE) -> 0
A13: C4 Purchase Price ($US/bbl): | B13: =B6*B11 -> 37.3445 | H13: Sulphur | I13: 1.38 | J13: $ / m3 per .1 wt% | K13: Enb. Ref Temp: | L13: =_xlfn.XLOOKUP($B$5,MonthlyData!$B:$B,MonthlyData!$AF:$AF) -> 0
A14: C4 Diff to WTI ($US/bbl): | B14: =B13-B6 -> -41.2755 | D14: C4 vs. C5+: | E14: =E10-I15 -> -337.06883 | H14: Calculated EQ CREDIT: | I14: =(750-$L$14)*$I$9+(0.2-$L$15)*$I$10*10 -> 18.05793 | K14: C5+ Density: | L14: =Inputs!C7 -> 660
H15: C5+ Price after EQ: | I15: =E9+I14 -> 658.30767 | K15: C5+ Sulfur: | L15: =Inputs!C8 -> 0.00015
A18: Condensate Only - Paper Blend | N18: SCENARIO #1 - IF C5+ ONLY:
A19: API 12.3 Sec.5.3
B20: TEMP CORR. VOLUMES & DENSITY INPUTS | H20: RESULTS | O20: Value | R20: Result
B21: m3 | C21: Dens @ 15C | D21: % of Blend | H21: Shrinkage Percent | I21: SHRINKAGE | J21: Sum of Volumes | K21: Resultant Volume | N21: Raw Heavy Volume | O21: =B22 -> 21147 | Q21: Raw (m3) | R21: =O32 -> 21147
A22: RAW CRUDE OIL: | B22: =Inputs!C5 -> 21147 | C22: =Inputs!C16 -> 965 | D22: =B22/B26 -> 0.86688525 | H22: % | I22: m3 | N22: Raw Heavy Density | O22: =C22 -> 965 | Q22: C5 (m3) | R22: =SUM(O34:S34) -> 3666.2356
A23: Butane: | B23: 0 | C23: 575 | D23: =B23/B26 -> 0 | H23: =IFERROR(26900*F36*(100-F36)^0.819*(I36-J36)^2.28,0) -> 0 | I23: =IFERROR(H23/100*(B36+D36),0) -> 0 | J23: =B36+D36 -> 21147 | K23: =B36+D36-I23 -> 21147 | N23: C5 Density | O23: =C24 -> 660 | Q23: Delivered (m3) | R23: =S40 -> 24693.378
A24: Condensate: | B24: =(C22-B28)/(B28-C24)*B22 -> 3247.2322 | C24: =L14 -> 660 | D24: =B24/B26 -> 0.13311475 | H24: =IFERROR(26900*F37*(100-F37)^0.819*(I37-J37)^2.28,0) -> 0.3733277 | I24: =IFERROR(H24/100*(B37+D37),0) -> 91.070427 | J24: =B37+D37 -> 24394.232 | K24: =B37+D37-I24 -> 24303.162 | N24: Target Density | O24: =B28 -> 924.4 | Q24: Shrinkage (m3) | R24: =R23-SUM(R21:R22) -> -119.8572
H25: =IFERROR(26900*F38*(100-F38)^0.819*(I38-J38)^2.28,0) -> 0 | I25: =IFERROR(H25/100*(B38+D38),0) -> 0 | J25: =B38+D38 -> 24303.162 | K25: =B38+D38-I25 -> 24303.162
A26: Total Receipts: | B26: =SUM(B22:B25) -> 24394.232 | D26: =SUM(D22:D25) -> 1 | H26: =IF(I26=0,"",(I26/K26)) -> 0.0037472666 | I26: =(SUM(I23:I25))*1 -> 91.070427 | K26: =K25 -> 24303.162 | N26: API 12.3 Heavy Oil Adjusted
A27: Wt.Avg. Kg/m3: | B27: =SUMPRODUCT(B22:B25,C22:C25)/SUM(B22:B25) -> 924.4 | J27: Total Receipts: | K27: =B26 -> 24394.232 | O27: Iteration 1 | P27: Iteration 2 | Q27: Iteration 3 | R27: Iteration 4 | S27: Iteration 5
A28: Target Density | B28: =Inputs!C18 -> 924.4 | J28: Total Shrinkage: | K28: =I26*-1 -> -91.070427 | N28: Target Density | O28: =$B$28 -> 924.4 | P28: =O28 -> 924.4 | Q28: =P28 -> 924.4 | R28: =Q28 -> 924.4 | S28: =R28 -> 924.4
B29: =D49 -> 924.4 | J29: Net Volume: | K29: =K27+K28 -> 24303.162 | N29: Diluent Density | O29: =$C$24 -> 660 | P29: =O29 -> 660 | Q29: =P29 -> 660 | R29: =Q29 -> 660 | S29: =R29 -> 660
J30: Total Shrinkage as % of Total Receipts: | K30: =I26/B26 -> 0.003733277 | N30: Raw Crude Density | O30: =$C$22 -> 965 | P30: =O41 -> 928.48481 | Q30: =P41 -> 924.82147 | R30: =Q41 -> 924.44359 | S30: =R41 -> 924.40451
A31: API 12.3 Sec.5.3
A32: --- Linked to INPUT values above --- | N32: Raw Heavy Volume (m3) | O32: =$B$22 -> 21147 | P32: =O40 -> 24286.911 | Q32: =P40 -> 24650.889 | R32: =Q40 -> 24689.02 | S32: =R40 -> 24692.97
B33: LIGHT | D33: RAW CRUDE OIL | N33: Raw Heavy Mass (kg) | O33: =O32*O30 -> 20406855 | P33: =P32*P30 -> 22550028 | Q33: =Q32*Q30 -> 22797672 | R33: =R32*R30 -> 22823606 | S33: =S32*S30 -> 22826293
B34: Diluent Volume | C34: Average Density | D34: Volume | E34: Average Density | F34: X = DILUENT Volume/(Crude Volume + DILUENT Volume) | G34: XX = CRUDE Volume/(CRUDE Volume + Diluent Volume) | H34: CRUDE + DILUENT BLEND | I34: 1/dL | J34: 1/dH | N34: Diluent Required (m3) | O34: =(O28*O32-O30*O32)/(O29-O28) -> 3247.2322 | P34: =(P28*P32-P30*P32)/(P29-P28) -> 375.21729 | Q34: =(Q28*Q32-Q30*Q32)/(Q29-Q28) -> 39.295037 | R34: =(R28*R32-R30*R32)/(R29-R28) -> 4.0699587 | S34: =(S28*S32-S30*S32)/(S29-S28) -> 0.42105704
B35: m3 | C35: kg/m3 | D35: m3 | E35: kg/m3 | F35: % | G35: % | H35: % | N35: Diluent Mass (kg) | O35: =O34*O29 -> 2143173.3 | P35: =P34*P29 -> 247643.41 | Q35: =Q34*Q29 -> 25934.725 | R35: =R34*R29 -> 2686.1728 | S35: =S34*S29 -> 277.89765
A36: Butane: | B36: =B23 -> 0 | C36: =C23 -> 575 | D36: =B22 -> 21147 | E36: =C22 -> 965 | F36: =IFERROR(B36/(B36+D36)*100,"") -> 0 | G36: =IFERROR(D36/(B36+D36)*100,"") -> 100 | H36: =F36+G36 -> 100 | I36: =IFERROR(1/C36,"") -> 0.0017391304 | J36: =IFERROR(1/E36,"") -> 0.0010362694
A37: Condensate: | B37: =B24 -> 3247.2322 | C37: =C24 -> 660 | D37: =K23 -> 21147 | E37: =E36 -> 965 | F37: =IFERROR(B37/(B37+D37)*100,"") -> 13.311475 | G37: =IFERROR(D37/(B37+D37)*100,"") -> 86.688525 | H37: =F37+G37 -> 100 | I37: =IFERROR(1/C37,"") -> 0.0015151515 | J37: =IFERROR(1/E37,"") -> 0.0010362694 | N37: Diluent as % of Blend | O37: =O34/(O32+O34) -> 0.13311475 | P37: =P34/(P32+P34) -> 0.015214311 | Q37: =Q34/(Q32+Q34) -> 0.0015915247 | R37: =R34/(R32+R34) -> 0.00016482177 | S37: =S34/(S32+S34) -> 1.7051406e-05
A38: OIL: | B38: =K24 -> 24303.162 | C38: =E37 -> 965 | D38: =B25 -> 0 | E38: =C25 -> 0 | F38: =IFERROR(B38/(B38+D38)*100,"") -> 100 | G38: =IFERROR(D38/(B38+D38)*100,"") -> 0 | H38: =F38+G38 -> 100 | I38: =IFERROR(1/C38,"") -> 0.0010362694 | J38: =IFERROR(1/E38,"") | N38: Shrinkage as % of Blend | O38: =31700*O37*(100-O37*100)^0.819*(1/O29-1/O30)^2.28 -> 0.004399438 | P38: =31700*P37*(100-P37*100)^0.819*(1/P29-1/P30)^2.28 -> 0.0004557311 | Q38: =31700*Q37*(100-Q37*100)^0.819*(1/Q29-1/Q30)^2.28 -> 4.7148425e-05 | R38: =31700*R37*(100-R37*100)^0.819*(1/R29-1/R30)^2.28 -> 4.87716e-06 | S38: =31700*S37*(100-S37*100)^0.819*(1/S29-1/S30)^2.28 -> 5.0449949e-07
A39: dL | B39: = Density of Light | N39: Shrinkage (m3) | O39: =-O38*(O32+O34) -> -107.32091 | P39: =-P38*(P32+P34) -> -11.239299 | Q39: =-Q38*(Q32+Q34) -> -1.1641033 | R39: =-R38*(R32+R34) -> -0.12043215 | S39: =-S38*(S32+S34) -> -0.012457803
A40: dH | B40: = Density of Heavy | N40: Volume After Shrinkage | O40: =O32+O34+O39 -> 24286.911 | P40: =P32+P34+P39 -> 24650.889 | Q40: =Q32+Q34+Q39 -> 24689.02 | R40: =R32+R34+R39 -> 24692.97 | S40: =S32+S34+S39 -> 24693.378
A41: X | B41: = % concentraion of Diluent. (i.e., Diluent percentage of total blend). | N41: Density After Shrinkage | O41: =(O33+O35)/O40 -> 928.48481 | P41: =(P33+P35)/P40 -> 924.82147 | Q41: =(Q33+Q35)/Q40 -> 924.44359 | R41: =(R33+R35)/R40 -> 924.40451 | S41: =(S33+S35)/S40 -> 924.40047
A42: XX | B42: = % concentraion of Crude. (i.e., Crude percentage of total blend).
A44: Condensate Only - Net Sales Calculation | N44: SCENARIO #1 - FINANCIAL RESULTS:
C45: m3 | D45: kg/m3 | E45: % Inject | F45: % of Blend | P45: m3 | Q45: kg/m3 | R45: % Inject | S45: % of Blend
B46: Raw Crude: | C46: =$B$22 -> 21147 | D46: =$C$22 -> 965 | F46: =C46/C49 -> 0.86688525 | O46: Raw Crude: | P46: =$B$22 -> 21147 | Q46: =$C$22 -> 965 | S46: =P46/P49 -> 0.85224678
B47: C5+: | C47: =$B$24 -> 3247.2322 | D47: =C24 -> 660 | E47: =C47/C46 -> 0.15355522 | F47: =C47/C49 -> 0.13311475 | O47: C5+: | P47: =$R$22 -> 3666.2356 | Q47: =$O$29 -> 660 | R47: =P47/P46 -> 0.17336906 | S47: =P47/P49 -> 0.14775322
B48: C4: | C48: =$B$23 -> 0 | D48: =$C$23 -> 575 | E48: =C48/C46 -> 0 | F48: =C48/C49 -> 0 | O48: C4: | P48: 0 | Q48: =$C$23 -> 575 | R48: =P48/P46 -> 0 | S48: =P48/P49 -> 0
B49: Blend (pre-Shrinkage): | C49: =SUM(C46:C48) -> 24394.232 | D49: =SUMPRODUCT(C46:C48,D46:D48)/SUM(C46:C48) -> 924.4 | F49: =SUM(F46:F48) -> 1 | O49: Blend (B4 Shrinkage): | P49: =SUM(P46:P48) -> 24813.236 | Q49: =SUMPRODUCT(P46:P48,Q46:Q48)/SUM(P46:P48) -> 919.93527 | S49: =SUM(S46:S48) -> 1
B50: Estimated Shrinkage: | C50: =I26 -> 91.070427 | O50: Estimated Shrinkage: | P50: =-R24 -> 119.8572
B51: NET BLEND: | C51: =C49-C50 -> 24303.162 | O51: NET BLEND: | P51: =P49-P50 -> 24693.378
C53: m3 | D53: $Cdn/m3 | E53: $Cdn | P53: m3 | Q53: $Cdn/m3 | R53: $Cdn
B54: SALE OF NET BLEND: | C54: =C51 -> 24303.162 | D54: =E8 -> 565.73896 | E54: =C54*D54 -> 13749245 | O54: SALE OF NET BLEND: | P54: =P51 -> 24693.378 | Q54: =D54 -> 565.73896 | R54: =P54*Q54 -> 13970006
B55: C5+Cost: | C55: =C47 -> 3247.2322 | D55: =I15*-1 -> -658.30767 | E55: =C55*D55 -> -2137677.9 | O55: C5+Cost: | P55: =P47 -> 3666.2356 | Q55: =D55 -> -658.30767 | R55: =P55*Q55 -> -2413511
B56: C4 Cost: | C56: =C48 -> 0 | D56: 0 | E56: =C56*D56 -> 0 | O56: C4 Cost: | P56: =P48 -> 0 | Q56: =D56 -> 0 | R56: =P56*Q56 -> 0
B57: C5+ Transportation: | C57: =C55 -> 3247.2322 | D57: =-(Inputs!C9+Inputs!C11) -> -38.189655 | E57: =C57*D57 -> -124010.68 | O57: C5+ Transportation: | P57: =P55 -> 3666.2356 | Q57: =D57 -> -38.189655 | R57: =P57*Q57 -> -140012.27
B58: Blend Transportation: | C58: =C49 -> 24394.232 | D58: =-('Spur-Netback'!F106+'Spur-Netback'!F107+'Spur-Netback'!F114+'Spur-Netback'!F115+'Spur-Netback'!F116+'Spur-Netback'!F117+'Spur-Netback'!F118) -> -24.1479 | E58: =C58*D58 -> -589069.48 | I58: Blend Revenue: | J58: =E54 -> 13749245 | K58: =J58/$C$46 -> 650.17475 | O58: Blend Transportation: | P58: =P51 -> 24693.378 | Q58: =D58 -> -24.1479 | R58: =P58*Q58 -> -596293.23
B59: Loss Allowance: | C59: =C49*Inputs!C26 -> 48.788464 | D59: =D54*-1 -> -565.73896 | E59: =C59*D59 -> -27601.535 | I59: Total Diluent Costs: | J59: =E55+E56 -> -2137677.9 | K59: =J59/$C$46 -> -101.08658 | O59: Loss Allowance: | P59: =P51*0.001 -> 24.693378 | Q59: =D59 -> -565.73896 | R59: =P59*Q59 -> -13970.006
B60: Transportation: | C60: 0 | D60: 0 | E60: =C60*D60 -> 0 | I60: C5+ Transporation Costs: | J60: =E57 -> -124010.68 | K60: =J60/$C$46 -> -5.8642209 | O60: Transportation: | P60: 0 | Q60: =D60 -> 0 | R60: =P60*Q60 -> 0
B61: Loss Allowance: | C61: 0 | D61: 0 | E61: =C61*D61 -> 0 | I61: BLEND Tariff & L/A Costs: | J61: =E58+E59+E60+E61 -> -616671.02 | K61: =J61/$C$46 -> -29.161158 | O61: Loss Allowance: | P61: 0 | Q61: =D61 -> 0 | R61: =P61*Q61 -> 0
D62: NET: | E62: =SUM(E54:E61) -> 10870886 | J62: =SUM(J58:J61) -> 10870886 | K62: =SUM(K58:K61) -> 514.06279 | Q62: NET: | R62: =SUM(R54:R61) -> 10806220
D63: m3 Raw Crude Production: | E63: =C46 -> 21147 | F63: m3 | K63: =E64 -> 514.06279 | Q63: m3 Raw Crude Production: | R63: =P46 -> 21147 | S63: m3
D64: Net Price Recived per m3 Raw Crude: | E64: =E62/E63 -> 514.06279 | F64: $Cdn/m3 | K64: =K62-K63 -> 0 | L64: Check | Q64: Net Price Recived per m3 Raw Heavy Crude: | R64: =R62/R63 -> 511.00485 | S64: $Cdn/m3
E65: =E64/6.29287 -> 81.68972 | F65: $Cdn/bbl | R65: =R64/6.29287 -> 81.203783 | S65: $Cdn/bbl
E66: =E65/B7 -> 59.760577 | F66: $US/bbl
D67: Raw Crude Net Price EXPRESSED AS Diff to WTI: | E67: =E66-B6 -> -18.859423 | F67: $US/bbl
D68: Raw Crude Net Price EXPRESSED AS DIFF to WCS: | E68: =E67-B8 -> -6.0394234 | F68: $US/bbl
D69: Diluent Fee per m3 of Raw Crude: | E69: =E64-(D54+D58+(C59/C54)*D59) -> -26.392548 | F69: $Cdn/m3 | Q69: Diluent Fee per m3 of Raw Heavy: | R69: =R64-(Q54+Q58+P59/P54*Q59) -> -30.020465
D70: Diluent Fee per m3 of Raw Crude: | E70: =(((C55-C50-C59)*D54)-(C55*I15))/C46 -> -17.956009 | F70: $Cdn/m3 | G70: Alternative Formula
D71: Diluent COST per m3 of Blended Crude: | E71: =(E55+E56+E57)/C51 -> -93.061494 | F71: $Cdn/m3
A74: Butane (Primary) & Condensate (Secondary) - Physical Blend
A75: API 12.3 Sec.5.3
B76: TEMP CORR. VOLUMES & DENSITY INPUTS | H76: RESULTS
B77: m3 | C77: Dens @ 15C | D77: % of Blend | H77: Shrinkage Percent | I77: SHRINKAGE | J77: Sum of Volumes | K77: Resultant Volume
A78: RAW CRUDE OIL: | B78: =$B$22 -> 21147 | C78: =$C$22 -> 965 | D78: =B78/B82 -> 0.87466113 | H78: % | I78: m3
A79: Butane: | B79: =$B$78*$E$79 -> 674.5893 | C79: 575 | D79: =B79/B82 -> 0.02790169 | E79: =Inputs!C25 -> 0.0319 | F79: % of Raw | H79: =IFERROR(26900*F91*(100-F91)^0.819*(I91-J91)^2.28,0) -> 0.22782348 | I79: =IFERROR(H79/100*(B91+D91),0) -> 49.714705 | J79: =B91+D91 -> 21821.589 | K79: =B91+D91-I79 -> 21771.875
A80: Condensate: | B80: =MAX(0,($B$78*$C$78+$B$79*$C$79-$D$49*$B$78-$D$49*$B$79)/($D$49-C80)) -> 2355.7742 | C80: =$C$24 -> 660 | D80: =B80/B82 -> 0.097437183 | E80: =D49 -> 924.4 | F80: C5 Only Target Blend 350cSt | H80: =IFERROR(26900*F92*(100-F92)^0.819*(I92-J92)^2.28,0) -> 0.28297562 | I80: =IFERROR(H80/100*(B92+D92),0) -> 68.275363 | J80: =B92+D92 -> 24127.649 | K80: =B92+D92-I80 -> 24059.373
H81: =IFERROR(26900*F93*(100-F93)^0.819*(I93-J93)^2.28,0) -> 0 | I81: =IFERROR(H81/100*(B93+D93),0) -> 0 | J81: =B93+D93 -> 24059.373 | K81: =B93+D93-I81 -> 24059.373
A82: Total Receipts: | B82: =SUM(B78:B81) -> 24177.364 | D82: =SUM(D78:D81) -> 1 | H82: =IF(I82=0,"",(I82/K82)) -> 0.0049041206 | I82: =(SUM(I79:I81))*1 -> 117.99007 | K82: =K81 -> 24059.373
A83: Wt.Avg. Kg/m3: | B83: =SUMPRODUCT(B78:B81,C78:C81)/SUM(B78:B81) -> 924.4 | C83: =IF(B83>E83, "Okay", "Check Overblending!") -> Okay | E83: =Inputs!C17 -> 924.2 | F83: Historical Actual Blend | J83: Total Receipts: | K83: =B82 -> 24177.364
B84: =D104 -> 924.4 | J84: Total Shrinkage: | K84: =I82*-1 -> -117.99007
J85: Net Volume: | K85: =K83+K84 -> 24059.373
A86: API 12.3 Sec.5.3 | J86: Total Shrinkage as % of Total Receipts: | K86: =I82/B82 -> 0.0048801876
A87: --- Linked to INPUT values above ---
B88: LIGHT | D88: RAW CRUDE OIL
B89: Diluent Volume | C89: Average Density | D89: Volume | E89: Average Density | F89: X = DILUENT Volume/(Crude Volume + DILUENT Volume) | G89: XX = CRUDE Volume/(CRUDE Volume + Diluent Volume) | H89: CRUDE + DILUENT BLEND | I89: 1/dL | J89: 1/dH
B90: m3 | C90: kg/m3 | D90: m3 | E90: kg/m3 | F90: % | G90: % | H90: %
A91: Butane: | B91: =B79 -> 674.5893 | C91: =C79 -> 575 | D91: =B78 -> 21147 | E91: =C78 -> 965 | F91: =IFERROR(B91/(B91+D91)*100,"") -> 3.0913848 | G91: =IFERROR(D91/(B91+D91)*100,"") -> 96.908615 | H91: =F91+G91 -> 100 | I91: =IFERROR(1/C91,"") -> 0.0017391304 | J91: =IFERROR(1/E91,"") -> 0.0010362694
A92: Condensate: | B92: =B80 -> 2355.7742 | C92: =C80 -> 660 | D92: =K79 -> 21771.875 | E92: =E91 -> 965 | F92: =IFERROR(B92/(B92+D92)*100,"") -> 9.7637951 | G92: =IFERROR(D92/(B92+D92)*100,"") -> 90.236205 | H92: =F92+G92 -> 100 | I92: =IFERROR(1/C92,"") -> 0.0015151515 | J92: =IFERROR(1/E92,"") -> 0.0010362694
A93: OIL: | B93: =K80 -> 24059.373 | C93: =E92 -> 965 | D93: =B81 -> 0 | E93: =C81 -> 0 | F93: =IFERROR(B93/(B93+D93)*100,"") -> 100 | G93: =IFERROR(D93/(B93+D93)*100,"") -> 0 | H93: =F93+G93 -> 100 | I93: =IFERROR(1/C93,"") -> 0.0010362694 | J93: =IFERROR(1/E93,"")
A94: dL | B94: = Density of Light
A95: dH | B95: = Density of Heavy
A96: X | B96: = % concentraion of Diluent. (i.e., Diluent percentage of total blend).
A97: XX | B97: = % concentraion of Crude. (i.e., Crude percentage of total blend).
A99: Butane & Condensate - Net Sales Calculation
C100: m3 | D100: kg/m3 | E100: % Inject | F100: % of Blend
B101: Raw Crude: | C101: =$B$78 -> 21147 | D101: =$C$78 -> 965 | F101: =C101/C104 -> 0.87466113
B102: C5+: | C102: =$B$80 -> 2355.7742 | D102: =$C$80 -> 660 | E102: =C102/C101 -> 0.11139992 | F102: =C102/C104 -> 0.097437183
B103: C4: | C103: =$B$79 -> 674.5893 | D103: =C79 -> 575 | E103: =C103/C101 -> 0.0319 | F103: =C103/C104 -> 0.02790169
B104: Blend (B4 Shrinkage): | C104: =SUM(C101:C103) -> 24177.364 | D104: =SUMPRODUCT(C101:C103,D101:D103)/SUM(C101:C103) -> 924.4 | F104: =SUM(F101:F103) -> 1
B105: Estimated Shrinkage: | C105: =I82 -> 117.99007
B106: NET BLEND: | C106: =C104-C105 -> 24059.373
C108: m3 | D108: $Cdn/m3 | E108: $Cdn
B109: SALE OF NET BLEND: | C109: =C106 -> 24059.373 | D109: =E8 -> 565.73896 | E109: =C109*D109 -> 13611325
B110: C5+Cost: | C110: =C102 -> 2355.7742 | D110: =I15*-1 -> -658.30767 | E110: =C110*D110 -> -1550824.2
...

Sheet KingMH-Plains Novacor Rainbow
A3: NOVACOR: Condensate Addition & Shrinkage Calculations
F7: RESULTS | J7: Rainbow SW (Interface) | K7: RP2 C5+ | L7: CHV
A8: Date | B8: ='Spur-Netback'!C37 -> 45413 | E8: Volume of Dry Crude = | F8: =B9 -> 21147 | G8: m3 | I8: Density (KG/M3) | J8: 815 | K8: =Inputs!C14 -> 737 | L8: =Inputs!C18 -> 924.4
A9: Volume of Raw Crude = | B9: =Inputs!C5 -> 21147 | C9: M3 | E9: % C5+ in Total Blend (Fc) = | F9: =B36 -> 19.324663 | G9: % | I9: Sulfur (%Swt) | J9: 0.35 | K9: 0.1 | L9: 4
A10: Density of Raw Crude = | B10: =Inputs!C16 -> 965 | C10: KG/M3 | E10: Condensate Required in Blend= | F10: =((F9/100)*B9)/(1-F9/100) -> 5065.4719 | G10: m3 | I10: WTI (USD/BBL) | J10: =_xlfn.XLOOKUP($B$8,MonthlyData!$B:$B,MonthlyData!$D:$D) -> 78.62 | K10: =J10 -> 78.62 | L10: =J10 -> 78.62
A11: Density of Condensate (RP2 C5+) = | B11: =K8 -> 737 | C11: KG/M3 | E11: Shrinkage Volume = | F11: =(B9+F10)*B37/100 -> 98.119075 | G11: m3 | I11: FX (CAD/USD) | J11: =_xlfn.XLOOKUP($B$8,MonthlyData!$B:$B,MonthlyData!$E:$E) -> 1.36695 | K11: =J11 -> 1.36695 | L11: =K11 -> 1.36695
A12: Density of Target Blend = | B12: =L8 -> 924.4 | C12: KG/M3 | E12: Volume of Blend = | F12: =B9+F10-F11 -> 26114.353 | G12: m3 | I12: Diff (USD/BBL) | J12: =_xlfn.XLOOKUP($B$8,MonthlyData!$B:$B,MonthlyData!$F:$F) -> -3.78 | K12: =_xlfn.XLOOKUP($B$8,MonthlyData!$B:$B,MonthlyData!$M:$M) -> -4.19 | L12: =_xlfn.XLOOKUP($B$8,MonthlyData!$B:$B,MonthlyData!$BP:$BP) -> -12.82
I13: WADF (CAD/M3) | J13: =_xlfn.XLOOKUP($B$8,MonthlyData!$B:$B,MonthlyData!$G:$G) -> 0.015 | K13: =_xlfn.XLOOKUP($B$8,MonthlyData!$B:$B,MonthlyData!$X:$X) -> -4.27 | L13: 0
A14: Raw Crude Density - as measured by Producer or at Truck Unload or Oil Analysis. | I14: Ref Price | J14: =J13+(J10+J12)*6.29287*J11 -> 643.79157 | K14: =K13+(K10+K12)*6.29287*K11 -> 635.97974 | L14: =L13+(L10+L12)*6.2898105*L11 -> 565.73896
A15: Condensate Density - as reported by CM or Plains or Producer/Customer deliveries in the delivery month. | E15: Apparent Condensate | F15: =F10-F11 -> 4967.3529 | I15: EQ | J15: =IF(J8>825,(825-J8)*0.49,IF(J8<800,(J8-800)*0.49,0))+(0.5-J9)*13.8 -> 2.07 | K15: =(750-K8)*$B$18+(0.2-$K$9)*13.8 -> 3.59 | L15: 0
A16: Target Blend Density - CHV density, as reported by CM or Plains or Producer/Customer, in the delivery month | E16: Shrinkage as: %C5+ | F16: =F11/F10*100 -> 1.9370174 | I16: Tariff on Purchase
E17: Shrinkage as: %Blend | F17: =(F19-F12)/F19*100 -> 0.3743221 | I17: Trucking on Purchase
A18: C5 Density Slope | B18: =_xlfn.XLOOKUP($B$8,MonthlyData!$B:$B,MonthlyData!$Y:$Y) -> 0.17 | E18: Shrinkage as: % Shrunk Blend | F18: =(F19-F12)/F12*100 -> 0.37572853 | I18: Other
A19: Rainbow Interface % | B19: 0.0197 | E19: vol blend w/o shrinkage | F19: =F8+F10 -> 26212.472 | I19: Netback | J19: =SUM(J14:J18) -> 645.86157 | K19: =SUM(K14:K18) -> 639.56974 | L19: =SUM(L14:L18) -> 565.73896
E20: C5+ as % of dry crude | F20: =F10/F8*100 -> 23.95362
E21: C5+ as % of blend | F21: =F10/F12*100 -> 19.397272
A24: NovaCor Eqn
A25: ITERATIONS: | D25: vol C5+ | E25: Density Blend
A26: % C5+ in Total Blend (Fc) = | B26: =((B10-B12)/(B10-B11))*100 -> 17.807018 | C26: % | D26: =(B26/100*$B$9)/(1-B26/100) -> 4581.4739 | E26: =(D26*$B$11+$B$9*$B$10)/(D26+$B$9)/(1-B27/100) -> 927.68764
A27: Blend Shrinkage Factor (Sf) = | B27: =(0.0266*B26)-(0.0004*(POWER(B26,2)))+(0.000001339*(POWER(B26,3))) -> 0.35439128 | C27: % | D27: =(B9/(1-B26/100))*(B26/100) -> 4581.4739
A28: % C5+ in Total Blend (Fc) = | B28: =(((($B$10-$B$12)/($B$10-$B$11))+((B27/100)*$B$12)/($B$10-$B$11)))*100 -> 19.243857 | C28: % | D28: =(B28/100*$B$9)/(1-B28/100) -> 5039.2431 | E28: =(D28*$B$11+$B$9*$B$10)/(D28+$B$9)/(1-B29/100) -> 924.57543
A29: Blend Shrinkage Factor (Sf) = | B29: =(0.0266*B28)-(0.0004*(POWER(B28,2)))+(0.000001339*(POWER(B28,3))) -> 0.37329856 | C29: %
A30: % C5+ in Total Blend (Fc) = | B30: =(((($B$10-$B$12)/($B$10-$B$11))+((B29/100)*$B$12)/($B$10-$B$11)))*100 -> 19.320514 | C30: % | D30: =(B30/100*$B$9)/(1-B30/100) -> 5064.1239 | E30: =(D30*$B$11+$B$9*$B$10)/(D30+$B$9)/(1-B31/100) -> 924.40901
A31: Blend Shrinkage Factor (Sf) = | B31: =(0.0266*B30)-(0.0004*(POWER(B30,2)))+(0.000001339*(POWER(B30,3))) -> 0.37426964 | C31: %
A32: % C5+ in Total Blend (Fc) = | B32: =(((($B$10-$B$12)/($B$10-$B$11))+((B31/100)*$B$12)/($B$10-$B$11)))*100 -> 19.324451 | C32: % | D32: =(B32/100*$B$9)/(1-B32/100) -> 5065.403 | E32: =(D32*$B$11+$B$9*$B$10)/(D32+$B$9)/(1-B33/100) -> 924.40046
A33: Blend Shrinkage Factor (Sf) = | B33: =(0.0266*B32)-(0.0004*(POWER(B32,2)))+(0.000001339*(POWER(B32,3))) -> 0.37431942 | C33: %
A34: % C5+ in Total Blend (Fc) = | B34: =(((($B$10-$B$12)/($B$10-$B$11))+((B33/100)*$B$12)/($B$10-$B$11)))*100 -> 19.324653 | C34: % | D34: =(B34/100*$B$9)/(1-B34/100) -> 5065.4686 | E34: =(D34*$B$11+$B$9*$B$10)/(D34+$B$9)/(1-B35/100) -> 924.40002
A35: Blend Shrinkage Factor (Sf) = | B35: =(0.0266*B34)-(0.0004*(POWER(B34,2)))+(0.000001339*(POWER(B34,3))) -> 0.37432197 | C35: %
A36: % C5+ in Total Blend (Fc) = | B36: =(((($B$10-$B$12)/($B$10-$B$11))+((B35/100)*$B$12)/($B$10-$B$11)))*100 -> 19.324663 | C36: % | D36: =(B36/100*$B$9)/(1-B36/100) -> 5065.4719 | E36: =(D36*$B$11+$B$9*$B$10)/(D36+$B$9)/(1-B37/100) -> 924.4
A37: Blend Shrinkage Factor (Sf) = | B37: =(0.0266*B36)-(0.0004*(POWER(B36,2)))+(0.000001339*(POWER(B36,3))) -> 0.3743221 | C37: %
A39: Pricing | E39: =1/1.3378 -> 0.74749589
A41: Condensate price @ Edmonton | B41: =$K$19 -> 639.56974 | C41: CAD/M3
A42: C5 RP2 Edm-Nipisi Toll: | B42: 16.54 | C42: CAD/M3
A43: C5 ENB/PMC Terminalling | B43: 3.47 | C43: CAD/M3
A44: Total Condensate price: | B44: =SUM(B41:B43) -> 659.57974 | C44: CAD/M3
A46: CHV Price (Edmonton) | B46: =$L$19 -> 565.73896 | C46: CAD/M3
A47: Rainbow Pipeline Terminal Fee | B47: 0 | C47: CAD/M3
A48: Rainbow Pipeline Tariff | B48: -11.82 | C48: CAD/M3
A49: Rainbow Inferface Fee | B49: =($L$19-$J$19)*$B$19 -> -1.5784156 | C49: CAD/M3
A50: Heavy Blend in Rainbow Nipisi Storage | B50: =SUM(B46:B49) -> 552.34054 | C50: CAD/M3
A52: Value of Heavy Blend: | B52: =B50*F12 -> 14424016 | C52: CAD | D52: =+B50*(F11/B9) -> 2.5627816 | E52: Shrinkage
A53: Value of Condensate: | B53: =F10*B44 -> 3341082.6 | C53: CAD | D53: =+(B44-B50)*F10/F8 -> 25.687669 | E53: Cond
A54: Value of Raw Crude | B54: =(B52-B53)/B9 -> 524.09009 | C54: CAD/M3
A55: Rainbow Loss Allowance | B55: =-0.15%*B46 -> -0.84860843 | C55: CAD/M3
A57: Raw Heavy Price | B57: =SUM(B54:B55) -> 523.24148 | C57: CAD/M3
B58: =B57/6.29287/$J$11 -> 60.827613 | C58: USD/BBL
B59: =B58-$J$10 -> -17.792387 | C59: Diff to WTI
A61: Diluent Fee per M3 of Raw Crude | B61: =-(B46-(B57-B49-B48-B47-B55)) -> -28.250451 | C61: CAD/M3
A62: Diluent Fee per M3 of Blended Crude | B62: =(B61*F8)/F12 -> -22.876779 | C62: CAD/M3
A63: Diluent Cost per M3 of Blended Crude | B63: =-(B44*F10)/F12 -> -127.94047 | C63: CAD/M3

Sheet KINGMitsueTT Dil Fee Nipisi
A1: Diluent Optimization Benefit - ESTIMATED (NO CRUDE VISCOSITY DATA)
A4: PRICING ASSUMPTIONS: | C4: WADF | D4: PAR | E4: STREAM
A5: MONTH: | B5: ='Spur-Netback'!C37 -> 45413 | C5: $Cdn/m3 | D5: $Cdn/m3 | E5: $Cdn/m3 | G5: =B5 -> 45413 | H5: CONDENSATE EQ: | I5: $/m3 | J5: C4 Content | K5: Penalty $/m3 | L5: Penalty $/m3 /.1%
A6: WTI: | B6: =_xlfn.XLOOKUP($B$5,MonthlyData!$B:$B,MonthlyData!$D:$D) -> 78.62 | H6: C5+ Allow Price | I6: =_xlfn.XLOOKUP($B$5,MonthlyData!$B:$B,MonthlyData!$Z:$Z) -> 636.91 | J6: <=5.0% | K6: 0 | L6: 0
A7: FX: | B7: =_xlfn.XLOOKUP($B$5,MonthlyData!$B:$B,MonthlyData!$E:$E) -> 1.36695 | H7: Butane Price | I7: 0 | J7: >5.0%-7.0% | K7: =ROUND(I6-I8,2) -> 636.91 | L7: =ROUND(K7/1000,6) -> 0.63691
A8: CHV INDEX ($US/bbl): | B8: =_xlfn.XLOOKUP($B$5,MonthlyData!$B:$B,MonthlyData!$BP:$BP) -> -12.82 | E8: =(B6+B8)*6.2898105*B7 -> 565.73896 | H8: 50% of Butane Value | I8: =ROUND(I7/2,2) -> 0 | J8: > 7.0% | K8: =ROUND(I6,2) -> 636.91 | L8: =ROUND(K8/1000,6) -> 0.63691
A9: C5+ INDEX ($US/bbl): | B9: =_xlfn.XLOOKUP($B$5,MonthlyData!$B:$B,MonthlyData!$M:$M) -> -4.19 | C9: =_xlfn.XLOOKUP($B$5,MonthlyData!$B:$B,MonthlyData!$X:$X) -> -4.27 | D9: =(($B$6+B9)*6.29287*$B$7)+C9 -> 635.97974 | E9: =D9-C9 -> 640.24974 | H9: Density Slope (C5+) | I9: =_xlfn.XLOOKUP($B$5,MonthlyData!$B:$B,MonthlyData!$Y:$Y) -> 0.17 | J9: $ / m3 per kg / m3 | L9: 750 kg/m3
A10: C4 Price %WTI (Landed): | B10: =_xlfn.XLOOKUP($B$5,MonthlyData!$B:$B,MonthlyData!$AM:$AM) -> 0.475 | E10: =(B6*B10)*6.29287*B7+D10 -> 321.23883 | H10: Sulphur | I10: =I13 -> 1.38 | J10: $ / m3 per .1 wt% | L10: .2% wt
A11: \ | B11: =B10 -> 0.475 | H11: CRUDE (INDUSTRY) EQ:
A12: C4 Diff: | B12: =1-B11 -> 0.525 | C12: (1 - 62.4%) | H12: Density Slope (Crude) | I12: 0.49 | J12: $ / m3 per kg / m3 | K12: Heavy Allow Price: | L12: =_xlfn.XLOOKUP($B$5,MonthlyData!$B:$B,MonthlyData!$AE:$AE) -> 0
A13: C4 Purchase Price ($US/bbl): | B13: =B6*B11 -> 37.3445 | H13: Sulphur | I13: 1.38 | J13: $ / m3 per .1 wt% | K13: Enb. Ref Temp: | L13: =_xlfn.XLOOKUP($B$5,MonthlyData!$B:$B,MonthlyData!$AF:$AF) -> 0
A14: C4 Diff to WTI ($US/bbl): | B14: =B13-B6 -> -41.2755 | D14: C4 vs. C5+: | E14: =E10-I15 -> -337.06883 | H14: Calculated EQ CREDIT: | I14: =(750-$L$14)*$I$9+(0.2-$L$15)*$I$10*10 -> 18.05793 | K14: C5+ Density: | L14: =Inputs!C7 -> 660
H15: C5+ Price after EQ: | I15: =E9+I14 -> 658.30767 | K15: C5+ Sulfur: | L15: =Inputs!C8 -> 0.00015
A18: Condensate Only - Paper Blend | N18: SCENARIO #1 - IF C5+ ONLY:
A19: API 12.3 Sec.5.3
B20: TEMP CORR. VOLUMES & DENSITY INPUTS | H20: RESULTS | O20: Value | R20: Result
B21: m3 | C21: Dens @ 15C | D21: % of Blend | H21: Shrinkage Percent | I21: SHRINKAGE | J21: Sum of Volumes | K21: Resultant Volume | N21: Raw Heavy Volume | O21: =B22 -> 21147 | Q21: Raw (m3) | R21: =O32 -> 21147
A22: RAW CRUDE OIL: | B22: =Inputs!C5 -> 21147 | C22: =Inputs!C16 -> 965 | D22: =B22/B26 -> 0.86688525 | H22: % | I22: m3 | N22: Raw Heavy Density | O22: =C22 -> 965 | Q22: C5 (m3) | R22: =SUM(O34:S34) -> 3666.2356
A23: Butane: | B23: 0 | C23: 575 | D23: =B23/B26 -> 0 | H23: =IFERROR(26900*F36*(100-F36)^0.819*(I36-J36)^2.28,0) -> 0 | I23: =IFERROR(H23/100*(B36+D36),0) -> 0 | J23: =B36+D36 -> 21147 | K23: =B36+D36-I23 -> 21147 | N23: C5 Density | O23: =C24 -> 660 | Q23: Delivered (m3) | R23: =S40 -> 24693.378
A24: Condensate: | B24: =(C22-B28)/(B28-C24)*B22 -> 3247.2322 | C24: =L14 -> 660 | D24: =B24/B26 -> 0.13311475 | H24: =IFERROR(26900*F37*(100-F37)^0.819*(I37-J37)^2.28,0) -> 0.3733277 | I24: =IFERROR(H24/100*(B37+D37),0) -> 91.070427 | J24: =B37+D37 -> 24394.232 | K24: =B37+D37-I24 -> 24303.162 | N24: Target Density | O24: =B28 -> 924.4 | Q24: Shrinkage (m3) | R24: =R23-SUM(R21:R22) -> -119.8572
H25: =IFERROR(26900*F38*(100-F38)^0.819*(I38-J38)^2.28,0) -> 0 | I25: =IFERROR(H25/100*(B38+D38),0) -> 0 | J25: =B38+D38 -> 24303.162 | K25: =B38+D38-I25 -> 24303.162
A26: Total Receipts: | B26: =SUM(B22:B25) -> 24394.232 | D26: =SUM(D22:D25) -> 1 | H26: =IF(I26=0,"",(I26/K26)) -> 0.0037472666 | I26: =(SUM(I23:I25))*1 -> 91.070427 | K26: =K25 -> 24303.162 | N26: API 12.3 Heavy Oil Adjusted
A27: Wt.Avg. Kg/m3: | B27: =SUMPRODUCT(B22:B25,C22:C25)/SUM(B22:B25) -> 924.4 | J27: Total Receipts: | K27: =B26 -> 24394.232 | O27: Iteration 1 | P27: Iteration 2 | Q27: Iteration 3 | R27: Iteration 4 | S27: Iteration 5
A28: Target Density | B28: =Inputs!C18 -> 924.4 | J28: Total Shrinkage: | K28: =I26*-1 -> -91.070427 | N28: Target Density | O28: =$B$28 -> 924.4 | P28: =O28 -> 924.4 | Q28: =P28 -> 924.4 | R28: =Q28 -> 924.4 | S28: =R28 -> 924.4
B29: =D49 -> 924.4 | J29: Net Volume: | K29: =K27+K28 -> 24303.162 | N29: Diluent Density | O29: =$C$24 -> 660 | P29: =O29 -> 660 | Q29: =P29 -> 660 | R29: =Q29 -> 660 | S29: =R29 -> 660
J30: Total Shrinkage as % of Total Receipts: | K30: =I26/B26 -> 0.003733277 | N30: Raw Crude Density | O30: =$C$22 -> 965 | P30: =O41 -> 928.48481 | Q30: =P41 -> 924.82147 | R30: =Q41 -> 924.44359 | S30: =R41 -> 924.40451
A31: API 12.3 Sec.5.3
A32: --- Linked to INPUT values above --- | N32: Raw Heavy Volume (m3) | O32: =$B$22 -> 21147 | P32: =O40 -> 24286.911 | Q32: =P40 -> 24650.889 | R32: =Q40 -> 24689.02 | S32: =R40 -> 24692.97
B33: LIGHT | D33: RAW CRUDE OIL | N33: Raw Heavy Mass (kg) | O33: =O32*O30 -> 20406855 | P33: =P32*P30 -> 22550028 | Q33: =Q32*Q30 -> 22797672 | R33: =R32*R30 -> 22823606 | S33: =S32*S30 -> 22826293
B34: Diluent Volume | C34: Average Density | D34: Volume | E34: Average Density | F34: X = DILUENT Volume/(Crude Volume + DILUENT Volume) | G34: XX = CRUDE Volume/(CRUDE Volume + Diluent Volume) | H34: CRUDE + DILUENT BLEND | I34: 1/dL | J34: 1/dH | N34: Diluent Required (m3) | O34: =(O28*O32-O30*O32)/(O29-O28) -> 3247.2322 | P34: =(P28*P32-P30*P32)/(P29-P28) -> 375.21729 | Q34: =(Q28*Q32-Q30*Q32)/(Q29-Q28) -> 39.295037 | R34: =(R28*R32-R30*R32)/(R29-R28) -> 4.0699587 | S34: =(S28*S32-S30*S32)/(S29-S28) -> 0.42105704
B35: m3 | C35: kg/m3 | D35: m3 | E35: kg/m3 | F35: % | G35: % | H35: % | N35: Diluent Mass (kg) | O35: =O34*O29 -> 2143173.3 | P35: =P34*P29 -> 247643.41 | Q35: =Q34*Q29 -> 25934.725 | R35: =R34*R29 -> 2686.1728 | S35: =S34*S29 -> 277.89765
A36: Butane: | B36: =B23 -> 0 | C36: =C23 -> 575 | D36: =B22 -> 21147 | E36: =C22 -> 965 | F36: =IFERROR(B36/(B36+D36)*100,"") -> 0 | G36: =IFERROR(D36/(B36+D36)*100,"") -> 100 | H36: =F36+G36 -> 100 | I36: =IFERROR(1/C36,"") -> 0.0017391304 | J36: =IFERROR(1/E36,"") -> 0.0010362694
A37: Condensate: | B37: =B24 -> 3247.2322 | C37: =C24 -> 660 | D37: =K23 -> 21147 | E37: =E36 -> 965 | F37: =IFERROR(B37/(B37+D37)*100,"") -> 13.311475 | G37: =IFERROR(D37/(B37+D37)*100,"") -> 86.688525 | H37: =F37+G37 -> 100 | I37: =IFERROR(1/C37,"") -> 0.0015151515 | J37: =IFERROR(1/E37,"") -> 0.0010362694 | N37: Diluent as % of Blend | O37: =O34/(O32+O34) -> 0.13311475 | P37: =P34/(P32+P34) -> 0.015214311 | Q37: =Q34/(Q32+Q34) -> 0.0015915247 | R37: =R34/(R32+R34) -> 0.00016482177 | S37: =S34/(S32+S34) -> 1.7051406e-05
A38: OIL: | B38: =K24 -> 24303.162 | C38: =E37 -> 965 | D38: =B25 -> 0 | E38: =C25 -> 0 | F38: =IFERROR(B38/(B38+D38)*100,"") -> 100 | G38: =IFERROR(D38/(B38+D38)*100,"") -> 0 | H38: =F38+G38 -> 100 | I38: =IFERROR(1/C38,"") -> 0.0010362694 | J38: =IFERROR(1/E38,"") | N38: Shrinkage as % of Blend | O38: =31700*O37*(100-O37*100)^0.819*(1/O29-1/O30)^2.28 -> 0.004399438 | P38: =31700*P37*(100-P37*100)^0.819*(1/P29-1/P30)^2.28 -> 0.0004557311 | Q38: =31700*Q37*(100-Q37*100)^0.819*(1/Q29-1/Q30)^2.28 -> 4.7148425e-05 | R38: =31700*R37*(100-R37*100)^0.819*(1/R29-1/R30)^2.28 -> 4.87716e-06 | S38: =31700*S37*(100-S37*100)^0.819*(1/S29-1/S30)^2.28 -> 5.0449949e-07
A39: dL | B39: = Density of Light | N39: Shrinkage (m3) | O39: =-O38*(O32+O34) -> -107.32091 | P39: =-P38*(P32+P34) -> -11.239299 | Q39: =-Q38*(Q32+Q34) -> -1.1641033 | R39: =-R38*(R32+R34) -> -0.12043215 | S39: =-S38*(S32+S34) -> -0.012457803
A40: dH | B40: = Density of Heavy | N40: Volume After Shrinkage | O40: =O32+O34+O39 -> 24286.911 | P40: =P32+P34+P39 -> 24650.889 | Q40: =Q32+Q34+Q39 -> 24689.02 | R40: =R32+R34+R39 -> 24692.97 | S40: =S32+S34+S39 -> 24693.378
A41: X | B41: = % concentraion of Diluent. (i.e., Diluent percentage of total blend). | N41: Density After Shrinkage | O41: =(O33+O35)/O40 -> 928.48481 | P41: =(P33+P35)/P40 -> 924.82147 | Q41: =(Q33+Q35)/Q40 -> 924.44359 | R41: =(R33+R35)/R40 -> 924.40451 | S41: =(S33+S35)/S40 -> 924.40047
A42: XX | B42: = % concentraion of Crude. (i.e., Crude percentage of total blend).
A44: Condensate Only - Net Sales Calculation | N44: SCENARIO #1 - FINANCIAL RESULTS:
C45: m3 | D45: kg/m3 | E45: % Inject | F45: % of Blend | P45: m3 | Q45: kg/m3 | R45: % Inject | S45: % of Blend
B46: Raw Crude: | C46: =$B$22 -> 21147 | D46: =$C$22 -> 965 | F46: =C46/C49 -> 0.86688525 | O46: Raw Crude: | P46: =$B$22 -> 21147 | Q46: =$C$22 -> 965 | S46: =P46/P49 -> 0.85224678
B47: C5+: | C47: =$B$24 -> 3247.2322 | D47: =C24 -> 660 | E47: =C47/C46 -> 0.15355522 | F47: =C47/C49 -> 0.13311475 | O47: C5+: | P47: =$R$22 -> 3666.2356 | Q47: =$O$29 -> 660 | R47: =P47/P46 -> 0.17336906 | S47: =P47/P49 -> 0.14775322
B48: C4: | C48: =$B$23 -> 0 | D48: =$C$23 -> 575 | E48: =C48/C46 -> 0 | F48: =C48/C49 -> 0 | O48: C4: | P48: 0 | Q48: =$C$23 -> 575 | R48: =P48/P46 -> 0 | S48: =P48/P49 -> 0
B49: Blend (B4 Shrinkage): | C49: =SUM(C46:C48) -> 24394.232 | D49: =SUMPRODUCT(C46:C48,D46:D48)/SUM(C46:C48) -> 924.4 | F49: =SUM(F46:F48) -> 1 | O49: Blend (B4 Shrinkage): | P49: =SUM(P46:P48) -> 24813.236 | Q49: =SUMPRODUCT(P46:P48,Q46:Q48)/SUM(P46:P48) -> 919.93527 | S49: =SUM(S46:S48) -> 1
B50: Estimated Shrinkage: | C50: =I26 -> 91.070427 | O50: Estimated Shrinkage: | P50: =-R24 -> 119.8572
B51: NET BLEND: | C51: =C49-C50 -> 24303.162 | O51: NET BLEND: | P51: =P49-P50 -> 24693.378
C53: m3 | D53: $Cdn/m3 | E53: $Cdn | P53: m3 | Q53: $Cdn/m3 | R53: $Cdn
B54: SALE OF NET BLEND: | C54: =C51 -> 24303.162 | D54: =E8 -> 565.73896 | E54: =C54*D54 -> 13749245 | O54: SALE OF NET BLEND: | P54: =P51 -> 24693.378 | Q54: =D54 -> 565.73896 | R54: =P54*Q54 -> 13970006
B55: C5+Cost: | C55: =C47 -> 3247.2322 | D55: =I15*-1 -> -658.30767 | E55: =C55*D55 -> -2137677.9 | O55: C5+Cost: | P55: =P47 -> 3666.2356 | Q55: =D55 -> -658.30767 | R55: =P55*Q55 -> -2413511
B56: C4 Cost: | C56: =C48 -> 0 | D56: 0 | E56: =C56*D56 -> 0 | O56: C4 Cost: | P56: =P48 -> 0 | Q56: =D56 -> 0 | R56: =P56*Q56 -> 0
B57: C5+ Transportation: | C57: =C55 -> 3247.2322 | D57: =-(Inputs!C9+Inputs!C12) -> -33.844828 | E57: =C57*D57 -> -109902.01 | O57: C5+ Transportation: | P57: =P55 -> 3666.2356 | Q57: =D57 -> -33.844828 | R57: =P57*Q57 -> -124083.11
B58: Blend Transportation: | C58: =C51 -> 24303.162 | D58: =-('Spur-Netback'!F106+'Spur-Netback'!F107+'Spur-Netback'!F114+'Spur-Netback'!F115+'Spur-Netback'!F116+'Spur-Netback'!F117+'Spur-Netback'!F118) -> -24.1479 | E58: =C58*D58 -> -586870.32 | I58: Blend Revenue: | J58: =E54 -> 13749245 | K58: =J58/$C$46 -> 650.17475 | O58: Blend Transportation: | P58: =P51 -> 24693.378 | Q58: =D58 -> -24.1479 | R58: =P58*Q58 -> -596293.23
B59: Loss Allowance: | C59: =C49*Inputs!C26 -> 48.788464 | D59: =D54*-1 -> -565.73896 | E59: =C59*D59 -> -27601.535 | I59: Total Diluent Costs: | J59: =E55+E56 -> -2137677.9 | K59: =J59/$C$46 -> -101.08658 | O59: Loss Allowance: | P59: =P51*0.001 -> 24.693378 | Q59: =D59 -> -565.73896 | R59: =P59*Q59 -> -13970.006
B60: Transportation: | C60: 0 | D60: 0 | E60: =C60*D60 -> 0 | I60: C5+ Transporation Costs: | J60: =E57 -> -109902.01 | K60: =J60/$C$46 -> -5.1970499 | O60: Transportation: | P60: 0 | Q60: =D60 -> 0 | R60: =P60*Q60 -> 0
B61: Loss Allowance: | C61: 0 | D61: 0 | E61: =C61*D61 -> 0 | I61: BLEND Tariff & L/A Costs: | J61: =E58+E59+E60+E61 -> -614471.86 | K61: =J61/$C$46 -> -29.057164 | O61: Loss Allowance: | P61: 0 | Q61: =D61 -> 0 | R61: =P61*Q61 -> 0
D62: NET: | E62: =SUM(E54:E61) -> 10887194 | J62: =SUM(J58:J61) -> 10887194 | K62: =SUM(K58:K61) -> 514.83395 | Q62: NET: | R62: =SUM(R54:R61) -> 10822149
D63: m3 Raw Crude Production: | E63: =C46 -> 21147 | F63: m3 | K63: =E64 -> 514.83395 | Q63: m3 Raw Crude Production: | R63: =P46 -> 21147 | S63: m3
D64: Net Price Recived per m3 Raw Crude: | E64: =E62/E63 -> 514.83395 | F64: $Cdn/m3 | K64: =K62-K63 -> 0 | L64: Check | Q64: Net Price Recived per m3 Raw Heavy Crude: | R64: =R62/R63 -> 511.75811 | S64: $Cdn/m3
E65: =E64/6.29287 -> 81.812266 | F65: $Cdn/bbl | R65: =R64/6.29287 -> 81.323484 | S65: $Cdn/bbl
E66: =E65/B7 -> 59.850226 | F66: $US/bbl
D67: Raw Crude Net Price EXPRESSED AS Diff to WTI: | E67: =E66-B6 -> -18.769774 | F67: $US/bbl
D68: Raw Crude Net Price EXPRESSED AS DIFF to WCS: | E68: =E67-B8 -> -5.9497743 | F68: $US/bbl
D69: Diluent Fee per m3 of Raw Crude: | E69: =E64-(D54+D58+(C59/C54)*D59) -> -25.621383 | F69: $Cdn/m3 | Q69: Diluent Fee per m3 of Raw Heavy: | R69: =R64-(Q54+Q58+P59/P54*Q59) -> -29.267207
D70: Diluent Fee per m3 of Raw Crude: | E70: =(((C55-C50-C59)*D54)-(C55*I15))/C46 -> -17.956009 | F70: $Cdn/m3 | G70: Alternative Formula
A73: Butane (Primary) & Condensate (Secondary) - Physical Blend
A74: API 12.3 Sec.5.3
B75: TEMP CORR. VOLUMES & DENSITY INPUTS | H75: RESULTS
B76: m3 | C76: Dens @ 15C | D76: % of Blend | H76: Shrinkage Percent | I76: SHRINKAGE | J76: Sum of Volumes | K76: Resultant Volume
A77: RAW CRUDE OIL: | B77: =$B$22 -> 21147 | C77: =$C$22 -> 965 | D77: =B77/B81 -> 0.87466113 | H77: % | I77: m3
A78: Butane: | B78: =$B$77*$E$78 -> 674.5893 | C78: 575 | D78: =B78/B81 -> 0.02790169 | E78: =Inputs!C25 -> 0.0319 | F78: % of Raw | H78: =IFERROR(26900*F90*(100-F90)^0.819*(I90-J90)^2.28,0) -> 0.22782348 | I78: =IFERROR(H78/100*(B90+D90),0) -> 49.714705 | J78: =B90+D90 -> 21821.589 | K78: =B90+D90-I78 -> 21771.875
A79: Condensate: | B79: =MAX(0,($B$77*$C$77+$B$78*$C$78-$D$49*$B$77-$D$49*$B$78)/($D$49-C79)) -> 2355.7742 | C79: =$C$24 -> 660 | D79: =B79/B81 -> 0.097437183 | E79: =D49 -> 924.4 | F79: C5 Only Target Blend 350cSt | H79: =IFERROR(26900*F91*(100-F91)^0.819*(I91-J91)^2.28,0) -> 0.28297562 | I79: =IFERROR(H79/100*(B91+D91),0) -> 68.275363 | J79: =B91+D91 -> 24127.649 | K79: =B91+D91-I79 -> 24059.373
H80: =IFERROR(26900*F92*(100-F92)^0.819*(I92-J92)^2.28,0) -> 0 | I80: =IFERROR(H80/100*(B92+D92),0) -> 0 | J80: =B92+D92 -> 24059.373 | K80: =B92+D92-I80 -> 24059.373
A81: Total Receipts: | B81: =SUM(B77:B80) -> 24177.364 | D81: =SUM(D77:D80) -> 1 | H81: =IF(I81=0,"",(I81/K81)) -> 0.0049041206 | I81: =(SUM(I78:I80))*1 -> 117.99007 | K81: =K80 -> 24059.373
A82: Wt.Avg. Kg/m3: | B82: =SUMPRODUCT(B77:B80,C77:C80)/SUM(B77:B80) -> 924.4 | C82: =IF(B82>E82, "Okay", "Check Overblending!") -> Okay | E82: =Inputs!C17 -> 924.2 | F82: Historical Actual Blend | J82: Total Receipts: | K82: =B81 -> 24177.364
B83: =D103 -> 924.4 | J83: Total Shrinkage: | K83: =I81*-1 -> -117.99007
J84: Net Volume: | K84: =K82+K83 -> 24059.373
A85: API 12.3 Sec.5.3 | J85: Total Shrinkage as % of Total Receipts: | K85: =I81/B81 -> 0.0048801876
A86: --- Linked to INPUT values above ---
B87: LIGHT | D87: RAW CRUDE OIL
B88: Diluent Volume | C88: Average Density | D88: Volume | E88: Average Density | F88: X = DILUENT Volume/(Crude Volume + DILUENT Volume) | G88: XX = CRUDE Volume/(CRUDE Volume + Diluent Volume) | H88: CRUDE + DILUENT BLEND | I88: 1/dL | J88: 1/dH
B89: m3 | C89: kg/m3 | D89: m3 | E89: kg/m3 | F89: % | G89: % | H89: %
A90: Butane: | B90: =B78 -> 674.5893 | C90: =C78 -> 575 | D90: =B77 -> 21147 | E90: =C77 -> 965 | F90: =IFERROR(B90/(B90+D90)*100,"") -> 3.0913848 | G90: =IFERROR(D90/(B90+D90)*100,"") -> 96.908615 | H90: =F90+G90 -> 100 | I90: =IFERROR(1/C90,"") -> 0.0017391304 | J90: =IFERROR(1/E90,"") -> 0.0010362694
A91: Condensate: | B91: =B79 -> 2355.7742 | C91: =C79 -> 660 | D91: =K78 -> 21771.875 | E91: =E90 -> 965 | F91: =IFERROR(B91/(B91+D91)*100,"") -> 9.7637951 | G91: =IFERROR(D91/(B91+D91)*100,"") -> 90.236205 | H91: =F91+G91 -> 100 | I91: =IFERROR(1/C91,"") -> 0.0015151515 | J91: =IFERROR(1/E91,"") -> 0.0010362694
A92: OIL: | B92: =K79 -> 24059.373 | C92: =E91 -> 965 | D92: =B80 -> 0 | E92: =C80 -> 0 | F92: =IFERROR(B92/(B92+D92)*100,"") -> 100 | G92: =IFERROR(D92/(B92+D92)*100,"") -> 0 | H92: =F92+G92 -> 100 | I92: =IFERROR(1/C92,"") -> 0.0010362694 | J92: =IFERROR(1/E92,"")
A93: dL | B93: = Density of Light
A94: dH | B94: = Density of Heavy
A95: X | B95: = % concentraion of Diluent. (i.e., Diluent percentage of total blend).
A96: XX | B96: = % concentraion of Crude. (i.e., Crude percentage of total blend).
A98: Butane & Condensate - Net Sales Calculation
C99: m3 | D99: kg/m3 | E99: % Inject | F99: % of Blend
B100: Raw Crude: | C100: =$B$77 -> 21147 | D100: =$C$77 -> 965 | F100: =C100/C103 -> 0.87466113
B101: C5+: | C101: =$B$79 -> 2355.7742 | D101: =$C$79 -> 660 | E101: =C101/C100 -> 0.11139992 | F101: =C101/C103 -> 0.097437183
B102: C4: | C102: =$B$78 -> 674.5893 | D102: =C78 -> 575 | E102: =C102/C100 -> 0.0319 | F102: =C102/C103 -> 0.02790169
B103: Blend (B4 Shrinkage): | C103: =SUM(C100:C102) -> 24177.364 | D103: =SUMPRODUCT(C100:C102,D100:D102)/SUM(C100:C102) -> 924.4 | F103: =SUM(F100:F102) -> 1
B104: Estimated Shrinkage: | C104: =I81 -> 117.99007
B105: NET BLEND: | C105: =C103-C104 -> 24059.373
C107: m3 | D107: $Cdn/m3 | E107: $Cdn
B108: SALE OF NET BLEND: | C108: =C105 -> 24059.373 | D108: =E8 -> 565.73896 | E108: =C108*D108 -> 13611325
B109: C5+Cost: | C109: =C101 -> 2355.7742 | D109: =I15*-1 -> -658.30767 | E109: =C109*D109 -> -1550824.2
B110: C4 Cost: | C110: =C102 -> 674.5893 | D110: =E10*-1 -> -321.23883 | E110: =C110*D110 -> -216704.28
...

Sheet Gibsons Novacor Edm
A3: NOVACOR: Condensate Addition & Shrinkage Calculations
F7: RESULTS | K7: CRW C5+ | L7: CHV
A8: Date | B8: ='Spur-Netback'!C37 -> 45413 | E8: Volume of Dry Crude = | F8: =B9 -> 21147 | G8: m3 | I8: Density (KG/M3) | K8: =Inputs!C13 -> 730 | L8: =Inputs!C18 -> 924.4
A9: Volume of Raw Crude = | B9: =Inputs!C5 -> 21147 | C9: M3 | E9: % C5+ in Total Blend (Fc) = | F9: =B36 -> 18.718424 | G9: % | I9: Sulfur (%Swt) | K9: 0.1 | L9: 4
A10: Density of Raw Crude = | B10: =Inputs!C16 -> 965 | C10: KG/M3 | E10: Condensate Required in Blend= | F10: =((F9/100)*B9)/(1-F9/100) -> 4869.966 | G10: m3 | I10: WTI (USD/BBL) | K10: =_xlfn.XLOOKUP($B$8,MonthlyData!$B:$B,MonthlyData!$D:$D) -> 78.62 | L10: =_xlfn.XLOOKUP($B$8,MonthlyData!$B:$B,MonthlyData!$D:$D) -> 78.62
A11: Density of Condensate (CRW C5+) = | B11: =K8 -> 730 | C11: KG/M3 | E11: Shrinkage Volume = | F11: =(B9+F10)*B37/100 -> 95.362644 | G11: m3 | I11: FX (CAD/USD) | K11: =_xlfn.XLOOKUP($B$8,MonthlyData!$B:$B,MonthlyData!$E:$E) -> 1.36695 | L11: =_xlfn.XLOOKUP($B$8,MonthlyData!$B:$B,MonthlyData!$E:$E) -> 1.36695
A12: Density of Target Blend = | B12: =L8 -> 924.4 | C12: KG/M3 | E12: Volume of Blend = | F12: =B9+F10-F11 -> 25921.603 | G12: m3 | I12: Diff (USD/BBL) | K12: =_xlfn.XLOOKUP($B$8,MonthlyData!$B:$B,MonthlyData!$M:$M) -> -4.19 | L12: =_xlfn.XLOOKUP($B$8,MonthlyData!$B:$B,MonthlyData!$BP:$BP) -> -12.82
I13: WADF (CAD/M3) | K13: =_xlfn.XLOOKUP($B$8,MonthlyData!$B:$B,MonthlyData!$X:$X) -> -4.27 | L13: 0
A14: Raw Crude Density - as measured by Producer or at Truck Unload or Oil Analysis. | I14: Ref Price | K14: =K13+(K10+K12)*6.29287*K11 -> 635.97974 | L14: =L13+(L10+L12)*6.2898105*L11 -> 565.73896
A15: Condensate Density - as reported by CM or Plains or Producer/Customer deliveries in the delivery month. | E15: Apparent Condensate | F15: =F10-F11 -> 4774.6034 | I15: EQ | K15: =(750-K8)*$B$18+(0.2-$K$9)*13.8 -> 4.78 | L15: 0
A16: Target Blend Density - CHV density, as reported by CM or Plains or Producer/Customer, in the delivery month | E16: Shrinkage as: %C5+ | F16: =F11/F10*100 -> 1.9581788 | I16: Tariff on Purchase
E17: Shrinkage as: %Blend | F17: =(F19-F12)/F19*100 -> 0.36654022 | I17: Trucking on Purchase
A18: C5 Density Slope | B18: =_xlfn.XLOOKUP($B$8,MonthlyData!$B:$B,MonthlyData!$Y:$Y) -> 0.17 | E18: Shrinkage as: % Shrunk Blend | F18: =(F19-F12)/F12*100 -> 0.36788868 | I18: Other
A19: Rainbow Interface % | B19: 0 | E19: vol blend w/o shrinkage | F19: =F8+F10 -> 26016.966 | I19: Netback | K19: =SUM(K14:K18) -> 640.75974 | L19: =SUM(L14:L18) -> 565.73896
E20: C5+ as % of dry crude | F20: =F10/F8*100 -> 23.029111
E21: C5+ as % of blend | F21: =F10/F12*100 -> 18.787287
A24: NovaCor Eqn
A25: ITERATIONS: | D25: vol C5+ | E25: Density Blend
A26: % C5+ in Total Blend (Fc) = | B26: =((B10-B12)/(B10-B11))*100 -> 17.276596 | C26: % | D26: =(B26/100*$B$9)/(1-B26/100) -> 4416.5031 | E26: =(D26*$B$11+$B$9*$B$10)/(D26+$B$9)/(1-B27/100) -> 927.61949
A27: Blend Shrinkage Factor (Sf) = | B27: =(0.0266*B26)-(0.0004*(POWER(B26,2)))+(0.000001339*(POWER(B26,3))) -> 0.34707001 | C27: % | D27: =(B9/(1-B26/100))*(B26/100) -> 4416.5031
A28: % C5+ in Total Blend (Fc) = | B28: =(((($B$10-$B$12)/($B$10-$B$11))+((B27/100)*$B$12)/($B$10-$B$11)))*100 -> 18.641836 | C28: % | D28: =(B28/100*$B$9)/(1-B28/100) -> 4845.4745 | E28: =(D28*$B$11+$B$9*$B$10)/(D28+$B$9)/(1-B29/100) -> 924.57136
A29: Blend Shrinkage Factor (Sf) = | B29: =(0.0266*B28)-(0.0004*(POWER(B28,2)))+(0.000001339*(POWER(B28,3))) -> 0.36554016 | C29: %
A30: % C5+ in Total Blend (Fc) = | B30: =(((($B$10-$B$12)/($B$10-$B$11))+((B29/100)*$B$12)/($B$10-$B$11)))*100 -> 18.714491 | C30: % | D30: =(B30/100*$B$9)/(1-B30/100) -> 4868.7071 | E30: =(D30*$B$11+$B$9*$B$10)/(D30+$B$9)/(1-B31/100) -> 924.4088
A31: Blend Shrinkage Factor (Sf) = | B31: =(0.0266*B30)-(0.0004*(POWER(B30,2)))+(0.000001339*(POWER(B30,3))) -> 0.36648895 | C31: %
A32: % C5+ in Total Blend (Fc) = | B32: =(((($B$10-$B$12)/($B$10-$B$11))+((B31/100)*$B$12)/($B$10-$B$11)))*100 -> 18.718223 | C32: % | D32: =(B32/100*$B$9)/(1-B32/100) -> 4869.9016 | E32: =(D32*$B$11+$B$9*$B$10)/(D32+$B$9)/(1-B33/100) -> 924.40045
A33: Blend Shrinkage Factor (Sf) = | B33: =(0.0266*B32)-(0.0004*(POWER(B32,2)))+(0.000001339*(POWER(B32,3))) -> 0.3665376 | C33: %
A34: % C5+ in Total Blend (Fc) = | B34: =(((($B$10-$B$12)/($B$10-$B$11))+((B33/100)*$B$12)/($B$10-$B$11)))*100 -> 18.718414 | C34: % | D34: =(B34/100*$B$9)/(1-B34/100) -> 4869.9629 | E34: =(D34*$B$11+$B$9*$B$10)/(D34+$B$9)/(1-B35/100) -> 924.40002
A35: Blend Shrinkage Factor (Sf) = | B35: =(0.0266*B34)-(0.0004*(POWER(B34,2)))+(0.000001339*(POWER(B34,3))) -> 0.36654009 | C35: %
A36: % C5+ in Total Blend (Fc) = | B36: =(((($B$10-$B$12)/($B$10-$B$11))+((B35/100)*$B$12)/($B$10-$B$11)))*100 -> 18.718424 | C36: % | D36: =(B36/100*$B$9)/(1-B36/100) -> 4869.966 | E36: =(D36*$B$11+$B$9*$B$10)/(D36+$B$9)/(1-B37/100) -> 924.4
A37: Blend Shrinkage Factor (Sf) = | B37: =(0.0266*B36)-(0.0004*(POWER(B36,2)))+(0.000001339*(POWER(B36,3))) -> 0.36654022 | C37: %
A39: Pricing | E39: =1/1.3378 -> 0.74749589
A41: Condensate price @ Edmonton | B41: =$K$19 -> 640.75974 | C41: CAD/M3
A42: Gibsons P/L Toll | B42: 2 | C42: CAD/M3
A43: C5 ENB Terminalling | B43: 3.39 | C43: CAD/M3
A44: Total Condensate price: | B44: =SUM(B41:B43) -> 646.14974 | C44: CAD/M3
A46: CHV Price (Edmonton) | B46: =$L$19 -> 565.73896 | C46: CAD/M3
A47: Pipeline Terminal Fee | B47: 0 | C47: CAD/M3
A48: Pipeline Tariff | B48: 0 | C48: CAD/M3
A49: Storage Fee | B49: 0 | C49: CAD/M3
A50: Heavy Blend in Gibsons Storage | B50: =SUM(B46:B49) -> 565.73896 | C50: CAD/M3
A52: Value of Heavy Blend: | B52: =B50*F12 -> 14664861 | C52: CAD | D52: =+B50*(F11/B9) -> 2.5512065 | E52: Shrinkage
A53: Value of Condensate: | B53: =F10*B44 -> 3146727.3 | C53: CAD | D53: =+(B44-B50)*F10/F8 -> 18.517888 | E53: Cond
A54: Value of Raw Crude | B54: =(B52-B53)/B9 -> 544.66986 | C54: CAD/M3
A55: Rainbow Loss Allowance | B55: =-0.15%*B46 -> -0.84860843 | C55: CAD/M3
A57: Raw Heavy Price | B57: =SUM(B54:B55) -> 543.82125 | C57: CAD/M3
B58: =B57/6.29287/$L$11 -> 63.220043 | C58: USD/BBL
B59: =B58-$J$10 -> 63.220043 | C59: Diff to WTI
A61: Diluent Fee per M3 of Raw Crude | B61: =-(B46-(B57-B49-B48-B47-B55)) -> -21.069094 | C61: CAD/M3
A62: Diluent Fee per M3 of Blended Crude | B62: =(B61*F8)/F12 -> -17.188294 | C62: CAD/M3
A63: Diluent Cost per M3 of Blended Crude | B63: =-(B44*F10)/F12 -> -121.39401 | C63: CAD/M3

Sheet FlintHills Novacor Hardisty
A3: NOVACOR: Condensate Addition & Shrinkage Calculations
F7: RESULTS | K7: CRW C5+ | L7: WCS
A8: Date | B8: ='Spur-Netback'!C37 -> 45413 | E8: Volume of Dry Crude = | F8: =B9 -> 21147 | G8: m3 | I8: Density (KG/M3) | K8: =Inputs!C13 -> 730 | L8: =_xlfn.XLOOKUP($B$8,MonthlyData!$B:$B,MonthlyData!$AD:$AD) -> 924.8
A9: Volume of Raw Crude = | B9: =Inputs!C5 -> 21147 | C9: M3 | E9: % C5+ in Total Blend (Fc) = | F9: =B36 -> 18.539624 | G9: % | I9: Sulfur (%Swt) | K9: 0.1 | L9: 4
A10: Density of Raw Crude = | B10: =Inputs!C16 -> 965 | C10: KG/M3 | E10: Condensate Required in Blend= | F10: =((F9/100)*B9)/(1-F9/100) -> 4812.8605 | G10: m3 | I10: WTI (USD/BBL) | K10: =_xlfn.XLOOKUP($B$8,MonthlyData!$B:$B,MonthlyData!$D:$D) -> 78.62 | L10: =_xlfn.XLOOKUP($B$8,MonthlyData!$B:$B,MonthlyData!$D:$D) -> 78.62
A11: Density of Condensate (CRW C5+) = | B11: =K8 -> 730 | C11: KG/M3 | E11: Shrinkage Volume = | F11: =(B9+F10)*B37/100 -> 94.545701 | G11: m3 | I11: FX (CAD/USD) | K11: =_xlfn.XLOOKUP($B$8,MonthlyData!$B:$B,MonthlyData!$E:$E) -> 1.36695 | L11: =_xlfn.XLOOKUP($B$8,MonthlyData!$B:$B,MonthlyData!$E:$E) -> 1.36695
A12: Density of Target Blend = | B12: =L8 -> 924.8 | C12: KG/M3 | E12: Volume of Blend = | F12: =B9+F10-F11 -> 25865.315 | G12: m3 | I12: Diff (USD/BBL) | K12: =_xlfn.XLOOKUP($B$8,MonthlyData!$B:$B,MonthlyData!$M:$M) -> -4.19 | L12: =_xlfn.XLOOKUP($B$8,MonthlyData!$B:$B,MonthlyData!$AA:$AA) -> -13.07
I13: WADF (CAD/M3) | K13: =_xlfn.XLOOKUP($B$8,MonthlyData!$B:$B,MonthlyData!$X:$X) -> -4.27 | L13: 0
A14: Raw Crude Density - as measured by Producer or at Truck Unload or Oil Analysis. | I14: Ref Price | K14: =K13+(K10+K12)*6.29287*K11 -> 635.97974 | L14: =L13+(L10+L12)*6.2898105*L11 -> 563.58949
A15: Condensate Density - as reported by CM or Plains or Producer/Customer deliveries in the delivery month. | E15: Apparent Condensate | F15: =F10-F11 -> 4718.3148 | I15: EQ | K15: =(750-K8)*$B$18+(0.2-$K$9)*13.8 -> 4.78 | L15: 0
A16: Target Blend Density - CHV density, as reported by CM or Plains or Producer/Customer, in the delivery month | E16: Shrinkage as: %C5+ | F16: =F11/F10*100 -> 1.9644388 | I16: Tariff on Purchase
E17: Shrinkage as: %Blend | F17: =(F19-F12)/F19*100 -> 0.36419957 | I17: Trucking on Purchase
A18: C5 Density Slope | B18: =_xlfn.XLOOKUP($B$8,MonthlyData!$B:$B,MonthlyData!$Y:$Y) -> 0.17 | E18: Shrinkage as: % Shrunk Blend | F18: =(F19-F12)/F12*100 -> 0.36553084 | I18: Other
A19: Rainbow Interface % | B19: 0 | E19: vol blend w/o shrinkage | F19: =F8+F10 -> 25959.861 | I19: Netback | K19: =SUM(K14:K18) -> 640.75974 | L19: =SUM(L14:L18) -> 563.58949
E20: C5+ as % of dry crude | F20: =F10/F8*100 -> 22.75907
E21: C5+ as % of blend | F21: =F10/F12*100 -> 18.607392
A24: NovaCor Eqn
A25: ITERATIONS: | D25: vol C5+ | E25: Density Blend
A26: % C5+ in Total Blend (Fc) = | B26: =((B10-B12)/(B10-B11))*100 -> 17.106383 | C26: % | D26: =(B26/100*$B$9)/(1-B26/100) -> 4364.0113 | E26: =(D26*$B$11+$B$9*$B$10)/(D26+$B$9)/(1-B27/100) -> 927.99864
A27: Blend Shrinkage Factor (Sf) = | B27: =(0.0266*B26)-(0.0004*(POWER(B26,2)))+(0.000001339*(POWER(B26,3))) -> 0.34468123 | C27: % | D27: =(B9/(1-B26/100))*(B26/100) -> 4364.0113
A28: % C5+ in Total Blend (Fc) = | B28: =(((($B$10-$B$12)/($B$10-$B$11))+((B27/100)*$B$12)/($B$10-$B$11)))*100 -> 18.462814 | C28: % | D28: =(B28/100*$B$9)/(1-B28/100) -> 4788.4056 | E28: =(D28*$B$11+$B$9*$B$10)/(D28+$B$9)/(1-B29/100) -> 924.97177
A29: Blend Shrinkage Factor (Sf) = | B29: =(0.0266*B28)-(0.0004*(POWER(B28,2)))+(0.000001339*(POWER(B28,3))) -> 0.36318767 | C29: %
A30: % C5+ in Total Blend (Fc) = | B30: =(((($B$10-$B$12)/($B$10-$B$11))+((B29/100)*$B$12)/($B$10-$B$11)))*100 -> 18.535642 | C30: % | D30: =(B30/100*$B$9)/(1-B30/100) -> 4811.5917 | E30: =(D30*$B$11+$B$9*$B$10)/(D30+$B$9)/(1-B31/100) -> 924.80891
A31: Blend Shrinkage Factor (Sf) = | B31: =(0.0266*B30)-(0.0004*(POWER(B30,2)))+(0.000001339*(POWER(B30,3))) -> 0.36414721 | C31: %
A32: % C5+ in Total Blend (Fc) = | B32: =(((($B$10-$B$12)/($B$10-$B$11))+((B31/100)*$B$12)/($B$10-$B$11)))*100 -> 18.539418 | C32: % | D32: =(B32/100*$B$9)/(1-B32/100) -> 4812.795 | E32: =(D32*$B$11+$B$9*$B$10)/(D32+$B$9)/(1-B33/100) -> 924.80046
A33: Blend Shrinkage Factor (Sf) = | B33: =(0.0266*B32)-(0.0004*(POWER(B32,2)))+(0.000001339*(POWER(B32,3))) -> 0.36419687 | C33: %
A34: % C5+ in Total Blend (Fc) = | B34: =(((($B$10-$B$12)/($B$10-$B$11))+((B33/100)*$B$12)/($B$10-$B$11)))*100 -> 18.539614 | C34: % | D34: =(B34/100*$B$9)/(1-B34/100) -> 4812.8573 | E34: =(D34*$B$11+$B$9*$B$10)/(D34+$B$9)/(1-B35/100) -> 924.80002
A35: Blend Shrinkage Factor (Sf) = | B35: =(0.0266*B34)-(0.0004*(POWER(B34,2)))+(0.000001339*(POWER(B34,3))) -> 0.36419944 | C35: %
A36: % C5+ in Total Blend (Fc) = | B36: =(((($B$10-$B$12)/($B$10-$B$11))+((B35/100)*$B$12)/($B$10-$B$11)))*100 -> 18.539624 | C36: % | D36: =(B36/100*$B$9)/(1-B36/100) -> 4812.8605 | E36: =(D36*$B$11+$B$9*$B$10)/(D36+$B$9)/(1-B37/100) -> 924.8
A37: Blend Shrinkage Factor (Sf) = | B37: =(0.0266*B36)-(0.0004*(POWER(B36,2)))+(0.000001339*(POWER(B36,3))) -> 0.36419957 | C37: %
A39: Pricing | E39: =1/1.3378 -> 0.74749589
A41: Condensate price @ Edmonton | B41: =$K$19 -> 640.75974 | C41: CAD/M3
A42: Gibsons P/L Toll | B42: 2 | C42: CAD/M3
A43: C5 ENB Terminalling | B43: 3.39 | C43: CAD/M3
A44: Total Condensate price: | B44: =SUM(B41:B43) -> 646.14974 | C44: CAD/M3
A46: CHV Price (Edmonton) | B46: =$L$19 -> 563.58949 | C46: CAD/M3
A47: Pipeline Terminal Fee | B47: 0 | C47: CAD/M3
A48: Pipeline Tariff | B48: 0 | C48: CAD/M3
A49: Storage Fee | B49: 0 | C49: CAD/M3
A50: Heavy Blend in Gibsons Storage | B50: =SUM(B46:B49) -> 563.58949 | C50: CAD/M3
A52: Value of Heavy Blend: | B52: =B50*F12 -> 14577420 | C52: CAD | D52: =+B50*(F11/B9) -> 2.519741 | E52: Shrinkage
A53: Value of Condensate: | B53: =F10*B44 -> 3109828.6 | C53: CAD | D53: =+(B44-B50)*F10/F8 -> 18.789944 | E53: Cond
A54: Value of Raw Crude | B54: =(B52-B53)/B9 -> 542.27981 | C54: CAD/M3
A55: Rainbow Loss Allowance | B55: =-0.15%*B46 -> -0.84538424 | C55: CAD/M3
A57: Raw Heavy Price | B57: =SUM(B54:B55) -> 541.43442 | C57: CAD/M3
B58: =B57/6.29287/$L$11 -> 62.94257 | C58: USD/BBL
B59: =B58-$J$10 -> 62.94257 | C59: Diff to WTI
A61: Diluent Fee per M3 of Raw Crude | B61: =-(B46-(B57-B49-B48-B47-B55)) -> -21.309685 | C61: CAD/M3
A62: Diluent Fee per M3 of Blended Crude | B62: =(B61*F8)/F12 -> -17.422402 | C62: CAD/M3
A63: Diluent Cost per M3 of Blended Crude | B63: =-(B44*F10)/F12 -> -120.23161 | C63: CAD/M3

Sheet MonthlyData
B1: 1 | C1: =B1+1 -> 2 | D1: =C1+1 -> 3 | E1: =D1+1 -> 4 | F1: =E1+1 -> 5 | G1: =F1+1 -> 6 | H1: =G1+1 -> 7 | I1: =H1+1 -> 8 | J1: =I1+1 -> 9 | ... CE1: =CD1+1 -> 82
B2: YEAR | C2: Days per Month | D2: WTI CMA (USD/BBL) | E2: FX (CAD/USD) | F2: MSW DIFF (USD/BBL) | G2: MSW WADF (CAD/M3) | H2: MSW PAR (BASE) PRICE | I2: MSW PAR (BASE) PRICE | J2: MSW STREAM PRICE | K2: MSW to WTI | L2: C5+ vs. MSW DIFF | M2: FTSK C5+ DIFF | N2: FTSK C5+ PAR (BASE) PRICE | O2: FTSK C5+ PAR (BASE) PRICE | P2: FTSK C5+ STREAM PRICE | Q2: FTSK C5+ to WTI | R2: PEACE C5+ DIFF | S2: PEACE C5+ PAR (BASE) PRICE | T2: PEACE C5+ PAR (BASE) PRICE | U2: PEACE C5+ STREAM PRICE | V2: PEACE C5+ to WTI | W2: KAPS C5+ DIFF | X2: CRW C5+ ENB WADF | Y2: C5+ DENSITY SLOPE (CAD/M3 per KG/M3) | Z2: C5+ ALLOW PRICE | AA2: WCS DIFF | AB2: WCS PRICE | AC2: WCS PRICE | AD2: WCS Density | AE2: HEAVY ALLOW PRICE | AF2: ENB REF TEMP | AG2: MSW vs. WCS DIFF | AH2: WCS vs. WTI | AI2: WCS vs. C5+ (Diluent Cost) | AJ2: C4 to WTI | AK2: C4 PRICE | AL2: C4 PRICE | AM2: C4 Landed Marten Hills %WTI | AN2: MSY DIFF/INDEX | AO2: MSY to MSW DIFF | AP2: MSE DIFF/INDEX | AQ2: MSE vs. MSW DIFF | AR2: CAL DIFF | AS2: CAL WADF | AT2: CAL PAR (BASE) PRICE | AU2: CAL PAR (BASE) PRICE | AV2: CAL STREAM PRICE | AW2: CAL to WTI | AX2: LSB DIFF | AY2: LSB WADF | AZ2: LSB PAR (BASE) PRICE | BA2: LSB PAR (BASE) PRICE | BB2: LSB STREAM PRICE | BC2: LSB to WTI | BD2: BRN DIFF | BE2: BRN WADF | BF2: BRN PAR (BASE) PRICE | BG2: BRN PAR (BASE) PRICE | BH2: BRN STREAM PRICE | BI2: BRN to WTI | BJ2: BRS DIFF | BK2: BRS WADF | BL2: BRS PAR (BASE) PRICE | BM2: BRS PAR (BASE) PRICE | BN2: BRS STREAM PRICE | BO2: BRS to WTI | BP2: CHV Diff | BQ2: CHV PRICE | BR2: CHV PRICE | BS2: CWH Diff | BT2: CWH PRICE | BU2: CWH PRICE | BV2: LLB Diff | BW2: LLB PRICE | BX2: LLB PRICE | BY2: WCB Diff | BZ2: WCB PRICE | CA2: WCB PRICE | CB2: Spur Historical Physical Blended Crude (KG/M3) | CC2: Spur Blended Crude Density to get to 350cSt (Paper Blend Target) | CD2: Tamarack Blended Crude Density to get to 350cSt (Paper Blend Target) | CE2: Obisidan Blended Crude Density to get to 350cSt (Paper Blend Target)
B3: MONTH | C3: Days | D3: USD/BBL | E3: Rate | F3: USD/BBL | G3: CAD/M3 | H3: USD/BBL | I3: CAD/M3 | J3: CAD/M3 | K3: % | L3: USD/BBL | M3: USD/BBL | N3: USD/BBL | O3: CAD/M3 | P3: CAD/M3 | Q3: % | R3: USD/BBL | S3: USD/BBL | T3: CAD/M3 | U3: CAD/M3 | V3: % | W3: USD/BBL | X3: CAD/M3 | Y3: CAD/M3 per KG/M3 | Z3: CAD/M3 | AA3: USD/BBL | AB3: CAD/M3 | AC3: USD/BBL | AD3: KG/M3 | AE3: CAD/M3 | AF3: DEG C | AG3: USD/BBL | AH3: % | AI3: USD/BBL | AJ3: % | AK3: USD/BBL | AL3: CAD/M3 | AM3: % | AN3: USD/BBL | AO3: USD/BBL | AP3: USD/BBL | AQ3: USD/BBL | AR3: USD/BBL | AS3: CAD/M3 | AT3: USD/BBL | AU3: CAD/M3 | AV3: CAD/M3 | AW3: % | AX3: USD/BBL | AY3: CAD/M3 | AZ3: USD/BBL | BA3: CAD/M3 | BB3: CAD/M3 | BC3: % | BD3: USD/BBL | BE3: CAD/M3 | BF3: USD/BBL | BG3: CAD/M3 | BH3: CAD/M3 | BI3: % | BJ3: USD/BBL | BK3: CAD/M3 | BL3: USD/BBL | BM3: CAD/M3 | BN3: CAD/M3 | BO3: % | BP3: USD/BBL | BQ3: CAD/M3 | BR3: USD/BBL | BS3: USD/BBL | BT3: CAD/M3 | BU3: USD/BBL | BV3: USD/BBL | BW3: CAD/M3 | BX3: USD/BBL | BY3: USD/BBL | BZ3: CAD/M3 | CA3: USD/BBL
B4: 40544 | C4: 31 | D4: 89.58 | E4: 0.9938 | F4: -5.61 | G4: 0.28 | H4: =I4/($E4*6.29287) -> 84.014772 | I4: =(($D4+F4)*6.29287*$E4)+G4 -> 525.41614 | J4: =I4-G4 -> 525.13614 | K4: =(D4+F4)/D4 -> 0.93737441 | L4: =M4-F4 -> 7.33 | M4: 1.72 | N4: =O4/(E4*6.29287) -> 89.699387 | O4: =((D4+M4)*6.29287*E4)+X4 -> 560.96689 | P4: =O4-X4 -> 570.97689 | Q4: =(D4+M4)/D4 -> 1.0192007 | T4: =(($D4+R4)*$E4*6.29287)+X4 -> 550.21026 | U4: =T4-X4 -> 560.22026 | X4: -10.01 | Y4: 0.34 | AA4: -18.4 | AB4: =(D4+AA4)*E4*6.2898105 -> 444.93292 | AC4: =D4+AA4 -> 71.18 | AG4: =M4-AA4 -> 20.12 | AH4: =(D4+AA4)/D4 -> 0.79459701 | AR4: 0 | AS4: 0 | AT4: =AU4/($E4*6.29287) -> 89.58 | AU4: =(($D4+AR4)*6.29287*$E4)+AS4 -> 560.22026 | AV4: =AU4-AS4 -> 560.22026 | AX4: 0 | AY4: 0 | AZ4: =BA4/($E4*6.29287) -> 89.58 | BA4: =(($D4+AX4)*6.29287*$E4)+AY4 -> 560.22026 | BB4: =BA4-AY4 -> 560.22026 | BD4: 0 | BE4: 0 | BF4: =BG4/($E4*6.29287) -> 89.58 | BG4: =(($D4+BD4)*6.29287*$E4)+BE4 -> 560.22026 | BH4: =BG4-BE4 -> 560.22026 | BJ4: 0 | BK4: 0 | BL4: =BM4/($E4*6.29287) -> 89.58 | BM4: =(($D4+BJ4)*6.29287*$E4)+BK4 -> 560.22026 | BN4: =BM4-BK4 -> 560.22026 | BP4: =AA4+0.25 -> -18.15 | BS4: N/A | BT4: N/A | BU4: N/A | BY4: N/A | BZ4: N/A | CA4: N/A
B5: 40575 | C5: 28 | D5: 89.74 | E5: 0.9876 | F5: -4.94 | G5: -0.68 | H5: =I5/(E5*6.29287) -> 84.690584 | I5: =((D5+F5)*6.29287*E5)+G5 -> 526.3383 | J5: =I5-G5 -> 527.0183 | K5: =(D5+F5)/D5 -> 0.94495208 | L5: =M5-F5 -> 8.72 | M5: 3.78 | N5: =O5/(E5*6.29287) -> 91.727516 | O5: =((D5+M5)*6.29287*E5)+X5 -> 570.07169 | P5: =O5-X5 -> 581.21169 | Q5: =(D5+M5)/D5 -> 1.0421217 | T5: =(($D5+R5)*$E5*6.29287)+X5 -> 546.5796 | U5: =T5-X5 -> 557.7196 | X5: -11.14 | Y5: 0.5 | AA5: -26.33 | AB5: =(D5+AA5)*E5*6.2898105 -> 393.89131 | AC5: =D5+AA5 -> 63.41 | AG5: =M5-AA5 -> 30.11 | AH5: =(D5+AA5)/D5 -> 0.70659684 | AR5: 0 | AS5: 0 | AT5: =AU5/($E5*6.29287) -> 89.74 | AU5: =(($D5+AR5)*6.29287*$E5)+AS5 -> 557.7196 | AV5: =AU5-AS5 -> 557.7196 | AX5: 0 | AY5: 0 | AZ5: =BA5/($E5*6.29287) -> 89.74 | BA5: =(($D5+AX5)*6.29287*$E5)+AY5 -> 557.7196 | BB5: =BA5-AY5 -> 557.7196 | BD5: 0 | BE5: 0 | BF5: =BG5/($E5*6.29287) -> 89.74 | BG5: =(($D5+BD5)*6.29287*$E5)+BE5 -> 557.7196 | BH5: =BG5-BE5 -> 557.7196 | BJ5: 0 | BK5: 0 | BL5: =BM5/($E5*6.29287) -> 89.74 | BM5: =(($D5+BJ5)*6.29287*$E5)+BK5 -> 557.7196 | BN5: =BM5-BK5 -> 557.7196 | BP5: =AA5+0.25 -> -26.08 | BS5: N/A | BT5: N/A | BU5: N/A | BY5: N/A | BZ5: N/A | CA5: N/A
B6: 40603 | C6: 31 | D6: 102.98 | E6: 0.9766 | F6: -3.53 | G6: -0.82 | H6: =I6/(E6*6.29287) -> 99.316572 | I6: =((D6+F6)*6.29287*E6)+G6 -> 610.36159 | J6: =I6-G6 -> 611.18159 | K6: =(D6+F6)/D6 -> 0.9657215 | L6: =M6-F6 -> 10.94 | M6: 7.41 | N6: =O6/(E6*6.29287) -> 107.31789 | O6: =((D6+M6)*6.29287*E6)+X6 -> 659.53464 | P6: =O6-X6 -> 678.41464 | Q6: =(D6+M6)/D6 -> 1.0719557 | T6: =(($D6+R6)*$E6*6.29287)+X6 -> 613.99562 | U6: =T6-X6 -> 632.87562 | X6: -18.88 | Y6: 0.51 | AA6: -23.85 | AB6: =(D6+AA6)*E6*6.2898105 -> 486.06623 | AC6: =D6+AA6 -> 79.13 | AG6: =M6-AA6 -> 31.26 | AH6: =(D6+AA6)/D6 -> 0.76840163 | AR6: 0 | AS6: 0 | AT6: =AU6/($E6*6.29287) -> 102.98 | AU6: =(($D6+AR6)*6.29287*$E6)+AS6 -> 632.87562 | AV6: =AU6-AS6 -> 632.87562 | AX6: 0 | AY6: 0 | AZ6: =BA6/($E6*6.29287) -> 102.98 | BA6: =(($D6+AX6)*6.29287*$E6)+AY6 -> 632.87562 | BB6: =BA6-AY6 -> 632.87562 | BD6: 0 | BE6: 0 | BF6: =BG6/($E6*6.29287) -> 102.98 | BG6: =(($D6+BD6)*6.29287*$E6)+BE6 -> 632.87562 | BH6: =BG6-BE6 -> 632.87562 | BJ6: 0 | BK6: 0 | BL6: =BM6/($E6*6.29287) -> 102.98 | BM6: =(($D6+BJ6)*6.29287*$E6)+BK6 -> 632.87562 | BN6: =BM6-BK6 -> 632.87562 | BP6: =AA6+0.25 -> -23.6 | BS6: N/A | BT6: N/A | BU6: N/A | BY6: N/A | BZ6: N/A | CA6: N/A
B7: 40634 | C7: 30 | D7: 110.04 | E7: 0.9582 | F7: 5.76 | G7: -0.89 | H7: =I7/(E7*6.29287) -> 115.6524 | I7: =((D7+F7)*6.29287*E7)+G7 -> 697.36409 | J7: =I7-G7 -> 698.25409 | K7: =(D7+F7)/D7 -> 1.0523446 | L7: =M7-F7 -> 9.2 | M7: 14.96 | N7: =O7/(E7*6.29287) -> 121.28679 | O7: =((D7+M7)*6.29287*E7)+X7 -> 731.3385 | P7: =O7-X7 -> 753.7285 | Q7: =(D7+M7)/D7 -> 1.1359506 | T7: =(($D7+R7)*$E7*6.29287)+X7 -> 641.13228 | U7: =T7-X7 -> 663.52228 | X7: -22.39 | Y7: 0.51 | AA7: -20.34 | AB7: =(D7+AA7)*E7*6.2898105 -> 540.61261 | AC7: =D7+AA7 -> 89.7 | AG7: =M7-AA7 -> 35.3 | AH7: =(D7+AA7)/D7 -> 0.81515812 | AR7: 0 | AS7: 0 | AT7: =AU7/($E7*6.29287) -> 110.04 | AU7: =(($D7+AR7)*6.29287*$E7)+AS7 -> 663.52228 | AV7: =AU7-AS7 -> 663.52228 | AX7: 0 | AY7: 0 | AZ7: =BA7/($E7*6.29287) -> 110.04 | BA7: =(($D7+AX7)*6.29287*$E7)+AY7 -> 663.52228 | BB7: =BA7-AY7 -> 663.52228 | BD7: 0 | BE7: 0 | BF7: =BG7/($E7*6.29287) -> 110.04 | BG7: =(($D7+BD7)*6.29287*$E7)+BE7 -> 663.52228 | BH7: =BG7-BE7 -> 663.52228 | BJ7: 0 | BK7: 0 | BL7: =BM7/($E7*6.29287) -> 110.04 | BM7: =(($D7+BJ7)*6.29287*$E7)+BK7 -> 663.52228 | BN7: =BM7-BK7 -> 663.52228 | BP7: =AA7+0.25 -> -20.09 | BS7: N/A | BT7: N/A | BU7: N/A | BY7: N/A | BZ7: N/A | CA7: N/A
B8: 40664 | C8: 31 | D8: 101.36 | E8: 0.968 | F8: 3.24 | G8: -1.33 | H8: =I8/(E8*6.29287) -> 104.38166 | I8: =((D8+F8)*6.29287*E8)+G8 -> 635.84071 | J8: =I8-G8 -> 637.17071 | K8: =(D8+F8)/D8 -> 1.0319653 | L8: =M8-F8 -> 1.51 | M8: 4.75 | N8: =O8/(E8*6.29287) -> 101.0587 | O8: =((D8+M8)*6.29287*E8)+X8 -> 615.59887 | P8: =O8-X8 -> 646.36887 | Q8: =(D8+M8)/D8 -> 1.0468627 | T8: =(($D8+R8)*$E8*6.29287)+X8 -> 586.66425 | U8: =T8-X8 -> 617.43425 | X8: -30.77 | Y8: 0.29 | AA8: -15.7 | AB8: =(D8+AA8)*E8*6.2898105 -> 521.54404 | AC8: =D8+AA8 -> 85.66 | AG8: =M8-AA8 -> 20.45 | AH8: =(D8+AA8)/D8 -> 0.84510655 | AR8: 0 | AS8: 0 | AT8: =AU8/($E8*6.29287) -> 101.36 | AU8: =(($D8+AR8)*6.29287*$E8)+AS8 -> 617.43425 | AV8: =AU8-AS8 -> 617.43425 | AX8: 0 | AY8: 0 | AZ8: =BA8/($E8*6.29287) -> 101.36 | BA8: =(($D8+AX8)*6.29287*$E8)+AY8 -> 617.43425 | BB8: =BA8-AY8 -> 617.43425 | BD8: 0 | BE8: 0 | BF8: =BG8/($E8*6.29287) -> 101.36 | BG8: =(($D8+BD8)*6.29287*$E8)+BE8 -> 617.43425 | BH8: =BG8-BE8 -> 617.43425 | BJ8: 0 | BK8: 0 | BL8: =BM8/($E8*6.29287) -> 101.36 | BM8: =(($D8+BJ8)*6.29287*$E8)+BK8 -> 617.43425 | BN8: =BM8-BK8 -> 617.43425 | BP8: =AA8+0.25 -> -15.45 | BS8: N/A | BT8: N/A | BU8: N/A | BY8: N/A | BZ8: N/A | CA8: N/A
B9: 40695 | C9: 30 | D9: 96.29 | E9: 0.9768 | F9: 4.04 | G9: -1.36 | H9: =I9/(E9*6.29287) -> 100.10875 | I9: =((D9+F9)*6.29287*E9)+G9 -> 615.35601 | J9: =I9-G9 -> 616.71601 | K9: =(D9+F9)/D9 -> 1.0419566 | L9: =M9-F9 -> 6.22 | M9: 10.26 | N9: =O9/(E9*6.29287) -> 103.4411 | O9: =((D9+M9)*6.29287*E9)+X9 -> 635.83958 | P9: =O9-X9 -> 654.94958 | Q9: =(D9+M9)/D9 -> 1.1065531 | T9: =(($D9+R9)*$E9*6.29287)+X9 -> 572.77263 | U9: =T9-X9 -> 591.88263 | X9: -19.11 | Y9: 0.43 | AA9: -16.87 | AB9: =(D9+AA9)*E9*6.2898105 -> 487.9475 | AC9: =D9+AA9 -> 79.42 | AG9: =M9-AA9 -> 27.13 | AH9: =(D9+AA9)/D9 -> 0.82480008 | AR9: 0 | AS9: 0 | AT9: =AU9/($E9*6.29287) -> 96.29 | AU9: =(($D9+AR9)*6.29287*$E9)+AS9 -> 591.88263 | AV9: =AU9-AS9 -> 591.88263 | AX9: 0 | AY9: 0 | AZ9: =BA9/($E9*6.29287) -> 96.29 | BA9: =(($D9+AX9)*6.29287*$E9)+AY9 -> 591.88263 | BB9: =BA9-AY9 -> 591.88263 | BD9: 0 | BE9: 0 | BF9: =BG9/($E9*6.29287) -> 96.29 | BG9: =(($D9+BD9)*6.29287*$E9)+BE9 -> 591.88263 | BH9: =BG9-BE9 -> 591.88263 | BJ9: 0 | BK9: 0 | BL9: =BM9/($E9*6.29287) -> 96.29 | BM9: =(($D9+BJ9)*6.29287*$E9)+BK9 -> 591.88263 | BN9: =BM9-BK9 -> 591.88263 | BP9: =AA9+0.25 -> -16.62 | BS9: N/A | BT9: N/A | BU9: N/A | BY9: N/A | BZ9: N/A | CA9: N/A
B10: 40725 | C10: 31 | D10: 97.34 | E10: 0.9553 | F10: 2.69 | G10: -0.94 | H10: =I10/(E10*6.29287) -> 99.873635 | I10: =((D10+F10)*6.29287*E10)+G10 -> 600.39822 | J10: =I10-G10 -> 601.33822 | K10: =(D10+F10)/D10 -> 1.0276351 | L10: =M10-F10 -> 8.02 | M10: 10.71 | N10: =O10/(E10*6.29287) -> 104.27063 | O10: =((D10+M10)*6.29287*E10)+X10 -> 626.83108 | P10: =O10-X10 -> 649.55108 | Q10: =(D10+M10)/D10 -> 1.1100267 | T10: =(($D10+R10)*$E10*6.29287)+X10 -> 562.44707 | U10: =T10-X10 -> 585.16707 | X10: -22.72 | Y10: 0.47 | AA10: -19.03 | AB10: =(D10+AA10)*E10*6.2898105 -> 470.53785 | AC10: =D10+AA10 -> 78.31 | AG10: =M10-AA10 -> 29.74 | AH10: =(D10+AA10)/D10 -> 0.80449969 | AR10: 0 | AS10: 0 | AT10: =AU10/($E10*6.29287) -> 97.34 | AU10: =(($D10+AR10)*6.29287*$E10)+AS10 -> 585.16707 | AV10: =AU10-AS10 -> 585.16707 | AX10: 0 | AY10: 0 | AZ10: =BA10/($E10*6.29287) -> 97.34 | BA10: =(($D10+AX10)*6.29287*$E10)+AY10 -> 585.16707 | BB10: =BA10-AY10 -> 585.16707 | BD10: 0 | BE10: 0 | BF10: =BG10/($E10*6.29287) -> 97.34 | BG10: =(($D10+BD10)*6.29287*$E10)+BE10 -> 585.16707 | BH10: =BG10-BE10 -> 585.16707 | BJ10: 0 | BK10: 0 | BL10: =BM10/($E10*6.29287) -> 97.34 | BM10: =(($D10+BJ10)*6.29287*$E10)+BK10 -> 585.16707 | BN10: =BM10-BK10 -> 585.16707 | BP10: =AA10+0.25 -> -18.78 | BS10: N/A | BT10: N/A | BU10: N/A | BY10: N/A | BZ10: N/A | CA10: N/A
B11: 40756 | C11: 31 | D11: 86.34 | E11: 0.9828 | F11: 3.58 | G11: -1.1 | H11: =I11/(E11*6.29287) -> 89.74214 | I11: =((D11+F11)*6.29287*E11)+G11 -> 555.02217 | J11: =I11-G11 -> 556.12217 | K11: =(D11+F11)/D11 -> 1.041464 | L11: =M11-F11 -> 7.98 | M11: 11.56 | N11: =O11/(E11*6.29287) -> 94.074389 | O11: =((D11+M11)*6.29287*E11)+X11 -> 581.81554 | P11: =O11-X11 -> 605.47554 | Q11: =(D11+M11)/D11 -> 1.1338893 | T11: =(($D11+R11)*$E11*6.29287)+X11 -> 510.32118 | U11: =T11-X11 -> 533.98118 | X11: -23.66 | Y11: 0.49 | AA11: -19.83 | AB11: =(D11+AA11)*E11*6.2898105 -> 411.13993 | AC11: =D11+AA11 -> 66.51 | AG11: =M11-AA11 -> 31.39 | AH11: =(D11+AA11)/D11 -> 0.77032662 | AR11: 0 | AS11: 0 | AT11: =AU11/($E11*6.29287) -> 86.34 | AU11: =(($D11+AR11)*6.29287*$E11)+AS11 -> 533.98118 | AV11: =AU11-AS11 -> 533.98118 | AX11: 0 | AY11: 0 | AZ11: =BA11/($E11*6.29287) -> 86.34 | BA11: =(($D11+AX11)*6.29287*$E11)+AY11 -> 533.98118 | BB11: =BA11-AY11 -> 533.98118 | BD11: 0 | BE11: 0 | BF11: =BG11/($E11*6.29287) -> 86.34 | BG11: =(($D11+BD11)*6.29287*$E11)+BE11 -> 533.98118 | BH11: =BG11-BE11 -> 533.98118 | BJ11: 0 | BK11: 0 | BL11: =BM11/($E11*6.29287) -> 86.34 | BM11: =(($D11+BJ11)*6.29287*$E11)+BK11 -> 533.98118 | BN11: =BM11-BK11 -> 533.98118 | BP11: =AA11+0.25 -> -19.58 | BS11: N/A | BT11: N/A | BU11: N/A | BY11: N/A | BZ11: N/A | CA11: N/A
B12: 40787 | C12: 30 | D12: 85.61 | E12: 1.0026 | F12: 6.37 | G12: -0.98 | H12: =I12/(E12*6.29287) -> 91.824672 | I12: =((D12+F12)*6.29287*E12)+G12 -> 579.34311 | J12: =I12-G12 -> 580.32311 | K12: =(D12+F12)/D12 -> 1.0744072 | L12: =M12-F12 -> 7.19 | M12: 13.56 | N12: =O12/(E12*6.29287) -> 94.497482 | O12: =((D12+M12)*6.29287*E12)+X12 -> 596.20648 | P12: =O12-X12 -> 625.68648 | Q12: =(D12+M12)/D12 -> 1.1583927 | T12: =(($D12+R12)*$E12*6.29287)+X12 -> 510.65331 | U12: =T12-X12 -> 540.13331 | X12: -29.48 | Y12: 0.44 | AA12: -14.01 | AB12: =(D12+AA12)*E12*6.2898105 -> 451.52134 | AC12: =D12+AA12 -> 71.6 | AG12: =M12-AA12 -> 27.57 | AH12: =(D12+AA12)/D12 -> 0.83635089 | AR12: 0 | AS12: 0 | AT12: =AU12/($E12*6.29287) -> 85.61 | AU12: =(($D12+AR12)*6.29287*$E12)+AS12 -> 540.13331 | AV12: =AU12-AS12 -> 540.13331 | AX12: 0 | AY12: 0 | AZ12: =BA12/($E12*6.29287) -> 85.61 | BA12: =(($D12+AX12)*6.29287*$E12)+AY12 -> 540.13331 | BB12: =BA12-AY12 -> 540.13331 | BD12: 0 | BE12: 0 | BF12: =BG12/($E12*6.29287) -> 85.61 | BG12: =(($D12+BD12)*6.29287*$E12)+BE12 -> 540.13331 | BH12: =BG12-BE12 -> 540.13331 | BJ12: 0 | BK12: 0 | BL12: =BM12/($E12*6.29287) -> 85.61 | BM12: =(($D12+BJ12)*6.29287*$E12)+BK12 -> 540.13331 | BN12: =BM12-BK12 -> 540.13331 | BP12: =AA12+0.25 -> -13.76 | BS12: N/A | BT12: N/A | BU12: N/A | BY12: N/A | BZ12: N/A | CA12: N/A
B13: 40817 | C13: 31 | D13: 86.43 | E13: 1.0198 | F13: 5.2 | G13: -0.68 | H13: =I13/(E13*6.29287) -> 91.524039 | I13: =((D13+F13)*6.29287*E13)+G13 -> 587.35267 | J13: =I13-G13 -> 588.03267 | K13: =(D13+F13)/D13 -> 1.0601643 | L13: =M13-F13 -> 13.46 | M13: 18.66 | N13: =O13/(E13*6.29287) -> 101.83015 | O13: =((D13+M13)*6.29287*E13)+X13 -> 653.4918 | P13: =O13-X13 -> 674.4118 | Q13: =(D13+M13)/D13 -> 1.2158973 | T13: =(($D13+R13)*$E13*6.29287)+X13 -> 533.74183 | U13: =T13-X13 -> 554.66183 | X13: -20.92 | Y13: 0.47 | AA13: -9.89 | AB13: =(D13+AA13)*E13*6.2898105 -> 490.95425 | AC13: =D13+AA13 -> 76.54 | AG13: =M13-AA13 -> 28.55 | AH13: =(D13+AA13)/D13 -> 0.88557214 | AR13: 0 | AS13: 0 | AT13: =AU13/($E13*6.29287) -> 86.43 | AU13: =(($D13+AR13)*6.29287*$E13)+AS13 -> 554.66183 | AV13: =AU13-AS13 -> 554.66183 | AX13: 0 | AY13: 0 | AZ13: =BA13/($E13*6.29287) -> 86.43 | BA13: =(($D13+AX13)*6.29287*$E13)+AY13 -> 554.66183 | BB13: =BA13-AY13 -> 554.66183 | BD13: 0 | BE13: 0 | BF13: =BG13/($E13*6.29287) -> 86.43 | BG13: =(($D13+BD13)*6.29287*$E13)+BE13 -> 554.66183 | BH13: =BG13-BE13 -> 554.66183 | BJ13: 0 | BK13: 0 | BL13: =BM13/($E13*6.29287) -> 86.43 | BM13: =(($D13+BJ13)*6.29287*$E13)+BK13 -> 554.66183 | BN13: =BM13-BK13 -> 554.66183 | BP13: =AA13+0.25 -> -9.64 | BS13: N/A | BT13: N/A | BU13: N/A | BY13: N/A | BZ13: N/A | CA13: N/A
B14: 40848 | C14: 30 | D14: 97.16 | E14: 1.0258 | F14: 1.76 | G14: -0.93 | H14: =I14/(E14*6.29287) -> 98.775931 | I14: =((D14+F14)*6.29287*E14)+G14 -> 637.62096 | J14: =I14-G14 -> 638.55096 | K14: =(D14+F14)/D14 -> 1.0181145 | L14: =M14-F14 -> 14.7 | M14: 16.46 | N14: =O14/(E14*6.29287) -> 110.1453 | O14: =((D14+M14)*6.29287*E14)+X14 -> 711.01278 | P14: =O14-X14 -> 733.44278 | Q14: =(D14+M14)/D14 -> 1.1694113 | T14: =(($D14+R14)*$E14*6.29287)+X14 -> 604.75976 | U14: =T14-X14 -> 627.18976 | X14: -22.43 | Y14: 0.43 | AA14: -9.84 | AB14: =(D14+AA14)*E14*6.2898105 -> 563.39629 | AC14: =D14+AA14 -> 87.32 | AG14: =M14-AA14 -> 26.3 | AH14: =(D14+AA14)/D14 -> 0.89872375 | AR14: 0 | AS14: 0 | AT14: =AU14/($E14*6.29287) -> 97.16 | AU14: =(($D14+AR14)*6.29287*$E14)+AS14 -> 627.18976 | AV14: =AU14-AS14 -> 627.18976 | AX14: 0 | AY14: 0 | AZ14: =BA14/($E14*6.29287) -> 97.16 | BA14: =(($D14+AX14)*6.29287*$E14)+AY14 -> 627.18976 | BB14: =BA14-AY14 -> 627.18976 | BD14: 0 | BE14: 0 | BF14: =BG14/($E14*6.29287) -> 97.16 | BG14: =(($D14+BD14)*6.29287*$E14)+BE14 -> 627.18976 | BH14: =BG14-BE14 -> 627.18976 | BJ14: 0 | BK14: 0 | BL14: =BM14/($E14*6.29287) -> 97.16 | BM14: =(($D14+BJ14)*6.29287*$E14)+BK14 -> 627.18976 | BN14: =BM14-BK14 -> 627.18976 | BP14: =AA14+0.25 -> -9.59 | BS14: N/A | BT14: N/A | BU14: N/A | BY14: N/A | BZ14: N/A | CA14: N/A
B15: 40878 | C15: 31 | D15: 98.58 | E15: 1.0238 | F15: -2.67 | G15: -1.36 | H15: =I15/(E15*6.29287) -> 95.698906 | I15: =((D15+F15)*6.29287*E15)+G15 -> 616.55363 | J15: =I15-G15 -> 617.91363 | K15: =(D15+F15)/D15 -> 0.9729154 | L15: =M15-F15 -> 11.58 | M15: 8.91 | N15: =O15/(E15*6.29287) -> 104.21184 | O15: =((D15+M15)*6.29287*E15)+X15 -> 671.39941 | P15: =O15-X15 -> 692.51941 | Q15: =(D15+M15)/D15 -> 1.0903834 | T15: =(($D15+R15)*$E15*6.29287)+X15 -> 613.99548 | U15: =T15-X15 -> 635.11548 | X15: -21.12 | Y15: 0.33 | AA15: -11.72 | AB15: =(D15+AA15)*E15*6.2898105 -> 559.33566 | AC15: =D15+AA15 -> 86.86 | AG15: =M15-AA15 -> 20.63 | AH15: =(D15+AA15)/D15 -> 0.88111179 | AR15: 0 | AS15: 0 | AT15: =AU15/($E15*6.29287) -> 98.58 | AU15: =(($D15+AR15)*6.29287*$E15)+AS15 -> 635.11548 | AV15: =AU15-AS15 -> 635.11548 | AX15: 0 | AY15: 0 | AZ15: =BA15/($E15*6.29287) -> 98.58 | BA15: =(($D15+AX15)*6.29287*$E15)+AY15 -> 635.11548 | BB15: =BA15-AY15 -> 635.11548 | BD15: 0 | BE15: 0 | BF15: =BG15/($E15*6.29287) -> 98.58 | BG15: =(($D15+BD15)*6.29287*$E15)+BE15 -> 635.11548 | BH15: =BG15-BE15 -> 635.11548 | BJ15: 0 | BK15: 0 | BL15: =BM15/($E15*6.29287) -> 98.58 | BM15: =(($D15+BJ15)*6.29287*$E15)+BK15 -> 635.11548 | BN15: =BM15-BK15 -> 635.11548 | BP15: =AA15+0.25 -> -11.47 | BS15: N/A | BT15: N/A | BU15: N/A | BY15: N/A | BZ15: N/A | CA15: N/A
B16: 40909 | C16: 31 | D16: 100.32 | E16: 1.0133 | F16: -4.49 | G16: -1.96 | H16: =I16/(E16*6.29287) -> 95.522624 | I16: =((D16+F16)*6.29287*E16)+G16 -> 609.10624 | J16: =I16-G16 -> 611.06624 | K16: =(D16+F16)/D16 -> 0.95524322 | L16: =M16-F16 -> 10.47 | M16: 5.98 | N16: =O16/(E16*6.29287) -> 103.36425 | O16: =((D16+M16)*6.29287*E16)+X16 -> 659.10888 | P16: =O16-X16 -> 677.82888 | Q16: =(D16+M16)/D16 -> 1.0596093 | T16: =(($D16+R16)*$E16*6.29287)+X16 -> 620.97702 | U16: =T16-X16 -> 639.69702 | X16: -18.72 | Y16: 0.29 | AA16: -13.85 | AB16: =(D16+AA16)*E16*6.2898105 -> 551.11352 | AC16: =D16+AA16 -> 86.47 | AG16: =M16-AA16 -> 19.83 | AH16: =(D16+AA16)/D16 -> 0.86194179 | AJ16: 0.908 | AK16: =AL16/(6.29287*E16) -> 91.09056 | AL16: =(AJ16*D16)*6.29287*E16 -> 580.84489 | AR16: 0 | AS16: 0 | AT16: =AU16/($E16*6.29287) -> 100.32 | AU16: =(($D16+AR16)*6.29287*$E16)+AS16 -> 639.69702 | AV16: =AU16-AS16 -> 639.69702 | AX16: 0 | AY16: 0 | AZ16: =BA16/($E16*6.29287) -> 100.32 | BA16: =(($D16+AX16)*6.29287*$E16)+AY16 -> 639.69702 | BB16: =BA16-AY16 -> 639.69702 | BD16: 0 | BE16: 0 | BF16: =BG16/($E16*6.29287) -> 100.32 | BG16: =(($D16+BD16)*6.29287*$E16)+BE16 -> 639.69702 | BH16: =BG16-BE16 -> 639.69702 | BJ16: 0 | BK16: 0 | BL16: =BM16/($E16*6.29287) -> 100.32 | BM16: =(($D16+BJ16)*6.29287*$E16)+BK16 -> 639.69702 | BN16: =BM16-BK16 -> 639.69702 | BP16: =AA16+0.25 -> -13.6 | BS16: N/A | BT16: N/A | BU16: N/A | BY16: N/A | BZ16: N/A | CA16: N/A
B17: 40940 | C17: 29 | D17: 102.26 | E17: 0.9965 | F17: -7.14 | G17: -0.137 | H17: =I17/(E17*6.29287) -> 95.098153 | I17: =((D17+F17)*6.29287*E17)+G17 -> 596.34577 | J17: =I17-G17 -> 596.48277 | K17: =(D17+F17)/D17 -> 0.93017798 | L17: =M17-F17 -> 15.4 | M17: 8.26 | N17: =O17/(E17*6.29287) -> 108.2109 | O17: =((D17+M17)*6.29287*E17)+X17 -> 678.57378 | P17: =O17-X17 -> 693.05378 | Q17: =(D17+M17)/D17 -> 1.0807745 | T17: =(($D17+R17)*$E17*6.29287)+X17 -> 626.77661 | U17: =T17-X17 -> 641.25661 | X17: -14.48 | Y17: 0.41 | AA17: -19.22 | AB17: =(D17+AA17)*E17*6.2898105 -> 520.47779 | AC17: =D17+AA17 -> 83.04 | AG17: =M17-AA17 -> 27.48 | AH17: =(D17+AA17)/D17 -> 0.81204772 | AJ17: 0.885 | AK17: =AL17/(6.29287*E17) -> 90.5001 | AL17: =(AJ17*D17)*6.29287*E17 -> 567.5121 | AR17: 0 | AS17: 0 | AT17: =AU17/($E17*6.29287) -> 102.26 | AU17: =(($D17+AR17)*6.29287*$E17)+AS17 -> 641.25661 | AV17: =AU17-AS17 -> 641.25661 | AX17: 0 | AY17: 0 | AZ17: =BA17/($E17*6.29287) -> 102.26 | BA17: =(($D17+AX17)*6.29287*$E17)+AY17 -> 641.25661 | BB17: =BA17-AY17 -> 641.25661 | BD17: 0 | BE17: 0 | BF17: =BG17/($E17*6.29287) -> 102.26 | BG17: =(($D17+BD17)*6.29287*$E17)+BE17 -> 641.25661 | BH17: =BG17-BE17 -> 641.25661 | BJ17: 0 | BK17: 0 | BL17: =BM17/($E17*6.29287) -> 102.26 | BM17: =(($D17+BJ17)*6.29287*$E17)+BK17 -> 641.25661 | BN17: =BM17-BK17 -> 641.25661 | BP17: =AA17+0.25 -> -18.97 | BS17: N/A | BT17: N/A | BU17: N/A | BY17: N/A | BZ17: N/A | CA17: N/A
B18: 40969 | C18: 31 | D18: 106.21 | E18: 0.9939 | F18: -19.85 | G18: -0.492 | H18: =I18/(E18*6.29287) -> 86.281336 | I18: =((D18+F18)*6.29287*E18)+G18 -> 539.64519 | J18: =I18-G18 -> 540.13719 | K18: =(D18+F18)/D18 -> 0.81310611 | L18: =M18-F18 -> 27 | M18: 7.15 | N18: =O18/(E18*6.29287) -> 110.56329 | O18: =((D18+M18)*6.29287*E18)+X18 -> 691.51625 | P18: =O18-X18 -> 709.00825 | Q18: =(D18+M18)/D18 -> 1.0673195 | T18: =(($D18+R18)*$E18*6.29287)+X18 -> 646.79669 | U18: =T18-X18 -> 664.28869 | X18: -17.492 | Y18: 0.56 | AA18: -31.2 | AB18: =(D18+AA18)*E18*6.2898105 -> 468.92071 | AC18: =D18+AA18 -> 75.01 | AG18: =M18-AA18 -> 38.35 | AH18: =(D18+AA18)/D18 -> 0.70624235 | AJ18: 0.827 | AK18: =AL18/(6.29287*E18) -> 87.83567 | AL18: =(AJ18*D18)*6.29287*E18 -> 549.36675 | AR18: 0 | AS18: 0 | AT18: =AU18/($E18*6.29287) -> 106.21 | AU18: =(($D18+AR18)*6.29287*$E18)+AS18 -> 664.28869 | AV18: =AU18-AS18 -> 664.28869 | AX18: 0 | AY18: 0 | AZ18: =BA18/($E18*6.29287) -> 106.21 | BA18: =(($D18+AX18)*6.29287*$E18)+AY18 -> 664.28869 | BB18: =BA18-AY18 -> 664.28869 | BD18: 0 | BE18: 0 | BF18: =BG18/($E18*6.29287) -> 106.21 | BG18: =(($D18+BD18)*6.29287*$E18)+BE18 -> 664.28869 | BH18: =BG18-BE18 -> 664.28869 | BJ18: 0 | BK18: 0 | BL18: =BM18/($E18*6.29287) -> 106.21 | BM18: =(($D18+BJ18)*6.29287*$E18)+BK18 -> 664.28869 | BN18: =BM18-BK18 -> 664.28869 | BP18: =AA18+0.25 -> -30.95 | BS18: N/A | BT18: N/A | BU18: N/A | BY18: N/A | BZ18: N/A | CA18: N/A
B19: 41000 | C19: 30 | D19: 103.35 | E19: 0.9926 | F19: -18.53 | G19: -0.378 | H19: =I19/(E19*6.29287) -> 84.759484 | I19: =((D19+F19)*6.29287*E19)+G19 -> 529.4334 | J19: =I19-G19 -> 529.8114 | K19: =(D19+F19)/D19 -> 0.82070634 | L19: =M19-F19 -> 23.19 | M19: 4.66 | N19: =O19/(E19*6.29287) -> 104.2625 | O19: =((D19+M19)*6.29287*E19)+X19 -> 651.25516 | P19: =O19-X19 -> 674.66316 | Q19: =(D19+M19)/D19 -> 1.0450895 | T19: =(($D19+R19)*$E19*6.29287)+X19 -> 622.14739 | U19: =T19-X19 -> 645.55539 | X19: -23.408 | Y19: 0.55 | AA19: -32.94 | AB19: =(D19+AA19)*E19*6.2898105 -> 439.58835 | AC19: =D19+AA19 -> 70.41 | AG19: =M19-AA19 -> 37.6 | AH19: =(D19+AA19)/D19 -> 0.68127721 | AJ19: 0.845 | AK19: =AL19/(6.29287*E19) -> 87.33075 | AL19: =(AJ19*D19)*6.29287*E19 -> 545.4943 | AR19: 0 | AS19: 0 | AT19: =AU19/($E19*6.29287) -> 103.35 | AU19: =(($D19+AR19)*6.29287*$E19)+AS19 -> 645.55539 | AV19: =AU19-AS19 -> 645.55539 | AX19: 0 | AY19: 0 | AZ19: =BA19/($E19*6.29287) -> 103.35 | BA19: =(($D19+AX19)*6.29287*$E19)+AY19 -> 645.55539 | BB19: =BA19-AY19 -> 645.55539 | BD19: 0 | BE19: 0 | BF19: =BG19/($E19*6.29287) -> 103.35 | BG19: =(($D19+BD19)*6.29287*$E19)+BE19 -> 645.55539 | BH19: =BG19-BE19 -> 645.55539 | BJ19: 0 | BK19: 0 | BL19: =BM19/($E19*6.29287) -> 103.35 | BM19: =(($D19+BJ19)*6.29287*$E19)+BK19 -> 645.55539 | BN19: =BM19-BK19 -> 645.55539 | BP19: =AA19+0.25 -> -32.69 | BS19: N/A | BT19: N/A | BU19: N/A | BY19: N/A | BZ19: N/A | CA19: N/A
B20: 41041 | C20: 31 | D20: 94.72 | E20: 1.0098 | F20: -8.11 | G20: -0.419 | H20: =I20/(E20*6.29287) -> 86.544063 | I20: =((D20+F20)*6.29287*E20)+G20 -> 549.94772 | J20: =I20-G20 -> 550.36672 | K20: =(D20+F20)/D20 -> 0.91437922 | L20: =M20-F20 -> 15.84 | M20: 7.73 | N20: =O20/(E20*6.29287) -> 98.583001 | O20: =((D20+M20)*6.29287*E20)+X20 -> 626.44964 | P20: =O20-X20 -> 651.02264 | Q20: =(D20+M20)/D20 -> 1.081609 | T20: =(($D20+R20)*$E20*6.29287)+X20 -> 577.32904 | U20: =T20-X20 -> 601.90204 | X20: -24.573 | Y20: 0.4 | AA20: -19.61 | AB20: =(D20+AA20)*E20*6.2898105 -> 477.05746 | AC20: =D20+AA20 -> 75.11 | AG20: =M20-AA20 -> 27.34 | AH20: =(D20+AA20)/D20 -> 0.79296875 | AJ20: 0.816 | AK20: =AL20/(6.29287*E20) -> 77.29152 | AL20: =(AJ20*D20)*6.29287*E20 -> 491.15207 | AR20: 0 | AS20: 0 | AT20: =AU20/($E20*6.29287) -> 94.72 | AU20: =(($D20+AR20)*6.29287*$E20)+AS20 -> 601.90204 | AV20: =AU20-AS20 -> 601.90204 | AX20: 0 | AY20: 0 | AZ20: =BA20/($E20*6.29287) -> 94.72 | BA20: =(($D20+AX20)*6.29287*$E20)+AY20 -> 601.90204 | BB20: =BA20-AY20 -> 601.90204 | BD20: 0 | BE20: 0 | BF20: =BG20/($E20*6.29287) -> 94.72 | BG20: =(($D20+BD20)*6.29287*$E20)+BE20 -> 601.90204 | BH20: =BG20-BE20 -> 601.90204 | BJ20: 0 | BK20: 0 | BL20: =BM20/($E20*6.29287) -> 94.72 | BM20: =(($D20+BJ20)*6.29287*$E20)+BK20 -> 601.90204 | BN20: =BM20-BK20 -> 601.90204 | BP20: =AA20+0.25 -> -19.36 | BS20: N/A | BT20: N/A | BU20: N/A | BY20: N/A | BZ20: N/A | CA20: N/A
B21: 41072 | C21: 30 | D21: 82.41 | E21: 1.0281 | F21: -3.71 | G21: 0.145 | H21: =I21/(E21*6.29287) -> 78.722412 | I21: =((D21+F21)*6.29287*E21)+G21 -> 509.31036 | J21: =I21-G21 -> 509.16536 | K21: =(D21+F21)/D21 -> 0.95498119 | L21: =M21-F21 -> 9.23 | M21: 5.52 | N21: =O21/(E21*6.29287) -> 85.140071 | O21: =((D21+M21)*6.29287*E21)+X21 -> 550.83069 | P21: =O21-X21 -> 568.88069 | Q21: =(D21+M21)/D21 -> 1.0669822 | T21: =(($D21+R21)*$E21*6.29287)+X21 -> 515.11795 | U21: =T21-X21 -> 533.16795 | X21: -18.05 | Y21: 0.31 | AA21: -16.04 | AB21: =(D21+AA21)*E21*6.2898105 -> 429.1852 | AC21: =D21+AA21 -> 66.37 | AG21: =M21-AA21 -> 21.56 | AH21: =(D21+AA21)/D21 -> 0.80536343 | AJ21: 0.726 | AK21: =AL21/(6.29287*E21) -> 59.82966 | AL21: =(AJ21*D21)*6.29287*E21 -> 387.07993 | AR21: 0 | AS21: 0 | AT21: =AU21/($E21*6.29287) -> 82.41 | AU21: =(($D21+AR21)*6.29287*$E21)+AS21 -> 533.16795 | AV21: =AU21-AS21 -> 533.16795 | AX21: 0 | AY21: 0 | AZ21: =BA21/($E21*6.29287) -> 82.41 | BA21: =(($D21+AX21)*6.29287*$E21)+AY21 -> 533.16795 | BB21: =BA21-AY21 -> 533.16795 | BD21: 0 | BE21: 0 | BF21: =BG21/($E21*6.29287) -> 82.41 | BG21: =(($D21+BD21)*6.29287*$E21)+BE21 -> 533.16795 | BH21: =BG21-BE21 -> 533.16795 | BJ21: 0 | BK21: 0 | BL21: =BM21/($E21*6.29287) -> 82.41 | BM21: =(($D21+BJ21)*6.29287*$E21)+BK21 -> 533.16795 | BN21: =BM21-BK21 -> 533.16795 | BP21: =AA21+0.25 -> -15.79 | BS21: N/A | BT21: N/A | BU21: N/A | BY21: N/A | BZ21: N/A | CA21: N/A
B22: 41102 | C22: 31 | D22: 87.93 | E22: 1.0139 | F22: -12.99 | G22: 0.488 | H22: =I22/(E22*6.29287) -> 75.016485 | I22: =((D22+F22)*6.29287*E22)+G22 -> 478.63075 | J22: =I22-G22 -> 478.14275 | K22: =(D22+F22)/D22 -> 0.85226885 | L22: =M22-F22 -> 15.8 | M22: 2.81 | N22: =O22/(E22*6.29287) -> 87.668847 | O22: =((D22+M22)*6.29287*E22)+X22 -> 559.35713 | P22: =O22-X22 -> 578.95213 | Q22: =(D22+M22)/D22 -> 1.0319572 | T22: =(($D22+R22)*$E22*6.29287)+X22 -> 541.42837 | U22: =T22-X22 -> 561.02337 | X22: -19.595 | Y22: 0.39 | AA22: -23.65 | AB22: =(D22+AA22)*E22*6.2898105 -> 409.92891 | AC22: =D22+AA22 -> 64.28 | AG22: =M22-AA22 -> 26.46 | AH22: =(D22+AA22)/D22 -> 0.73103605 | AJ22: 0.711 | AK22: =AL22/(6.29287*E22) -> 62.51823 | AL22: =(AJ22*D22)*6.29287*E22 -> 398.88762 | AR22: 0 | AS22: 0 | AT22: =AU22/($E22*6.29287) -> 87.93 | AU22: =(($D22+AR22)*6.29287*$E22)+AS22 -> 561.02337 | AV22: =AU22-AS22 -> 561.02337 | AX22: 0 | AY22: 0 | AZ22: =BA22/($E22*6.29287) -> 87.93 | BA22: =(($D22+AX22)*6.29287*$E22)+AY22 -> 561.02337 | BB22: =BA22-AY22 -> 561.02337 | BD22: 0 | BE22: 0 | BF22: =BG22/($E22*6.29287) -> 87.93 | BG22: =(($D22+BD22)*6.29287*$E22)+BE22 -> 561.02337 | BH22: =BG22-BE22 -> 561.02337 | BJ22: 0 | BK22: 0 | BL22: =BM22/($E22*6.29287) -> 87.93 | BM22: =(($D22+BJ22)*6.29287*$E22)+BK22 -> 561.02337 | BN22: =BM22-BK22 -> 561.02337 | BP22: =AA22+0.25 -> -23.4 | BS22: N/A | BT22: N/A | BU22: N/A | BY22: N/A | BZ22: N/A | CA22: N/A
B23: 41133 | C23: 31 | D23: 94.16 | E23: 0.9921 | F23: -6.74 | G23: 0.719 | H23: =I23/(E23*6.29287) -> 87.535166 | I23: =((D23+F23)*6.29287*E23)+G23 -> 546.49573 | J23: =I23-G23 -> 545.77673 | K23: =(D23+F23)/D23 -> 0.92841971 | L23: =M23-F23 -> 9.83 | M23: 3.09 | N23: =O23/(E23*6.29287) -> 94.094865 | O23: =((D23+M23)*6.29287*E23)+X23 -> 587.44895 | P23: =O23-X23 -> 607.14695 | Q23: =(D23+M23)/D23 -> 1.0328165 | T23: =(($D23+R23)*$E23*6.29287)+X23 -> 568.1576 | U23: =T23-X23 -> 587.8556 | X23: -19.698 | Y23: 0.39 | AA23: -25.13 | AB23: =(D23+AA23)*E23*6.2898105 -> 430.75555 | AC23: =D23+AA23 -> 69.03 | AG23: =M23-AA23 -> 28.22 | AH23: =(D23+AA23)/D23 -> 0.73311385 | AJ23: 0.731 | AK23: =AL23/(6.29287*E23) -> 68.83096 | AL23: =(AJ23*D23)*6.29287*E23 -> 429.72244 | AR23: 0 | AS23: 0 | AT23: =AU23/($E23*6.29287) -> 94.16 | AU23: =(($D23+AR23)*6.29287*$E23)+AS23 -> 587.8556 | AV23: =AU23-AS23 -> 587.8556 | AX23: 0 | AY23: 0 | AZ23: =BA23/($E23*6.29287) -> 94.16 | BA23: =(($D23+AX23)*6.29287*$E23)+AY23 -> 587.8556 | BB23: =BA23-AY23 -> 587.8556 | BD23: 0 | BE23: 0 | BF23: =BG23/($E23*6.29287) -> 94.16 | BG23: =(($D23+BD23)*6.29287*$E23)+BE23 -> 587.8556 | BH23: =BG23-BE23 -> 587.8556 | BJ23: 0 | BK23: 0 | BL23: =BM23/($E23*6.29287) -> 94.16 | BM23: =(($D23+BJ23)*6.29287*$E23)+BK23 -> 587.8556 | BN23: =BM23-BK23 -> 587.8556 | BP23: =AA23+0.25 -> -24.88 | BS23: N/A | BT23: N/A | BU23: N/A | BY23: N/A | BZ23: N/A | CA23: N/A
B24: 41164 | C24: 30 | D24: 94.56 | E24: 0.9783 | F24: -1.89 | G24: 0.113 | H24: =I24/(E24*6.29287) -> 92.688355 | I24: =((D24+F24)*6.29287*E24)+G24 -> 570.61869 | J24: =I24-G24 -> 570.50569 | K24: =(D24+F24)/D24 -> 0.98001269 | L24: =M24-F24 -> 7.74 | M24: 5.85 | N24: =O24/(E24*6.29287) -> 96.578325 | O24: =((D24+M24)*6.29287*E24)+X24 -> 594.56656 | P24: =O24-X24 -> 618.15556 | Q24: =(D24+M24)/D24 -> 1.0618655 | T24: =(($D24+R24)*$E24*6.29287)+X24 -> 558.55212 | U24: =T24-X24 -> 582.14112 | X24: -23.589 | Y24: 0.3 | AA24: -16.39 | AB24: =(D24+AA24)*E24*6.2898105 -> 481.00515 | AC24: =D24+AA24 -> 78.17 | AG24: =M24-AA24 -> 22.24 | AH24: =(D24+AA24)/D24 -> 0.8266709 | AJ24: 0.788 | AK24: =AL24/(6.29287*E24) -> 74.51328 | AL24: =(AJ24*D24)*6.29287*E24 -> 458.7272 | AR24: 0 | AS24: 0 | AT24: =AU24/($E24*6.29287) -> 94.56 | AU24: =(($D24+AR24)*6.29287*$E24)+AS24 -> 582.14112 | AV24: =AU24-AS24 -> 582.14112 | AX24: 0 | AY24: 0 | AZ24: =BA24/($E24*6.29287) -> 94.56 | BA24: =(($D24+AX24)*6.29287*$E24)+AY24 -> 582.14112 | BB24: =BA24-AY24 -> 582.14112 | BD24: 0 | BE24: 0 | BF24: =BG24/($E24*6.29287) -> 94.56 | BG24: =(($D24+BD24)*6.29287*$E24)+BE24 -> 582.14112 | BH24: =BG24-BE24 -> 582.14112 | BJ24: 0 | BK24: 0 | BL24: =BM24/($E24*6.29287) -> 94.56 | BM24: =(($D24+BJ24)*6.29287*$E24)+BK24 -> 582.14112 | BN24: =BM24-BK24 -> 582.14112 | BP24: =AA24+0.25 -> -16.14 | BS24: N/A | BT24: N/A | BU24: N/A | BY24: N/A | BZ24: N/A | CA24: N/A
B25: 41183 | C25: 31 | D25: 89.57 | E25: 0.9872 | F25: 3.74 | G25: -0.258 | H25: =I25/(E25*6.29287) -> 93.26847 | I25: =((D25+F25)*6.29287*E25)+G25 -> 579.4137 | J25: =I25-G25 -> 579.6717 | K25: =(D25+F25)/D25 -> 1.0417551 | L25: =M25-F25 -> 4.7 | M25: 8.44 | N25: =O25/(E25*6.29287) -> 94.966371 | O25: =((D25+M25)*6.29287*E25)+X25 -> 589.96161 | P25: =O25-X25 -> 608.86961 | Q25: =(D25+M25)/D25 -> 1.094228 | T25: =(($D25+R25)*$E25*6.29287)+X25 -> 537.52962 | U25: =T25-X25 -> 556.43762 | X25: -18.908 | Y25: 0.24 | AA25: -9.69 | AB25: =(D25+AA25)*E25*6.2898105 -> 495.99896 | AC25: =D25+AA25 -> 79.88 | AG25: =M25-AA25 -> 18.13 | AH25: =(D25+AA25)/D25 -> 0.89181646 | AJ25: 0.848 | AK25: =AL25/(6.29287*E25) -> 75.95536 | AL25: =(AJ25*D25)*6.29287*E25 -> 471.8591 | AR25: 0 | AS25: 0 | AT25: =AU25/($E25*6.29287) -> 89.57 | AU25: =(($D25+AR25)*6.29287*$E25)+AS25 -> 556.43762 | AV25: =AU25-AS25 -> 556.43762 | AX25: 0 | AY25: 0 | AZ25: =BA25/($E25*6.29287) -> 89.57 | BA25: =(($D25+AX25)*6.29287*$E25)+AY25 -> 556.43762 | BB25: =BA25-AY25 -> 556.43762 | BD25: 0 | BE25: 0 | BF25: =BG25/($E25*6.29287) -> 89.57 | BG25: =(($D25+BD25)*6.29287*$E25)+BE25 -> 556.43762 | BH25: =BG25-BE25 -> 556.43762 | BJ25: 0 | BK25: 0 | BL25: =BM25/($E25*6.29287) -> 89.57 | BM25: =(($D25+BJ25)*6.29287*$E25)+BK25 -> 556.43762 | BN25: =BM25-BK25 -> 556.43762 | BP25: =AA25+0.25 -> -9.44 | BS25: N/A | BT25: N/A | BU25: N/A | BY25: N/A | BZ25: N/A | CA25: N/A
B26: 41214 | C26: 30 | D26: 86.73 | E26: 0.997 | F26: -0.56 | G26: -0.02 | H26: =I26/(E26*6.29287) -> 86.166812 | I26: =((D26+F26)*6.29287*E26)+G26 -> 540.60984 | J26: =I26-G26 -> 540.62984 | K26: =(D26+F26)/D26 -> 0.99354318 | L26: =M26-F26 -> 8.62 | M26: 8.06 | N26: =O26/(E26*6.29287) -> 92.127261 | O26: =((D26+M26)*6.29287*E26)+X26 -> 578.00564 | P26: =O26-X26 -> 594.71164 | Q26: =(D26+M26)/D26 -> 1.0929321 | T26: =(($D26+R26)*$E26*6.29287)+X26 -> 527.43727 | U26: =T26-X26 -> 544.14327 | X26: -16.706 | Y26: 0.33 | AA26: -14.27 | AB26: =(D26+AA26)*E26*6.2898105 -> 454.39239 | AC26: =D26+AA26 -> 72.46 | AG26: =M26-AA26 -> 22.33 | AH26: =(D26+AA26)/D26 -> 0.83546639 | AJ26: 0.916 | AK26: =AL26/(6.29287*E26) -> 79.44468 | AL26: =(AJ26*D26)*6.29287*E26 -> 498.43524 | AR26: 0 | AS26: 0 | AT26: =AU26/($E26*6.29287) -> 86.73 | AU26: =(($D26+AR26)*6.29287*$E26)+AS26 -> 544.14327 | AV26: =AU26-AS26 -> 544.14327 | AX26: 0 | AY26: 0 | AZ26: =BA26/($E26*6.29287) -> 86.73 | BA26: =(($D26+AX26)*6.29287*$E26)+AY26 -> 544.14327 | BB26: =BA26-AY26 -> 544.14327 | BD26: 0 | BE26: 0 | BF26: =BG26/($E26*6.29287) -> 86.73 | BG26: =(($D26+BD26)*6.29287*$E26)+BE26 -> 544.14327 | BH26: =BG26-BE26 -> 544.14327 | BJ26: 0 | BK26: 0 | BL26: =BM26/($E26*6.29287) -> 86.73 | BM26: =(($D26+BJ26)*6.29287*$E26)+BK26 -> 544.14327 | BN26: =BM26-BK26 -> 544.14327 | BP26: =AA26+0.25 -> -14.02 | BS26: N/A | BT26: N/A | BU26: N/A | BY26: N/A | BZ26: N/A | CA26: N/A
B27: 41244 | C27: 31 | D27: 88.25 | E27: 0.9896 | F27: -13.15 | G27: 0.386 | H27: =I27/(E27*6.29287) -> 75.161984 | I27: =((D27+F27)*6.29287*E27)+G27 -> 468.06555 | J27: =I27-G27 -> 467.67955 | K27: =(D27+F27)/D27 -> 0.8509915 | L27: =M27-F27 -> 26.37 | M27: 13.22 | N27: =O27/(E27*6.29287) -> 99.355964 | O27: =((D27+M27)*6.29287*E27)+X27 -> 618.73173 | P27: =O27-X27 -> 631.89673 | Q27: =(D27+M27)/D27 -> 1.1498017 | T27: =(($D27+R27)*$E27*6.29287)+X27 -> 536.40518 | U27: =T27-X27 -> 549.57018 | X27: -13.165 | Y27: 0.66 | AA27: -30.37 | AB27: =(D27+AA27)*E27*6.2898105 -> 360.26807 | AC27: =D27+AA27 -> 57.88 | AG27: =M27-AA27 -> 43.59 | AH27: =(D27+AA27)/D27 -> 0.65586402 | AJ27: 0.932 | AK27: =AL27/(6.29287*E27) -> 82.249 | AL27: =(AJ27*D27)*6.29287*E27 -> 512.19941 | AR27: 0 | AS27: 0 | AT27: =AU27/($E27*6.29287) -> 88.25 | AU27: =(($D27+AR27)*6.29287*$E27)+AS27 -> 549.57018 | AV27: =AU27-AS27 -> 549.57018 | AX27: 0 | AY27: 0 | AZ27: =BA27/($E27*6.29287) -> 88.25 | BA27: =(($D27+AX27)*6.29287*$E27)+AY27 -> 549.57018 | BB27: =BA27-AY27 -> 549.57018 | BD27: 0 | BE27: 0 | BF27: =BG27/($E27*6.29287) -> 88.25 | BG27: =(($D27+BD27)*6.29287*$E27)+BE27 -> 549.57018 | BH27: =BG27-BE27 -> 549.57018 | BJ27: 0 | BK27: 0 | BL27: =BM27/($E27*6.29287) -> 88.25 | BM27: =(($D27+BJ27)*6.29287*$E27)+BK27 -> 549.57018 | BN27: =BM27-BK27 -> 549.57018 | BP27: =AA27+0.25 -> -30.12 | BS27: N/A | BT27: N/A | BU27: N/A | BY27: N/A | BZ27: N/A | CA27: N/A
... B39: 41609 | C39: 31 | D39: 97.8943 | E39: 1.0639 | F39: -19.31 | G39: -1.3 | H39: =I39/(E39*6.29287) -> 78.390125 | I39: =((D39+F39)*6.29287*E39)+G39 -> 524.82066 | J39: =I39-G39 -> 526.12066 | K39: =(D39+F39)/D39 -> 0.80274643 | L39: =M39-F39 -> 17.93 | M39: -1.38 | N39: =O39/(E39*6.29287) -> 94.390322 | O39: =((D39+M39)*6.29287*E39)+X39 -> 631.94173 | P39: =O39-X39 -> 646.16173 | Q39: =(D39+M39)/D39 -> 0.98590316 | T39: =(($D39+R39)*$E39*6.29287)+X39 -> 641.18081 | U39: =T39-X39 -> 655.40081 | X39: -14.22 | Y39: 0.6 | AA39: -38.94 | AB39: =(D39+AA39)*E39*6.2898105 -> 394.50622 | AC39: =D39+AA39 -> 58.9543 | AG39: =M39-AA39 -> 37.56 | AH39: =(D39+AA39)/D39 -> 0.60222403 | AJ39: 0.761 | AK39: =AL39/(6.29287*E39) -> 74.497562 | AL39: =(AJ39*D39)*6.29287*E39 -> 498.76002 | AR39: 0 | AS39: 0 | AT39: =AU39/($E39*6.29287) -> 97.8943 | AU39: =(($D39+AR39)*6.29287*$E39)+AS39 -> 655.40081 | AV39: =AU39-AS39 -> 655.40081 | AX39: 0 | AY39: 0 | AZ39: =BA39/($E39*6.29287) -> 97.8943 | BA39: =(($D39+AX39)*6.29287*$E39)+AY39 -> 655.40081 | BB39: =BA39-AY39 -> 655.40081 | BD39: 0 | BE39: 0 | BF39: =BG39/($E39*6.29287) -> 97.8943 | BG39: =(($D39+BD39)*6.29287*$E39)+BE39 -> 655.40081 | BH39: =BG39-BE39 -> 655.40081 | BJ39: 0 | BK39: 0 | BL39: =BM39/($E39*6.29287) -> 97.8943 | BM39: =(($D39+BJ39)*6.29287*$E39)+BK39 -> 655.40081 | BN39: =BM39-BK39 -> 655.40081 | BP39: =AA39+0.25 -> -38.69 | BS39: N/A | BT39: N/A | BU39: N/A | BY39: N/A | BZ39: N/A | CA39: N/A
B40: 41640 | C40: 31 | D40: 94.86 | E40: 1.0942 | F40: -13.07 | G40: -0.58 | H40: =I40/(E40*6.29287) -> 81.705767 | I40: =((D40+F40)*6.29287*E40)+G40 -> 562.598 | J40: =I40-G40 -> 563.178 | K40: =(D40+F40)/D40 -> 0.86221801 | L40: =M40-F40 -> 16.42 | M40: 3.35 | N40: =O40/(E40*6.29287) -> 95.330101 | O40: =((D40+M40)*6.29287*E40)+X40 -> 656.41051 | P40: =O40-X40 -> 676.24051 | Q40: =(D40+M40)/D40 -> 1.0353152 | T40: =(($D40+R40)*$E40*6.29287)+X40 -> 633.34355 | U40: =T40-X40 -> 653.17355 | X40: -19.83 | Y40: 0.49 | AA40: -29.17 | AB40: =(D40+AA40)*E40*6.2898105 -> 452.09899 | AC40: =D40+AA40 -> 65.69 | AG40: =M40-AA40 -> 32.52 | AH40: =(D40+AA40)/D40 -> 0.6924942 | AR40: 0 | AS40: 0 | AT40: =AU40/($E40*6.29287) -> 94.86 | AU40: =(($D40+AR40)*6.29287*$E40)+AS40 -> 653.17355 | AV40: =AU40-AS40 -> 653.17355 | AX40: 0 | AY40: 0 | AZ40: =BA40/($E40*6.29287) -> 94.86 | BA40: =(($D40+AX40)*6.29287*$E40)+AY40 -> 653.17355 | BB40: =BA40-AY40 -> 653.17355 | BD40: 0 | BE40: 0 | BF40: =BG40/($E40*6.29287) -> 94.86 | BG40: =(($D40+BD40)*6.29287*$E40)+BE40 -> 653.17355 | BH40: =BG40-BE40 -> 653.17355 | BJ40: 0 | BK40: 0 | BL40: =BM40/($E40*6.29287) -> 94.86 | BM40: =(($D40+BJ40)*6.29287*$E40)+BK40 -> 653.17355 | BN40: =BM40-BK40 -> 653.17355 | BP40: =AA40+0.25 -> -28.92 | BS40: N/A | BT40: N/A | BU40: N/A | BY40: N/A | BZ40: N/A | CA40: N/A
B41: 41671 | C41: 28 | D41: 100.68 | E41: 1.1055 | F41: -5.07 | G41: -0.4553 | H41: =I41/(E41*6.29287) -> 95.544553 | I41: =((D41+F41)*6.29287*E41)+G41 -> 664.68127 | J41: =I41-G41 -> 665.13657 | K41: =(D41+F41)/D41 -> 0.94964243 | L41: =M41-F41 -> 10.22 | M41: 5.15 | N41: =O41/(E41*6.29287) -> 102.98031 | O41: =((D41+M41)*6.29287*E41)+X41 -> 716.41013 | P41: =O41-X41 -> 736.23473 | Q41: =(D41+M41)/D41 -> 1.0511522 | T41: =(($D41+R41)*$E41*6.29287)+X41 -> 680.58278 | U41: =T41-X41 -> 700.40738 | X41: -19.8246 | Y41: 0.36 | AA41: -19.14 | AB41: =(D41+AA41)*E41*6.2898105 -> 566.97905 | AC41: =D41+AA41 -> 81.54 | AG41: =M41-AA41 -> 24.29 | AH41: =(D41+AA41)/D41 -> 0.80989273 | AR41: 0 | AS41: 0 | AT41: =AU41/($E41*6.29287) -> 100.68 | AU41: =(($D41+AR41)*6.29287*$E41)+AS41 -> 700.40738 | AV41: =AU41-AS41 -> 700.40738 | AX41: 0 | AY41: 0 | AZ41: =BA41/($E41*6.29287) -> 100.68 | BA41: =(($D41+AX41)*6.29287*$E41)+AY41 -> 700.40738 | BB41: =BA41-AY41 -> 700.40738 | BD41: 0 | BE41: 0 | BF41: =BG41/($E41*6.29287) -> 100.68 | BG41: =(($D41+BD41)*6.29287*$E41)+BE41 -> 700.40738 | BH41: =BG41-BE41 -> 700.40738 | BJ41: 0 | BK41: 0 | BL41: =BM41/($E41*6.29287) -> 100.68 | BM41: =(($D41+BJ41)*6.29287*$E41)+BK41 -> 700.40738 | BN41: =BM41-BK41 -> 700.40738 | BP41: =AA41+0.25 -> -18.89 | BS41: N/A | BT41: N/A | BU41: N/A | BY41: N/A | BZ41: N/A | CA41: N/A
B42: 41699 | C42: 31 | D42: 100.51 | E42: 1.1107 | F42: -6.6 | G42: -0.7059 | H42: =I42/(E42*6.29287) -> 93.809006 | I42: =((D42+F42)*6.29287*E42)+G42 -> 655.67717 | J42: =I42-G42 -> 656.38307 | K42: =(D42+F42)/D42 -> 0.93433489 | L42: =M42-F42 -> 9.97 | M42: 3.37 | N42: =O42/(E42*6.29287) -> 102.25719 | O42: =((D42+M42)*6.29287*E42)+X42 -> 714.72569 | P42: =O42-X42 -> 726.06829 | Q42: =(D42+M42)/D42 -> 1.033529 | T42: =(($D42+R42)*$E42*6.29287)+X42 -> 691.17111 | U42: =T42-X42 -> 702.51371 | X42: -11.3426 | Y42: 0.37 | AA42: -21.09 | AB42: =(D42+AA42)*E42*6.2898105 -> 554.83547 | AC42: =D42+AA42 -> 79.42 | AG42: =M42-AA42 -> 24.46 | AH42: =(D42+AA42)/D42 -> 0.79017013 | AR42: 0 | AS42: 0 | AT42: =AU42/($E42*6.29287) -> 100.51 | AU42: =(($D42+AR42)*6.29287*$E42)+AS42 -> 702.51371 | AV42: =AU42-AS42 -> 702.51371 | AX42: 0 | AY42: 0 | AZ42: =BA42/($E42*6.29287) -> 100.51 | BA42: =(($D42+AX42)*6.29287*$E42)+AY42 -> 702.51371 | BB42: =BA42-AY42 -> 702.51371 | BD42: 0 | BE42: 0 | BF42: =BG42/($E42*6.29287) -> 100.51 | BG42: =(($D42+BD42)*6.29287*$E42)+BE42 -> 702.51371 | BH42: =BG42-BE42 -> 702.51371 | BJ42: 0 | BK42: 0 | BL42: =BM42/($E42*6.29287) -> 100.51 | BM42: =(($D42+BJ42)*6.29287*$E42)+BK42 -> 702.51371 | BN42: =BM42-BK42 -> 702.51371 | BP42: =AA42+0.25 -> -20.84 | BS42: N/A | BT42: N/A | BU42: N/A | BY42: N/A | BZ42: N/A | CA42: N/A
B43: 41730 | C43: 30 | D43: 102.03 | E43: 1.0991 | F43: -8.32 | G43: -0.5652 | H43: =I43/(E43*6.29287) -> 93.628282 | I43: =((D43+F43)*6.29287*E43)+G43 -> 647.5794 | J43: =I43-G43 -> 648.1446 | K43: =(D43+F43)/D43 -> 0.91845536 | L43: =M43-F43 -> 10.23 | M43: 1.91 | N43: =O43/(E43*6.29287) -> 102.06353 | O43: =((D43+M43)*6.29287*E43)+X43 -> 705.92173 | P43: =O43-X43 -> 718.90033 | Q43: =(D43+M43)/D43 -> 1.01872 | T43: =(($D43+R43)*$E43*6.29287)+X43 -> 692.71122 | U43: =T43-X43 -> 705.68982 | X43: -12.9786 | Y43: 0.38 | AA43: -22.47 | AB43: =(D43+AA43)*E43*6.2898105 -> 550.00868 | AC43: =D43+AA43 -> 79.56 | AG43: =M43-AA43 -> 24.38 | AH43: =(D43+AA43)/D43 -> 0.77977066 | AR43: 0 | AS43: 0 | AT43: =AU43/($E43*6.29287) -> 102.03 | AU43: =(($D43+AR43)*6.29287*$E43)+AS43 -> 705.68982 | AV43: =AU43-AS43 -> 705.68982 | AX43: 0 | AY43: 0 | AZ43: =BA43/($E43*6.29287) -> 102.03 | BA43: =(($D43+AX43)*6.29287*$E43)+AY43 -> 705.68982 | BB43: =BA43-AY43 -> 705.68982 | BD43: 0 | BE43: 0 | BF43: =BG43/($E43*6.29287) -> 102.03 | BG43: =(($D43+BD43)*6.29287*$E43)+BE43 -> 705.68982 | BH43: =BG43-BE43 -> 705.68982 | BJ43: 0 | BK43: 0 | BL43: =BM43/($E43*6.29287) -> 102.03 | BM43: =(($D43+BJ43)*6.29287*$E43)+BK43 -> 705.68982 | BN43: =BM43-BK43 -> 705.68982 | BP43: =AA43+0.25 -> -22.22 | BS43: N/A | BT43: N/A | BU43: N/A | BY43: N/A | BZ43: N/A | CA43: N/A
B44: 41760 | C44: 31 | D44: 101.79 | E44: 1.0894 | F44: -4.12 | G44: -0.9166 | H44: =I44/(E44*6.29287) -> 97.536296 | I44: =((D44+F44)*6.29287*E44)+G44 -> 668.65545 | J44: =I44-G44 -> 669.57205 | K44: =(D44+F44)/D44 -> 0.95952451 | L44: =M44-F44 -> 7.48 | M44: 3.36 | N44: =O44/(E44*6.29287) -> 103.22224 | O44: =((D44+M44)*6.29287*E44)+X44 -> 707.63514 | P44: =O44-X44 -> 720.85084 | Q44: =(D44+M44)/D44 -> 1.0330091 | T44: =(($D44+R44)*$E44*6.29287)+X44 -> 684.60082 | U44: =T44-X44 -> 697.81652 | X44: -13.2157 | Y44: 0.34 | AA44: -19.07 | AB44: =(D44+AA44)*E44*6.2898105 -> 566.80733 | AC44: =D44+AA44 -> 82.72 | AG44: =M44-AA44 -> 22.43 | AH44: =(D44+AA44)/D44 -> 0.8126535 | AR44: 0 | AS44: 0 | AT44: =AU44/($E44*6.29287) -> 101.79 | AU44: =(($D44+AR44)*6.29287*$E44)+AS44 -> 697.81652 | AV44: =AU44-AS44 -> 697.81652 | AX44: 0 | AY44: 0 | AZ44: =BA44/($E44*6.29287) -> 101.79 | BA44: =(($D44+AX44)*6.29287*$E44)+AY44 -> 697.81652 | BB44: =BA44-AY44 -> 697.81652 | BD44: 0 | BE44: 0 | BF44: =BG44/($E44*6.29287) -> 101.79 | BG44: =(($D44+BD44)*6.29287*$E44)+BE44 -> 697.81652 | BH44: =BG44-BE44 -> 697.81652 | BJ44: 0 | BK44: 0 | BL44: =BM44/($E44*6.29287) -> 101.79 | BM44: =(($D44+BJ44)*6.29287*$E44)+BK44 -> 697.81652 | BN44: =BM44-BK44 -> 697.81652 | BP44: =AA44+0.25 -> -18.82 | BS44: N/A | BT44: N/A | BU44: N/A | BY44: N/A | BZ44: N/A | CA44: N/A
B45: 41791 | C45: 30 | D45: 105.15 | E45: 1.0831 | F45: -5.97 | G45: -0.6286 | H45: =I45/(E45*6.29287) -> 99.087773 | I45: =((D45+F45)*6.29287*E45)+G45 -> 675.36319 | J45: =I45-G45 -> 675.99179 | K45: =(D45+F45)/D45 -> 0.94322397 | L45: =M45-F45 -> 7.17 | M45: 1.2 | N45: =O45/(E45*6.29287) -> 104.51422 | O45: =((D45+M45)*6.29287*E45)+X45 -> 712.34883 | P45: =O45-X45 -> 724.86113 | Q45: =(D45+M45)/D45 -> 1.0114123 | T45: =(($D45+R45)*$E45*6.29287)+X45 -> 704.16986 | U45: =T45-X45 -> 716.68216 | X45: -12.5123 | Y45: 0.29 | AA45: -18.59 | AB45: =(D45+AA45)*E45*6.2898105 -> 589.68946 | AC45: =D45+AA45 -> 86.56 | AG45: =M45-AA45 -> 19.79 | AH45: =(D45+AA45)/D45 -> 0.82320495 | AR45: 0 | AS45: 0 | AT45: =AU45/($E45*6.29287) -> 105.15 | AU45: =(($D45+AR45)*6.29287*$E45)+AS45 -> 716.68216 | AV45: =AU45-AS45 -> 716.68216 | AX45: 0 | AY45: 0 | AZ45: =BA45/($E45*6.29287) -> 105.15 | BA45: =(($D45+AX45)*6.29287*$E45)+AY45 -> 716.68216 | BB45: =BA45-AY45 -> 716.68216 | BD45: 0 | BE45: 0 | BF45: =BG45/($E45*6.29287) -> 105.15 | BG45: =(($D45+BD45)*6.29287*$E45)+BE45 -> 716.68216 | BH45: =BG45-BE45 -> 716.68216 | BJ45: 0 | BK45: 0 | BL45: =BM45/($E45*6.29287) -> 105.15 | BM45: =(($D45+BJ45)*6.29287*$E45)+BK45 -> 716.68216 | BN45: =BM45-BK45 -> 716.68216 | BP45: =AA45+0.25 -> -18.34 | BS45: N/A | BT45: N/A | BU45: N/A | BY45: N/A | BZ45: N/A | CA45: N/A
B46: 41821 | C46: 31 | D46: 102.39 | E46: 1.0739 | F46: -7.18 | G46: -1.0052 | H46: =I46/(E46*6.29287) -> 95.061256 | I46: =((D46+F46)*6.29287*E46)+G46 -> 642.41571 | J46: =I46-G46 -> 643.42091 | K46: =(D46+F46)/D46 -> 0.92987596 | L46: =M46-F46 -> 3.88 | M46: -3.3 | N46: =O46/(E46*6.29287) -> 96.900715 | O46: =((D46+M46)*6.29287*E46)+X46 -> 654.84661 | P46: =O46-X46 -> 669.64161 | Q46: =(D46+M46)/D46 -> 0.96777029 | T46: =(($D46+R46)*$E46*6.29287)+X46 -> 677.14772 | U46: =T46-X46 -> 691.94272 | X46: -14.795 | Y46: 0.24 | AA46: -19.66 | AB46: =(D46+AA46)*E46*6.2898105 -> 558.81033 | AC46: =D46+AA46 -> 82.73 | AG46: =M46-AA46 -> 16.36 | AH46: =(D46+AA46)/D46 -> 0.80798906 | AR46: 0 | AS46: 0 | AT46: =AU46/($E46*6.29287) -> 102.39 | AU46: =(($D46+AR46)*6.29287*$E46)+AS46 -> 691.94272 | AV46: =AU46-AS46 -> 691.94272 | AX46: 0 | AY46: 0 | AZ46: =BA46/($E46*6.29287) -> 102.39 | BA46: =(($D46+AX46)*6.29287*$E46)+AY46 -> 691.94272 | BB46: =BA46-AY46 -> 691.94272 | BD46: 0 | BE46: 0 | BF46: =BG46/($E46*6.29287) -> 102.39 | BG46: =(($D46+BD46)*6.29287*$E46)+BE46 -> 691.94272 | BH46: =BG46-BE46 -> 691.94272 | BJ46: 0 | BK46: 0 | BL46: =BM46/($E46*6.29287) -> 102.39 | BM46: =(($D46+BJ46)*6.29287*$E46)+BK46 -> 691.94272 | BN46: =BM46-BK46 -> 691.94272 | BP46: =AA46+0.25 -> -19.41 | BS46: N/A | BT46: N/A | BU46: N/A | BY46: N/A | BZ46: N/A | CA46: N/A
B47: 41852 | C47: 31 | D47: 96.08 | E47: 1.0927 | F47: -8.54 | G47: -1.137 | H47: =I47/(E47*6.29287) -> 87.374648 | I47: =((D47+F47)*6.29287*E47)+G47 -> 600.80722 | J47: =I47-G47 -> 601.94422 | K47: =(D47+F47)/D47 -> 0.91111574 | L47: =M47-F47 -> 4.25 | M47: -4.29 | N47: =O47/(E47*6.29287) -> 90.376781 | O47: =((D47+M47)*6.29287*E47)+X47 -> 621.45055 | P47: =O47-X47 -> 631.16815 | Q47: =(D47+M47)/D47 -> 0.95534971 | T47: =(($D47+R47)*$E47*6.29287)+X47 -> 650.94953 | U47: =T47-X47 -> 660.66713 | X47: -9.7176 | Y47: 0.28 | AA47: -22.19 | AB47: =(D47+AA47)*E47*6.2898105 -> 507.8368 | AC47: =D47+AA47 -> 73.89 | AG47: =M47-AA47 -> 17.9 | AH47: =(D47+AA47)/D47 -> 0.76904663 | AR47: 0 | AS47: 0 | AT47: =AU47/($E47*6.29287) -> 96.08 | AU47: =(($D47+AR47)*6.29287*$E47)+AS47 -> 660.66713 | AV47: =AU47-AS47 -> 660.66713 | AX47: 0 | AY47: 0 | AZ47: =BA47/($E47*6.29287) -> 96.08 | BA47: =(($D47+AX47)*6.29287*$E47)+AY47 -> 660.66713 | BB47: =BA47-AY47 -> 660.66713 | BD47: 0 | BE47: 0 | BF47: =BG47/($E47*6.29287) -> 96.08 | BG47: =(($D47+BD47)*6.29287*$E47)+BE47 -> 660.66713 | BH47: =BG47-BE47 -> 660.66713 | BJ47: 0 | BK47: 0 | BL47: =BM47/($E47*6.29287) -> 96.08 | BM47: =(($D47+BJ47)*6.29287*$E47)+BK47 -> 660.66713 | BN47: =BM47-BK47 -> 660.66713 | BP47: =AA47+0.25 -> -21.94 | BS47: N/A | BT47: N/A | BU47: N/A | BY47: N/A | BZ47: N/A | CA47: N/A
B48: 41883 | C48: 30 | D48: 93.03 | E48: 1.1012 | F48: -8.06 | G48: -1.1469 | H48: =I48/(E48*6.29287) -> 84.804495 | I48: =((D48+F48)*6.29287*E48)+G48 -> 587.67043 | J48: =I48-G48 -> 588.81733 | K48: =(D48+F48)/D48 -> 0.91336128 | L48: =M48-F48 -> 4.49 | M48: -3.57 | N48: =O48/(E48*6.29287) -> 87.764872 | O48: =((D48+M48)*6.29287*E48)+X48 -> 608.18497 | P48: =O48-X48 -> 619.93172 | Q48: =(D48+M48)/D48 -> 0.96162528 | T48: =(($D48+R48)*$E48*6.29287)+X48 -> 632.92403 | U48: =T48-X48 -> 644.67078 | X48: -11.746744 | Y48: 0.23 | AA48: -18.68 | AB48: =(D48+AA48)*E48*6.2898105 -> 514.97333 | AC48: =D48+AA48 -> 74.35 | AG48: =M48-AA48 -> 15.11 | AH48: =(D48+AA48)/D48 -> 0.79920456 | AR48: 0 | AS48: 0 | AT48: =AU48/($E48*6.29287) -> 93.03 | AU48: =(($D48+AR48)*6.29287*$E48)+AS48 -> 644.67078 | AV48: =AU48-AS48 -> 644.67078 | AX48: 0 | AY48: 0 | AZ48: =BA48/($E48*6.29287) -> 93.03 | BA48: =(($D48+AX48)*6.29287*$E48)+AY48 -> 644.67078 | BB48: =BA48-AY48 -> 644.67078 | BD48: 0 | BE48: 0 | BF48: =BG48/($E48*6.29287) -> 93.03 | BG48: =(($D48+BD48)*6.29287*$E48)+BE48 -> 644.67078 | BH48: =BG48-BE48 -> 644.67078 | BJ48: 0 | BK48: 0 | BL48: =BM48/($E48*6.29287) -> 93.03 | BM48: =(($D48+BJ48)*6.29287*$E48)+BK48 -> 644.67078 | BN48: =BM48-BK48 -> 644.67078 | BP48: =AA48+0.25 -> -18.43 | BS48: N/A | BT48: N/A | BU48: N/A | BY48: N/A | BZ48: N/A | CA48: N/A
B49: 41913 | C49: 31 | D49: 84.34 | E49: 1.1213 | F49: -4.54 | G49: -0.7865 | H49: =I49/(E49*6.29287) -> 79.688538 | I49: =((D49+F49)*6.29287*E49)+G49 -> 562.29787 | J49: =I49-G49 -> 563.08437 | K49: =(D49+F49)/D49 -> 0.94617026 | L49: =M49-F49 -> 4.45 | M49: -0.09 | N49: =O49/(E49*6.29287) -> 82.806559 | O49: =((D49+M49)*6.29287*E49)+X49 -> 584.29924 | P49: =O49-X49 -> 594.48444 | Q49: =(D49+M49)/D49 -> 0.99893289 | T49: =(($D49+R49)*$E49*6.29287)+X49 -> 584.9343 | U49: =T49-X49 -> 595.1195 | X49: -10.1852 | Y49: 0.21 | AA49: -13.74 | AB49: =(D49+AA49)*E49*6.2898105 -> 497.92517 | AC49: =D49+AA49 -> 70.6 | AG49: =M49-AA49 -> 13.65 | AH49: =(D49+AA49)/D49 -> 0.83708798 | AR49: 0 | AS49: 0 | AT49: =AU49/($E49*6.29287) -> 84.34 | AU49: =(($D49+AR49)*6.29287*$E49)+AS49 -> 595.1195 | AV49: =AU49-AS49 -> 595.1195 | AX49: 0 | AY49: 0 | AZ49: =BA49/($E49*6.29287) -> 84.34 | BA49: =(($D49+AX49)*6.29287*$E49)+AY49 -> 595.1195 | BB49: =BA49-AY49 -> 595.1195 | BD49: 0 | BE49: 0 | BF49: =BG49/($E49*6.29287) -> 84.34 | BG49: =(($D49+BD49)*6.29287*$E49)+BE49 -> 595.1195 | BH49: =BG49-BE49 -> 595.1195 | BJ49: 0 | BK49: 0 | BL49: =BM49/($E49*6.29287) -> 84.34 | BM49: =(($D49+BJ49)*6.29287*$E49)+BK49 -> 595.1195 | BN49: =BM49-BK49 -> 595.1195 | BP49: =AA49+0.25 -> -13.49 | BS49: N/A | BT49: N/A | BU49: N/A | BY49: N/A | BZ49: N/A | CA49: N/A
B50: 41944 | C50: 30 | D50: 75.81 | E50: 1.1326 | F50: -5.3 | G50: -0.7316 | H50: =I50/(E50*6.29287) -> 70.407352 | I50: =((D50+F50)*6.29287*E50)+G50 -> 501.81464 | J50: =I50-G50 -> 502.54624 | K50: =(D50+F50)/D50 -> 0.93008838 | L50: =M50-F50 -> 3.17 | M50: -2.13 | N50: =O50/(E50*6.29287) -> 72.665128 | O50: =((D50+M50)*6.29287*E50)+X50 -> 517.9065 | P50: =O50-X50 -> 525.1398 | Q50: =(D50+M50)/D50 -> 0.97190344 | T50: =(($D50+R50)*$E50*6.29287)+X50 -> 533.08766 | U50: =T50-X50 -> 540.32096 | X50: -7.2333 | Y50: 0.16 | AA50: -12.94 | AB50: =(D50+AA50)*E50*6.2898105 -> 447.87578 | AC50: =D50+AA50 -> 62.87 | AG50: =M50-AA50 -> 10.81 | AH50: =(D50+AA50)/D50 -> 0.82931012 | AR50: 0 | AS50: 0 | AT50: =AU50/($E50*6.29287) -> 75.81 | AU50: =(($D50+AR50)*6.29287*$E50)+AS50 -> 540.32096 | AV50: =AU50-AS50 -> 540.32096 | AX50: 0 | AY50: 0 | AZ50: =BA50/($E50*6.29287) -> 75.81 | BA50: =(($D50+AX50)*6.29287*$E50)+AY50 -> 540.32096 | BB50: =BA50-AY50 -> 540.32096 | BD50: 0 | BE50: 0 | BF50: =BG50/($E50*6.29287) -> 75.81 | BG50: =(($D50+BD50)*6.29287*$E50)+BE50 -> 540.32096 | BH50: =BG50-BE50 -> 540.32096 | BJ50: 0 | BK50: 0 | BL50: =BM50/($E50*6.29287) -> 75.81 | BM50: =(($D50+BJ50)*6.29287*$E50)+BK50 -> 540.32096 | BN50: =BM50-BK50 -> 540.32096 | BP50: =AA50+0.25 -> -12.69 | BS50: N/A | BT50: N/A | BU50: N/A | BY50: N/A | BZ50: N/A | CA50: N/A
B51: 41974 | C51: 31 | D51: 59.29 | E51: 1.1533 | F51: -9.23 | G51: -1.0259 | H51: =I51/(E51*6.29287) -> 49.918644 | I51: =((D51+F51)*6.29287*E51)+G51 -> 362.2879 | J51: =I51-G51 -> 363.3138 | K51: =(D51+F51)/D51 -> 0.84432451 | L51: =M51-F51 -> 3.72 | M51: -5.51 | N51: =O51/(E51*6.29287) -> 52.860008 | O51: =((D51+M51)*6.29287*E51)+X51 -> 383.63505 | P51: =O51-X51 -> 390.31195 | Q51: =(D51+M51)/D51 -> 0.90706696 | T51: =(($D51+R51)*$E51*6.29287)+X51 -> 423.62425 | U51: =T51-X51 -> 430.30115 | X51: -6.6769 | Y51: 0.17 | AA51: -16.05 | AB51: =(D51+AA51)*E51*6.2898105 -> 313.66462 | AC51: =D51+AA51 -> 43.24 | AG51: =M51-AA51 -> 10.54 | AH51: =(D51+AA51)/D51 -> 0.72929668 | AR51: 0 | AS51: 0 | AT51: =AU51/($E51*6.29287) -> 59.29 | AU51: =(($D51+AR51)*6.29287*$E51)+AS51 -> 430.30115 | AV51: =AU51-AS51 -> 430.30115 | AX51: 0 | AY51: 0 | AZ51: =BA51/($E51*6.29287) -> 59.29 | BA51: =(($D51+AX51)*6.29287*$E51)+AY51 -> 430.30115 | BB51: =BA51-AY51 -> 430.30115 | BD51: 0 | BE51: 0 | BF51: =BG51/($E51*6.29287) -> 59.29 | BG51: =(($D51+BD51)*6.29287*$E51)+BE51 -> 430.30115 | BH51: =BG51-BE51 -> 430.30115 | BJ51: 0 | BK51: 0 | BL51: =BM51/($E51*6.29287) -> 59.29 | BM51: =(($D51+BJ51)*6.29287*$E51)+BK51 -> 430.30115 | BN51: =BM51-BK51 -> 430.30115 | BP51: =AA51+0.25 -> -15.8 | BS51: N/A | BT51: N/A | BU51: N/A | BY51: N/A | BZ51: N/A | CA51: N/A
B52: 42005 | C52: 31 | D52: 47.33 | E52: 1.2115 | F52: -6.97 | G52: -0.881 | H52: =I52/(E52*6.29287) -> 40.244441 | I52: =((D52+F52)*6.29287*E52)+G52 -> 306.81605 | J52: =I52-G52 -> 307.69705 | K52: =(D52+F52)/D52 -> 0.85273611 | L52: =M52-F52 -> 2.08 | M52: -4.89 | N52: =O52/(E52*6.29287) -> 41.381173 | O52: =((D52+M52)*6.29287*E52)+X52 -> 315.48228 | P52: =O52-X52 -> 323.55458 | Q52: =(D52+M52)/D52 -> 0.89668286 | T52: =(($D52+R52)*$E52*6.29287)+X52 -> 352.76272 | U52: =T52-X52 -> 360.83502 | X52: -8.0723 | Y52: 0.21 | AA52: -16.9 | AB52: =(D52+AA52)*E52*6.2898105 -> 231.87981 | AC52: =D52+AA52 -> 30.43 | AG52: =F52-AA52 -> 9.93 | AH52: =(D52+AA52)/D52 -> 0.6429326 | AR52: 0 | AS52: 0 | AT52: =AU52/($E52*6.29287) -> 47.33 | AU52: =(($D52+AR52)*6.29287*$E52)+AS52 -> 360.83502 | AV52: =AU52-AS52 -> 360.83502 | AX52: 0 | AY52: 0 | AZ52: =BA52/($E52*6.29287) -> 47.33 | BA52: =(($D52+AX52)*6.29287*$E52)+AY52 -> 360.83502 | BB52: =BA52-AY52 -> 360.83502 | BD52: 0 | BE52: 0 | BF52: =BG52/($E52*6.29287) -> 47.33 | BG52: =(($D52+BD52)*6.29287*$E52)+BE52 -> 360.83502 | BH52: =BG52-BE52 -> 360.83502 | BJ52: 0 | BK52: 0 | BL52: =BM52/($E52*6.29287) -> 47.33 | BM52: =(($D52+BJ52)*6.29287*$E52)+BK52 -> 360.83502 | BN52: =BM52-BK52 -> 360.83502 | BP52: =AA52+0.25 -> -16.65 | BS52: N/A | BT52: N/A | BU52: N/A | BY52: N/A | BZ52: N/A | CA52: N/A
B53: 42036 | C53: 28 | D53: 50.72 | E53: 1.25 | F53: -7.18 | G53: -1.1731 | H53: =I53/(E53*6.29287) -> 43.390866 | I53: =((D53+F53)*6.29287*E53)+G53 -> 341.31635 | J53: =I53-G53 -> 342.48945 | K53: =(D53+F53)/D53 -> 0.85843849 | L53: =M53-F53 -> 2.94 | M53: -4.24 | N53: =O53/(E53*6.29287) -> 45.274979 | O53: =((D53+M53)*6.29287*E53)+X53 -> 356.13695 | P53: =O53-X53 -> 365.61575 | Q53: =(D53+M53)/D53 -> 0.91640379 | T53: =(($D53+R53)*$E53*6.29287)+X53 -> 389.48916 | U53: =T53-X53 -> 398.96796 | X53: -9.4788 | Y53: 0.17 | AA53: -14.2 | AB53: =(D53+AA53)*E53*6.2898105 -> 287.12985 | AC53: =D53+AA53 -> 36.52 | AG53: =F53-AA53 -> 7.02 | AH53: =(D53+AA53)/D53 -> 0.72003155 | AR53: 0 | AS53: 0 | AT53: =AU53/($E53*6.29287) -> 50.72 | AU53: =(($D53+AR53)*6.29287*$E53)+AS53 -> 398.96796 | AV53: =AU53-AS53 -> 398.96796 | AX53: 0 | AY53: 0 | AZ53: =BA53/($E53*6.29287) -> 50.72 | BA53: =(($D53+AX53)*6.29287*$E53)+AY53 -> 398.96796 | BB53: =BA53-AY53 -> 398.96796 | BD53: 0 | BE53: 0 | BF53: =BG53/($E53*6.29287) -> 50.72 | BG53: =(($D53+BD53)*6.29287*$E53)+BE53 -> 398.96796 | BH53: =BG53-BE53 -> 398.96796 | BJ53: 0 | BK53: 0 | BL53: =BM53/($E53*6.29287) -> 50.72 | BM53: =(($D53+BJ53)*6.29287*$E53)+BK53 -> 398.96796 | BN53: =BM53-BK53 -> 398.96796 | BP53: =AA53+0.25 -> -13.95 | BS53: N/A | BT53: N/A | BU53: N/A | BY53: N/A | BZ53: N/A | CA53: N/A
B54: 42064 | C54: 31 | D54: 47.85 | E54: 1.2619 | F54: -6.26 | G54: -0.7858 | H54: =I54/(E54*6.29287) -> 41.491045 | I54: =((D54+F54)*6.29287*E54)+G54 -> 329.47925 | J54: =I54-G54 -> 330.26505 | K54: =(D54+F54)/D54 -> 0.8691745 | L54: =M54-F54 -> 6.35 | M54: 0.09 | N54: =O54/(E54*6.29287) -> 47.183241 | O54: =((D54+M54)*6.29287*E54)+X54 -> 374.68083 | P54: =O54-X54 -> 380.69023 | Q54: =(D54+M54)/D54 -> 1.0018809 | T54: =(($D54+R54)*$E54*6.29287)+X54 -> 373.96614 | U54: =T54-X54 -> 379.97554 | X54: -6.0094 | Y54: 0.25 | AA54: -13.09 | AB54: =(D54+AA54)*E54*6.2898105 -> 275.89401 | AC54: =D54+AA54 -> 34.76 | AG54: =F54-AA54 -> 6.83 | AH54: =(D54+AA54)/D54 -> 0.72643678 | AR54: 0 | AS54: 0 | AT54: =AU54/($E54*6.29287) -> 47.85 | AU54: =(($D54+AR54)*6.29287*$E54)+AS54 -> 379.97554 | AV54: =AU54-AS54 -> 379.97554 | AX54: 0 | AY54: 0 | AZ54: =BA54/($E54*6.29287) -> 47.85 | BA54: =(($D54+AX54)*6.29287*$E54)+AY54 -> 379.97554 | BB54: =BA54-AY54 -> 379.97554 | BD54: 0 | BE54: 0 | BF54: =BG54/($E54*6.29287) -> 47.85 | BG54: =(($D54+BD54)*6.29287*$E54)+BE54 -> 379.97554 | BH54: =BG54-BE54 -> 379.97554 | BJ54: 0 | BK54: 0 | BL54: =BM54/($E54*6.29287) -> 47.85 | BM54: =(($D54+BJ54)*6.29287*$E54)+BK54 -> 379.97554 | BN54: =BM54-BK54 -> 379.97554 | BP54: =AA54+0.25 -> -12.84 | BS54: N/A | BT54: N/A | BU54: N/A | BY54: N/A | BZ54: N/A | CA54: N/A
B55: 42095 | C55: 30 | D55: 54.63 | E55: 1.2331 | F55: -4.93 | G55: -0.4266 | H55: =I55/(E55*6.29287) -> 49.645024 | I55: =((D55+F55)*6.29287*E55)+G55 -> 385.23238 | J55: =I55-G55 -> 385.65898 | K55: =(D55+F55)/D55 -> 0.90975654 | L55: =M55-F55 -> 5.61 | M55: 0.68 | N55: =O55/(E55*6.29287) -> 54.352519 | O55: =((D55+M55)*6.29287*E55)+X55 -> 421.76131 | P55: =O55-X55 -> 429.19111 | Q55: =(D55+M55)/D55 -> 1.0124474 | T55: =(($D55+R55)*$E55*6.29287)+X55 -> 416.48469 | U55: =T55-X55 -> 423.91449 | X55: -7.4298 | Y55: 0.27 | AA55: -14.37 | AB55: =(D55+AA55)*E55*6.2898105 -> 312.25516 | AC55: =D55+AA55 -> 40.26 | AG55: =F55-AA55 -> 9.44 | AH55: =(D55+AA55)/D55 -> 0.73695772 | AR55: 0 | AS55: 0 | AT55: =AU55/($E55*6.29287) -> 54.63 | AU55: =(($D55+AR55)*6.29287*$E55)+AS55 -> 423.91449 | AV55: =AU55-AS55 -> 423.91449 | AX55: 0 | AY55: 0 | AZ55: =BA55/($E55*6.29287) -> 54.63 | BA55: =(($D55+AX55)*6.29287*$E55)+AY55 -> 423.91449 | BB55: =BA55-AY55 -> 423.91449 | BD55: 0 | BE55: 0 | BF55: =BG55/($E55*6.29287) -> 54.63 | BG55: =(($D55+BD55)*6.29287*$E55)+BE55 -> 423.91449 | BH55: =BG55-BE55 -> 423.91449 | BJ55: 0 | BK55: 0 | BL55: =BM55/($E55*6.29287) -> 54.63 | BM55: =(($D55+BJ55)*6.29287*$E55)+BK55 -> 423.91449 | BN55: =BM55-BK55 -> 423.91449 | BP55: =AA55+0.25 -> -14.12 | BS55: N/A | BT55: N/A | BU55: N/A | BY55: N/A | BZ55: N/A | CA55: N/A
B56: 42125 | C56: 31 | D56: 59.37 | E56: 1.2185 | F56: -2.82 | G56: -0.7128 | H56: =I56/(E56*6.29287) -> 56.457041 | I56: =((D56+F56)*6.29287*E56)+G56 -> 432.9048 | J56: =I56-G56 -> 433.6176 | K56: =(D56+F56)/D56 -> 0.95250126 | L56: =M56-F56 -> 4.36 | M56: 1.54 | N56: =O56/(E56*6.29287) -> 59.636555 | O56: =((D56+M56)*6.29287*E56)+X56 -> 457.28488 | P56: =O56-X56 -> 467.04948 | Q56: =(D56+M56)/D56 -> 1.025939 | T56: =(($D56+R56)*$E56*6.29287)+X56 -> 445.47637 | U56: =T56-X56 -> 455.24097 | X56: -9.7646 | Y56: 0.23 | AA56: -11.87 | AB56: =(D56+AA56)*E56*6.2898105 -> 364.04637 | AC56: =D56+AA56 -> 47.5 | AG56: =F56-AA56 -> 9.05 | AH56: =(D56+AA56)/D56 -> 0.80006737 | AR56: 0 | AS56: 0 | AT56: =AU56/($E56*6.29287) -> 59.37 | AU56: =(($D56+AR56)*6.29287*$E56)+AS56 -> 455.24097 | AV56: =AU56-AS56 -> 455.24097 | AX56: 0 | AY56: 0 | AZ56: =BA56/($E56*6.29287) -> 59.37 | BA56: =(($D56+AX56)*6.29287*$E56)+AY56 -> 455.24097 | BB56: =BA56-AY56 -> 455.24097 | BD56: 0 | BE56: 0 | BF56: =BG56/($E56*6.29287) -> 59.37 | BG56: =(($D56+BD56)*6.29287*$E56)+BE56 -> 455.24097 | BH56: =BG56-BE56 -> 455.24097 | BJ56: 0 | BK56: 0 | BL56: =BM56/($E56*6.29287) -> 59.37 | BM56: =(($D56+BJ56)*6.29287*$E56)+BK56 -> 455.24097 | BN56: =BM56-BK56 -> 455.24097 | BP56: =AA56+0.25 -> -11.62 | BS56: N/A | BT56: N/A | BU56: N/A | BY56: N/A | BZ56: N/A | CA56: N/A
B57: 42156 | C57: 30 | D57: 59.83 | E57: 1.2366 | F57: -0.83 | G57: -0.3902 | H57: =I57/(E57*6.29287) -> 58.949857 | I57: =((D57+F57)*6.29287*E57)+G57 -> 458.73382 | J57: =I57-G57 -> 459.12402 | K57: =(D57+F57)/D57 -> 0.98612736 | L57: =M57-F57 -> -1.39 | M57: -2.22 | N57: =O57/(E57*6.29287) -> 56.375768 | O57: =((D57+M57)*6.29287*E57)+X57 -> 438.70287 | P57: =O57-X57 -> 448.30737 | Q57: =(D57+M57)/D57 -> 0.96289487 | T57: =(($D57+R57)*$E57*6.29287)+X57 -> 455.97838 | U57: =T57-X57 -> 465.58288 | X57: -9.6045 | Y57: 0.09 | AA57: -8.54 | AB57: =(D57+AA57)*E57*6.2898105 -> 398.93258 | AC57: =D57+AA57 -> 51.29 | AG57: =F57-AA57 -> 7.71 | AH57: =(D57+AA57)/D57 -> 0.85726224 | AR57: 0 | AS57: 0 | AT57: =AU57/($E57*6.29287) -> 59.83 | AU57: =(($D57+AR57)*6.29287*$E57)+AS57 -> 465.58288 | AV57: =AU57-AS57 -> 465.58288 | AX57: 0 | AY57: 0 | AZ57: =BA57/($E57*6.29287) -> 59.83 | BA57: =(($D57+AX57)*6.29287*$E57)+AY57 -> 465.58288 | BB57: =BA57-AY57 -> 465.58288 | BD57: 0 | BE57: 0 | BF57: =BG57/($E57*6.29287) -> 59.83 | BG57: =(($D57+BD57)*6.29287*$E57)+BE57 -> 465.58288 | BH57: =BG57-BE57 -> 465.58288 | BJ57: 0 | BK57: 0 | BL57: =BM57/($E57*6.29287) -> 59.83 | BM57: =(($D57+BJ57)*6.29287*$E57)+BK57 -> 465.58288 | BN57: =BM57-BK57 -> 465.58288 | BP57: =AA57+0.25 -> -8.29 | BS57: N/A | BT57: N/A | BU57: N/A | BY57: N/A | BZ57: N/A | CA57: N/A
B58: 42186 | C58: 31 | D58: 50.93 | E58: 1.2865 | F58: -0.43 | G58: -0.2291 | H58: =I58/(E58*6.29287) -> 50.471701 | I58: =((D58+F58)*6.29287*E58)+G58 -> 408.60765 | J58: =I58-G58 -> 408.83675 | K58: =(D58+F58)/D58 -> 0.99155704 | L58: =M58-F58 -> -3.92 | M58: -4.35 | N58: =O58/(E58*6.29287) -> 46.109495 | O58: =((D58+M58)*6.29287*E58)+X58 -> 373.2922 | P58: =O58-X58 -> 377.1013 | Q58: =(D58+M58)/D58 -> 0.91458865 | T58: =(($D58+R58)*$E58*6.29287)+X58 -> 408.50884 | U58: =T58-X58 -> 412.31794 | X58: -3.8091 | Y58: 0.06 | AA58: -7.44 | AB58: =(D58+AA58)*E58*6.2898105 -> 351.91417 | AC58: =D58+AA58 -> 43.49 | AG58: =F58-AA58 -> 7.01 | AH58: =(D58+AA58)/D58 -> 0.85391714 | AR58: 0 | AS58: 0 | AT58: =AU58/($E58*6.29287) -> 50.93 | AU58: =(($D58+AR58)*6.29287*$E58)+AS58 -> 412.31794 | AV58: =AU58-AS58 -> 412.31794 | AX58: 0 | AY58: 0 | AZ58: =BA58/($E58*6.29287) -> 50.93 | BA58: =(($D58+AX58)*6.29287*$E58)+AY58 -> 412.31794 | BB58: =BA58-AY58 -> 412.31794 | BD58: 0 | BE58: 0 | BF58: =BG58/($E58*6.29287) -> 50.93 | BG58: =(($D58+BD58)*6.29287*$E58)+BE58 -> 412.31794 | BH58: =BG58-BE58 -> 412.31794 | BJ58: 0 | BK58: 0 | BL58: =BM58/($E58*6.29287) -> 50.93 | BM58: =(($D58+BJ58)*6.29287*$E58)+BK58 -> 412.31794 | BN58: =BM58-BK58 -> 412.31794 | BP58: =AA58+0.25 -> -7.19 | BS58: N/A | BT58: N/A | BU58: N/A | BY58: N/A | BZ58: N/A | CA58: N/A
B59: 42217 | C59: 31 | D59: 42.89 | E59: 1.3149 | F59: -3.8 | G59: -0.3234 | H59: =I59/(E59*6.29287) -> 39.050916 | I59: =((D59+F59)*6.29287*E59)+G59 -> 323.1266 | J59: =I59-G59 -> 323.45 | K59: =(D59+F59)/D59 -> 0.91140126 | L59: =M59-F59 -> 2.44 | M59: -1.36 | N59: =O59/(E59*6.29287) -> 41.093272 | O59: =((D59+M59)*6.29287*E59)+X59 -> 340.02607 | P59: =O59-X59 -> 343.63977 | Q59: =(D59+M59)/D59 -> 0.96829098 | T59: =(($D59+R59)*$E59*6.29287)+X59 -> 351.27938 | U59: =T59-X59 -> 354.89308 | X59: -3.6137 | Y59: 0.25 | AA59: -13.41 | AB59: =(D59+AA59)*E59*6.2898105 -> 243.81351 | AC59: =D59+AA59 -> 29.48 | AG59: =F59-AA59 -> 9.61 | AH59: =(D59+AA59)/D59 -> 0.68733971 | AR59: 0 | AS59: 0 | AT59: =AU59/($E59*6.29287) -> 42.89 | AU59: =(($D59+AR59)*6.29287*$E59)+AS59 -> 354.89308 | AV59: =AU59-AS59 -> 354.89308 | AX59: 0 | AY59: 0 | AZ59: =BA59/($E59*6.29287) -> 42.89 | BA59: =(($D59+AX59)*6.29287*$E59)+AY59 -> 354.89308 | BB59: =BA59-AY59 -> 354.89308 | BD59: 0 | BE59: 0 | BF59: =BG59/($E59*6.29287) -> 42.89 | BG59: =(($D59+BD59)*6.29287*$E59)+BE59 -> 354.89308 | BH59: =BG59-BE59 -> 354.89308 | BJ59: 0 | BK59: 0 | BL59: =BM59/($E59*6.29287) -> 42.89 | BM59: =(($D59+BJ59)*6.29287*$E59)+BK59 -> 354.89308 | BN59: =BM59-BK59 -> 354.89308 | BP59: =AA59+0.25 -> -13.16 | BS59: N/A | BT59: N/A | BU59: N/A | BY59: N/A | BZ59: N/A | CA59: N/A
B60: 42248 | C60: 30 | D60: 45.47 | E60: 1.3267 | F60: -6.03 | G60: -0.6549 | H60: =I60/(E60*6.29287) -> 39.361557 | I60: =((D60+F60)*6.29287*E60)+G60 -> 328.61982 | J60: =I60-G60 -> 329.27472 | K60: =(D60+F60)/D60 -> 0.86738509 | L60: =M60-F60 -> 5.07 | M60: -0.96 | N60: =O60/(E60*6.29287) -> 43.317319 | O60: =((D60+M60)*6.29287*E60)+X60 -> 361.64549 | P60: =O60-X60 -> 371.60289 | Q60: =(D60+M60)/D60 -> 0.97888718 | T60: =(($D60+R60)*$E60*6.29287)+X60 -> 369.66029 | U60: =T60-X60 -> 379.61769 | X60: -9.9574 | Y60: 0.38 | AA60: -18.97 | AB60: =(D60+AA60)*E60*6.2898105 -> 221.13433 | AC60: =D60+AA60 -> 26.5 | AG60: =F60-AA60 -> 12.94 | AH60: =(D60+AA60)/D60 -> 0.58280185 | AR60: 0 | AS60: 0 | AT60: =AU60/($E60*6.29287) -> 45.47 | AU60: =(($D60+AR60)*6.29287*$E60)+AS60 -> 379.61769 | AV60: =AU60-AS60 -> 379.61769 | AX60: 0 | AY60: 0 | AZ60: =BA60/($E60*6.29287) -> 45.47 | BA60: =(($D60+AX60)*6.29287*$E60)+AY60 -> 379.61769 | BB60: =BA60-AY60 -> 379.61769 | BD60: 0 | BE60: 0 | BF60: =BG60/($E60*6.29287) -> 45.47 | BG60: =(($D60+BD60)*6.29287*$E60)+BE60 -> 379.61769 | BH60: =BG60-BE60 -> 379.61769 | BJ60: 0 | BK60: 0 | BL60: =BM60/($E60*6.29287) -> 45.47 | BM60: =(($D60+BJ60)*6.29287*$E60)+BK60 -> 379.61769 | BN60: =BM60-BK60 -> 379.61769 | BP60: =AA60+0.25 -> -18.72 | BS60: N/A | BT60: N/A | BU60: N/A | BY60: N/A | BZ60: N/A | CA60: N/A
B61: 42278 | C61: 31 | D61: 46.29 | E61: 1.3073 | F61: -2.89 | G61: -1.0219 | H61: =I61/(E61*6.29287) -> 43.275782 | I61: =((D61+F61)*6.29287*E61)+G61 -> 356.01553 | J61: =I61-G61 -> 357.03743 | K61: =(D61+F61)/D61 -> 0.93756751 | L61: =M61-F61 -> 2.35 | M61: -0.54 | N61: =O61/(E61*6.29287) -> 44.390872 | O61: =((D61+M61)*6.29287*E61)+X61 -> 365.189 | P61: =O61-X61 -> 376.3701 | Q61: =(D61+M61)/D61 -> 0.98833441 | T61: =(($D61+R61)*$E61*6.29287)+X61 -> 369.63141 | U61: =T61-X61 -> 380.81251 | X61: -11.1811 | Y61: 0.26 | AA61: -13.51 | AB61: =(D61+AA61)*E61*6.2898105 -> 269.5391 | AC61: =D61+AA61 -> 32.78 | AG61: =F61-AA61 -> 10.62 | AH61: =(D61+AA61)/D61 -> 0.70814431 | AR61: 0 | AS61: 0 | AT61: =AU61/($E61*6.29287) -> 46.29 | AU61: =(($D61+AR61)*6.29287*$E61)+AS61 -> 380.81251 | AV61: =AU61-AS61 -> 380.81251 | AX61: 0 | AY61: 0 | AZ61: =BA61/($E61*6.29287) -> 46.29 | BA61: =(($D61+AX61)*6.29287*$E61)+AY61 -> 380.81251 | BB61: =BA61-AY61 -> 380.81251 | BD61: 0 | BE61: 0 | BF61: =BG61/($E61*6.29287) -> 46.29 | BG61: =(($D61+BD61)*6.29287*$E61)+BE61 -> 380.81251 | BH61: =BG61-BE61 -> 380.81251 | BJ61: 0 | BK61: 0 | BL61: =BM61/($E61*6.29287) -> 46.29 | BM61: =(($D61+BJ61)*6.29287*$E61)+BK61 -> 380.81251 | BN61: =BM61-BK61 -> 380.81251 | BP61: =AA61+0.25 -> -13.26 | BS61: N/A | BT61: N/A | BU61: N/A | BY61: N/A | BZ61: N/A | CA61: N/A
B62: 42309 | C62: 30 | D62: 42.92 | E62: 1.328 | F62: -2.03 | G62: -1.0414 | H62: =I62/(E62*6.29287) -> 40.765385 | I62: =((D62+F62)*6.29287*E62)+G62 -> 340.67352 | J62: =I62-G62 -> 341.71492 | K62: =(D62+F62)/D62 -> 0.9527027 | L62: =M62-F62 -> 0.91 | M62: -1.12 | N62: =O62/(E62*6.29287) -> 41.122012 | O62: =((D62+M62)*6.29287*E62)+X62 -> 343.65383 | P62: =O62-X62 -> 349.31973 | Q62: =(D62+M62)/D62 -> 0.97390494 | T62: =(($D62+R62)*$E62*6.29287)+X62 -> 353.01359 | U62: =T62-X62 -> 358.67949 | X62: -5.6659 | Y62: 0.29 | AA62: -15.14 | AB62: =(D62+AA62)*E62*6.2898105 -> 232.04268 | AC62: =D62+AA62 -> 27.78 | AG62: =F62-AA62 -> 13.11 | AH62: =(D62+AA62)/D62 -> 0.6472507 | AR62: 0 | AS62: 0 | AT62: =AU62/($E62*6.29287) -> 42.92 | AU62: =(($D62+AR62)*6.29287*$E62)+AS62 -> 358.67949 | AV62: =AU62-AS62 -> 358.67949 | AX62: 0 | AY62: 0 | AZ62: =BA62/($E62*6.29287) -> 42.92 | BA62: =(($D62+AX62)*6.29287*$E62)+AY62 -> 358.67949 | BB62: =BA62-AY62 -> 358.67949 | BD62: 0 | BE62: 0 | BF62: =BG62/($E62*6.29287) -> 42.92 | BG62: =(($D62+BD62)*6.29287*$E62)+BE62 -> 358.67949 | BH62: =BG62-BE62 -> 358.67949 | BJ62: 0 | BK62: 0 | BL62: =BM62/($E62*6.29287) -> 42.92 | BM62: =(($D62+BJ62)*6.29287*$E62)+BK62 -> 358.67949 | BN62: =BM62-BK62 -> 358.67949 | BP62: =AA62+0.25 -> -14.89 | BS62: N/A | BT62: N/A | BU62: N/A | BY62: N/A | BZ62: N/A | CA62: N/A
B63: 42339 | C63: 31 | D63: 37.33 | E63: 1.3705 | F63: -2.45 | G63: 0.1455 | H63: =I63/(E63*6.29287) -> 34.896871 | I63: =((D63+F63)*6.29287*E63)+G63 -> 300.96382 | J63: =I63-G63 -> 300.81832 | K63: =(D63+F63)/D63 -> 0.93436914 | L63: =M63-F63 -> 2.58 | M63: 0.13 | N63: =O63/(E63*6.29287) -> 37.143548 | O63: =((D63+M63)*6.29287*E63)+X63 -> 320.34001 | P63: =O63-X63 -> 323.06921 | Q63: =(D63+M63)/D63 -> 1.0034825 | T63: =(($D63+R63)*$E63*6.29287)+X63 -> 319.21884 | U63: =T63-X63 -> 321.94804 | X63: -2.7292 | Y63: 0.33 | AA63: -14.82 | AB63: =(D63+AA63)*E63*6.2898105 -> 194.04037 | AC63: =D63+AA63 -> 22.51 | AG63: =F63-AA63 -> 12.37 | AH63: =(D63+AA63)/D63 -> 0.60300027 | AR63: 0 | AS63: 0 | AT63: =AU63/($E63*6.29287) -> 37.33 | AU63: =(($D63+AR63)*6.29287*$E63)+AS63 -> 321.94804 | AV63: =AU63-AS63 -> 321.94804 | AX63: 0 | AY63: 0 | AZ63: =BA63/($E63*6.29287) -> 37.33 | BA63: =(($D63+AX63)*6.29287*$E63)+AY63 -> 321.94804 | BB63: =BA63-AY63 -> 321.94804 | BD63: 0 | BE63: 0 | BF63: =BG63/($E63*6.29287) -> 37.33 | BG63: =(($D63+BD63)*6.29287*$E63)+BE63 -> 321.94804 | BH63: =BG63-BE63 -> 321.94804 | BJ63: 0 | BK63: 0 | BL63: =BM63/($E63*6.29287) -> 37.33 | BM63: =(($D63+BJ63)*6.29287*$E63)+BK63 -> 321.94804 | BN63: =BM63-BK63 -> 321.94804 | BP63: =AA63+0.25 -> -14.57 | BS63: N/A | BT63: N/A | BU63: N/A | BY63: N/A | BZ63: N/A | CA63: N/A
B64: 42370 | C64: =C52 -> 31 | D64: 31.78 | E64: 1.4223 | F64: -3.58 | G64: -0.797 | H64: =I64/(E64*6.29287) -> 28.110953 | I64: =((D64+F64)*6.29287*E64)+G64 -> 251.60284 | J64: =I64-G64 -> 252.39984 | K64: =(D64+F64)/D64 -> 0.88735053 | L64: =M64-F64 -> 6.43 | M64: 2.85 | N64: =O64/(E64*6.29287) -> 34.218552 | O64: =((D64+M64)*6.29287*E64)+X64 -> 306.26799 | P64: =O64-X64 -> 309.95059 | Q64: =(D64+M64)/D64 -> 1.089679 | T64: =(($D64+R64)*$E64*6.29287)+X64 -> 280.75949 | U64: =T64-X64 -> 284.44209 | X64: -3.6826 | Y64: 0.39 | AA64: -13.9 | AB64: =(D64+AA64)*E64*6.2898105 -> 159.95443 | AC64: =D64+AA64 -> 17.88 | AG64: =F64-AA64 -> 10.32 | AH64: =(D64+AA64)/D64 -> 0.562618 | AJ64: 0.75 | AK64: =AL64/(6.29287*E64) -> 23.835 | AL64: =(AJ64*D64)*6.29287*E64 -> 213.33157 | AR64: 0 | AS64: 0 | AT64: =AU64/($E64*6.29287) -> 31.78 | AU64: =(($D64+AR64)*6.29287*$E64)+AS64 -> 284.44209 | AV64: =AU64-AS64 -> 284.44209 | AX64: 0 | AY64: 0 | AZ64: =BA64/($E64*6.29287) -> 31.78 | BA64: =(($D64+AX64)*6.29287*$E64)+AY64 -> 284.44209 | BB64: =BA64-AY64 -> 284.44209 | BD64: 0 | BE64: 0 | BF64: =BG64/($E64*6.29287) -> 31.78 | BG64: =(($D64+BD64)*6.29287*$E64)+BE64 -> 284.44209 | BH64: =BG64-BE64 -> 284.44209 | BJ64: 0 | BK64: 0 | BL64: =BM64/($E64*6.29287) -> 31.78 | BM64: =(($D64+BJ64)*6.29287*$E64)+BK64 -> 284.44209 | BN64: =BM64-BK64 -> 284.44209 | BP64: =AA64+0.25 -> -13.65 | BS64: N/A | BT64: N/A | BU64: N/A | BY64: N/A | BZ64: N/A | CA64: N/A
B65: 42401 | C65: 29 | D65: 30.62 | E65: 1.3796 | F65: -4.08 | G65: -0.9474 | H65: =I65/(E65*6.29287) -> 26.430873 | I65: =((D65+F65)*6.29287*E65)+G65 -> 229.46342 | J65: =I65-G65 -> 230.41082 | K65: =(D65+F65)/D65 -> 0.86675376 | L65: =M65-F65 -> 5.33 | M65: 1.25 | N65: =O65/(E65*6.29287) -> 31.321463 | O65: =((D65+M65)*6.29287*E65)+X65 -> 271.92178 | P65: =O65-X65 -> 276.68398 | Q65: =(D65+M65)/D65 -> 1.040823 | T65: =(($D65+R65)*$E65*6.29287)+X65 -> 261.06972 | U65: =T65-X65 -> 265.83192 | X65: -4.7622 | Y65: 0.33 | AA65: -14.32 | AB65: =(D65+AA65)*E65*6.2898105 -> 141.44199 | AC65: =D65+AA65 -> 16.3 | AG65: =F65-AA65 -> 10.24 | AH65: =(D65+AA65)/D65 -> 0.53233181 | AJ65: 0.75 | AK65: =AL65/(6.29287*E65) -> 22.965 | AL65: =(AJ65*D65)*6.29287*E65 -> 199.37394 | AR65: 0 | AS65: 0 | AT65: =AU65/($E65*6.29287) -> 30.62 | AU65: =(($D65+AR65)*6.29287*$E65)+AS65 -> 265.83192 | AV65: =AU65-AS65 -> 265.83192 | AX65: 0 | AY65: 0 | AZ65: =BA65/($E65*6.29287) -> 30.62 | BA65: =(($D65+AX65)*6.29287*$E65)+AY65 -> 265.83192 | BB65: =BA65-AY65 -> 265.83192 | BD65: 0 | BE65: 0 | BF65: =BG65/($E65*6.29287) -> 30.62 | BG65: =(($D65+BD65)*6.29287*$E65)+BE65 -> 265.83192 | BH65: =BG65-BE65 -> 265.83192 | BJ65: 0 | BK65: 0 | BL65: =BM65/($E65*6.29287) -> 30.62 | BM65: =(($D65+BJ65)*6.29287*$E65)+BK65 -> 265.83192 | BN65: =BM65-BK65 -> 265.83192 | BP65: =AA65+0.25 -> -14.07 | BS65: N/A | BT65: N/A | BU65: N/A | BY65: N/A | BZ65: N/A | CA65: N/A
B66: 42430 | C66: =C54 -> 31 | D66: 37.96 | E66: 1.3226 | F66: -3.41 | G66: -0.7717 | H66: =I66/(E66*6.29287) -> 34.45728 | I66: =((D66+F66)*6.29287*E66)+G66 -> 286.78622 | J66: =I66-G66 -> 287.55792 | K66: =(D66+F66)/D66 -> 0.9101686 | L66: =M66-F66 -> 2.14 | M66: -1.27 | N66: =O66/(E66*6.29287) -> 35.60309 | O66: =((D66+M66)*6.29287*E66)+X66 -> 296.32273 | P66: =O66-X66 -> 305.36903 | Q66: =(D66+M66)/D66 -> 0.96654373 | T66: =(($D66+R66)*$E66*6.29287)+X66 -> 306.89288 | U66: =T66-X66 -> 315.93918 | X66: -9.0463 | Y66: 0.26 | AA66: -14.5 | AB66: =(D66+AA66)*E66*6.2898105 -> 195.16147 | AC66: =D66+AA66 -> 23.46 | AG66: =F66-AA66 -> 11.09 | AH66: =(D66+AA66)/D66 -> 0.61801897 | AJ66: 0.75 | AK66: =AL66/(6.29287*E66) -> 28.47 | AL66: =(AJ66*D66)*6.29287*E66 -> 236.95438 | AR66: 0 | AS66: 0 | AT66: =AU66/($E66*6.29287) -> 37.96 | AU66: =(($D66+AR66)*6.29287*$E66)+AS66 -> 315.93918 | AV66: =AU66-AS66 -> 315.93918 | AX66: 0 | AY66: 0 | AZ66: =BA66/($E66*6.29287) -> 37.96 | BA66: =(($D66+AX66)*6.29287*$E66)+AY66 -> 315.93918 | BB66: =BA66-AY66 -> 315.93918 | BD66: 0 | BE66: 0 | BF66: =BG66/($E66*6.29287) -> 37.96 | BG66: =(($D66+BD66)*6.29287*$E66)+BE66 -> 315.93918 | BH66: =BG66-BE66 -> 315.93918 | BJ66: 0 | BK66: 0 | BL66: =BM66/($E66*6.29287) -> 37.96 | BM66: =(($D66+BJ66)*6.29287*$E66)+BK66 -> 315.93918 | BN66: =BM66-BK66 -> 315.93918 | BP66: =AA66+0.25 -> -14.25 | BS66: N/A | BT66: N/A | BU66: N/A | BY66: N/A | BZ66: N/A | CA66: N/A
B67: 42461 | C67: =C55 -> 30 | D67: 41.12 | E67: 1.2819 | F67: -2.16 | G67: -0.7512 | H67: =I67/(E67*6.29287) -> 38.866878 | I67: =((D67+F67)*6.29287*E67)+G67 -> 313.5325 | J67: =I67-G67 -> 314.2837 | K67: =(D67+F67)/D67 -> 0.94747082 | L67: =M67-F67 -> 1.6 | M67: -0.56 | N67: =O67/(E67*6.29287) -> 39.771735 | O67: =((D67+M67)*6.29287*E67)+X67 -> 320.83183 | P67: =O67-X67 -> 327.19063 | Q67: =(D67+M67)/D67 -> 0.98638132 | T67: =(($D67+R67)*$E67*6.29287)+X67 -> 325.34925 | U67: =T67-X67 -> 331.70805 | X67: -6.3588 | Y67: 0.25 | AA67: -13.24 | AB67: =(D67+AA67)*E67*6.2898105 -> 224.79388 | AC67: =D67+AA67 -> 27.88 | AG67: =F67-AA67 -> 11.08 | AH67: =(D67+AA67)/D67 -> 0.67801556 | AJ67: 0.75 | AK67: =AL67/(6.29287*E67) -> 30.84 | AL67: =(AJ67*D67)*6.29287*E67 -> 248.78104 | AR67: 0 | AS67: 0 | AT67: =AU67/($E67*6.29287) -> 41.12 | AU67: =(($D67+AR67)*6.29287*$E67)+AS67 -> 331.70805 | AV67: =AU67-AS67 -> 331.70805 | AX67: 0 | AY67: 0 | AZ67: =BA67/($E67*6.29287) -> 41.12 | BA67: =(($D67+AX67)*6.29287*$E67)+AY67 -> 331.70805 | BB67: =BA67-AY67 -> 331.70805 | BD67: 0 | BE67: 0 | BF67: =BG67/($E67*6.29287) -> 41.12 | BG67: =(($D67+BD67)*6.29287*$E67)+BE67 -> 331.70805 | BH67: =BG67-BE67 -> 331.70805 | BJ67: 0 | BK67: 0 | BL67: =BM67/($E67*6.29287) -> 41.12 | BM67: =(($D67+BJ67)*6.29287*$E67)+BK67 -> 331.70805 | BN67: =BM67-BK67 -> 331.70805 | BP67: =AA67+0.25 -> -12.99 | BS67: N/A | BT67: N/A | BU67: N/A | BY67: N/A | BZ67: N/A | CA67: N/A
B68: 42491 | C68: =C56 -> 31 | D68: 46.8 | E68: 1.2942 | F68: -4.37 | G68: -0.7155 | H68: =I68/(E68*6.29287) -> 42.342146 | I68: =((D68+F68)*6.29287*E68)+G68 -> 344.84428 | J68: =I68-G68 -> 345.55978 | K68: =(D68+F68)/D68 -> 0.90662393 | L68: =M68-F68 -> 4.22 | M68: -0.15 | N68: =O68/(E68*6.29287) -> 46.025816 | O68: =((D68+M68)*6.29287*E68)+X68 -> 374.84494 | P68: =O68-X68 -> 379.92844 | Q68: =(D68+M68)/D68 -> 0.99679487 | T68: =(($D68+R68)*$E68*6.29287)+X68 -> 376.06657 | U68: =T68-X68 -> 381.15007 | X68: -5.0835 | Y68: 0.28 | AA68: -14.28 | AB68: =(D68+AA68)*E68*6.2898105 -> 264.72167 | AC68: =D68+AA68 -> 32.52 | AG68: =F68-AA68 -> 9.91 | AH68: =(D68+AA68)/D68 -> 0.69487179 | AJ68: 0.75 | AK68: =AL68/(6.29287*E68) -> 35.1 | AL68: =(AJ68*D68)*6.29287*E68 -> 285.86256 | AR68: 0 | AS68: 0 | AT68: =AU68/($E68*6.29287) -> 46.8 | AU68: =(($D68+AR68)*6.29287*$E68)+AS68 -> 381.15007 | AV68: =AU68-AS68 -> 381.15007 | AX68: 0 | AY68: 0 | AZ68: =BA68/($E68*6.29287) -> 46.8 | BA68: =(($D68+AX68)*6.29287*$E68)+AY68 -> 381.15007 | BB68: =BA68-AY68 -> 381.15007 | BD68: 0 | BE68: 0 | BF68: =BG68/($E68*6.29287) -> 46.8 | BG68: =(($D68+BD68)*6.29287*$E68)+BE68 -> 381.15007 | BH68: =BG68-BE68 -> 381.15007 | BJ68: 0 | BK68: 0 | BL68: =BM68/($E68*6.29287) -> 46.8 | BM68: =(($D68+BJ68)*6.29287*$E68)+BK68 -> 381.15007 | BN68: =BM68-BK68 -> 381.15007 | BP68: =AA68+0.25 -> -14.03 | BS68: N/A | BT68: N/A | BU68: N/A | BY68: N/A | BZ68: N/A | CA68: N/A
B69: 42522 | C69: =C57 -> 30 | D69: 48.85 | E69: 1.2896 | F69: -2.73 | G69: -0.4303 | H69: =I69/(E69*6.29287) -> 46.066977 | I69: =((D69+F69)*6.29287*E69)+G69 -> 373.84665 | J69: =I69-G69 -> 374.27695 | K69: =(D69+F69)/D69 -> 0.94411464 | L69: =M69-F69 -> -1.11 | M69: -3.84 | N69: =O69/(E69*6.29287) -> 44.091597 | O69: =((D69+M69)*6.29287*E69)+X69 -> 357.81588 | P69: =O69-X69 -> 365.26898 | Q69: =(D69+M69)/D69 -> 0.92139202 | T69: =(($D69+R69)*$E69*6.29287)+X69 -> 388.97858 | U69: =T69-X69 -> 396.43168 | X69: -7.4531 | Y69: 0.16 | AA69: -12.38 | AB69: =(D69+AA69)*E69*6.2898105 -> 295.82056 | AC69: =D69+AA69 -> 36.47 | AG69: =F69-AA69 -> 9.65 | AH69: =(D69+AA69)/D69 -> 0.74657114 | AJ69: 0.75 | AK69: =AL69/(6.29287*E69) -> 36.6375 | AL69: =(AJ69*D69)*6.29287*E69 -> 297.32376 | AR69: 0 | AS69: 0 | AT69: =AU69/($E69*6.29287) -> 48.85 | AU69: =(($D69+AR69)*6.29287*$E69)+AS69 -> 396.43168 | AV69: =AU69-AS69 -> 396.43168 | AX69: 0 | AY69: 0 | AZ69: =BA69/($E69*6.29287) -> 48.85 | BA69: =(($D69+AX69)*6.29287*$E69)+AY69 -> 396.43168 | BB69: =BA69-AY69 -> 396.43168 | BD69: 0 | BE69: 0 | BF69: =BG69/($E69*6.29287) -> 48.85 | BG69: =(($D69+BD69)*6.29287*$E69)+BE69 -> 396.43168 | BH69: =BG69-BE69 -> 396.43168 | BJ69: 0 | BK69: 0 | BL69: =BM69/($E69*6.29287) -> 48.85 | BM69: =(($D69+BJ69)*6.29287*$E69)+BK69 -> 396.43168 | BN69: =BM69-BK69 -> 396.43168 | BP69: =AA69+0.25 -> -12.13 | BS69: N/A | BT69: N/A | BU69: N/A | BY69: N/A | BZ69: N/A | CA69: N/A
B70: 42552 | C70: =C58 -> 31 | D70: 44.8 | E70: 1.305 | F70: -1.63 | G70: -0.7142 | H70: =I70/(E70*6.29287) -> 43.083032 | I70: =((D70+F70)*6.29287*E70)+G70 -> 353.80627 | J70: =I70-G70 -> 354.52047 | K70: =(D70+F70)/D70 -> 0.96361607 | L70: =M70-F70 -> -0.65 | M70: -2.28 | N70: =O70/(E70*6.29287) -> 41.784752 | O70: =((D70+M70)*6.29287*E70)+X70 -> 343.14455 | P70: =O70-X70 -> 349.18255 | Q70: =(D70+M70)/D70 -> 0.94910714 | T70: =(($D70+R70)*$E70*6.29287)+X70 -> 361.86835 | U70: =T70-X70 -> 367.90635 | X70: -6.038 | Y70: 0.19 | AA70: -12 | AB70: =(D70+AA70)*E70*6.2898105 -> 269.22905 | AC70: =D70+AA70 -> 32.8 | AG70: =F70-AA70 -> 10.37 | AH70: =(D70+AA70)/D70 -> 0.73214286 | AJ70: 0.75 | AK70: =AL70/(6.29287*E70) -> 33.6 | AL70: =(AJ70*D70)*6.29287*E70 -> 275.92976 | AR70: 0 | AS70: 0 | AT70: =AU70/($E70*6.29287) -> 44.8 | AU70: =(($D70+AR70)*6.29287*$E70)+AS70 -> 367.90635 | AV70: =AU70-AS70 -> 367.90635 | AX70: 0 | AY70: 0 | AZ70: =BA70/($E70*6.29287) -> 44.8 | BA70: =(($D70+AX70)*6.29287*$E70)+AY70 -> 367.90635 | BB70: =BA70-AY70 -> 367.90635 | BD70: 0 | BE70: 0 | BF70: =BG70/($E70*6.29287) -> 44.8 | BG70: =(($D70+BD70)*6.29287*$E70)+BE70 -> 367.90635 | BH70: =BG70-BE70 -> 367.90635 | BJ70: 0 | BK70: 0 | BL70: =BM70/($E70*6.29287) -> 44.8 | BM70: =(($D70+BJ70)*6.29287*$E70)+BK70 -> 367.90635 | BN70: =BM70-BK70 -> 367.90635 | BP70: =AA70+0.25 -> -11.75 | BS70: N/A | BT70: N/A | BU70: N/A | BY70: N/A | BZ70: N/A | CA70: N/A
B71: 42583 | C71: =C59 -> 31 | D71: 44.8 | E71: 1.2994 | F71: -3.53 | G71: -0.8892 | H71: =I71/(E71*6.29287) -> 41.161255 | I71: =((D71+F71)*6.29287*E71)+G71 -> 336.57374 | J71: =I71-G71 -> 337.46294 | K71: =(D71+F71)/D71 -> 0.92120536 | L71: =M71-F71 -> 0.17 | M71: -3.36 | N71: =O71/(E71*6.29287) -> 40.753057 | O71: =((D71+M71)*6.29287*E71)+X71 -> 333.23593 | P71: =O71-X71 -> 338.85303 | Q71: =(D71+M71)/D71 -> 0.925 | T71: =(($D71+R71)*$E71*6.29287)+X71 -> 360.7105 | U71: =T71-X71 -> 366.3276 | X71: -5.6171 | Y71: 0.22 | AA71: -13.9 | AB71: =(D71+AA71)*E71*6.2898105 -> 252.54507 | AC71: =D71+AA71 -> 30.9 | AG71: =F71-AA71 -> 10.37 | AH71: =(D71+AA71)/D71 -> 0.68973214 | AJ71: 0.75 | AK71: =AL71/(6.29287*E71) -> 33.6 | AL71: =(AJ71*D71)*6.29287*E71 -> 274.7457 | AR71: 0 | AS71: 0 | AT71: =AU71/($E71*6.29287) -> 44.8 | AU71: =(($D71+AR71)*6.29287*$E71)+AS71 -> 366.3276 | AV71: =AU71-AS71 -> 366.3276 | AX71: 0 | AY71: 0 | AZ71: =BA71/($E71*6.29287) -> 44.8 | BA71: =(($D71+AX71)*6.29287*$E71)+AY71 -> 366.3276 | BB71: =BA71-AY71 -> 366.3276 | BD71: 0 | BE71: 0 | BF71: =BG71/($E71*6.29287) -> 44.8 | BG71: =(($D71+BD71)*6.29287*$E71)+BE71 -> 366.3276 | BH71: =BG71-BE71 -> 366.3276 | BJ71: 0 | BK71: 0 | BL71: =BM71/($E71*6.29287) -> 44.8 | BM71: =(($D71+BJ71)*6.29287*$E71)+BK71 -> 366.3276 | BN71: =BM71-BK71 -> 366.3276 | BP71: =AA71+0.25 -> -13.65 | BS71: N/A | BT71: N/A | BU71: N/A | BY71: N/A | BZ71: N/A | CA71: N/A
B72: 42614 | C72: =C60 -> 30 | D72: 45.23 | E72: 1.3109 | F72: -3.71 | G72: -0.674 | H72: =I72/(E72*6.29287) -> 41.438296 | I72: =((D72+F72)*6.29287*E72)+G72 -> 341.8379 | J72: =I72-G72 -> 342.5119 | K72: =(D72+F72)/D72 -> 0.9179748 | L72: =M72-F72 -> 3.74 | M72: 0.03 | N72: =O72/(E72*6.29287) -> 44.629815 | O72: =((D72+M72)*6.29287*E72)+X72 -> 368.16577 | P72: =O72-X72 -> 373.36437 | Q72: =(D72+M72)/D72 -> 1.0006633 | T72: =(($D72+R72)*$E72*6.29287)+X72 -> 367.91829 | U72: =T72-X72 -> 373.11689 | X72: -5.1986 | Y72: 0.3 | AA72: -14.61 | AB72: =(D72+AA72)*E72*6.2898105 -> 252.47147 | AC72: =D72+AA72 -> 30.62 | AG72: =F72-AA72 -> 10.9 | AH72: =(D72+AA72)/D72 -> 0.6769843 | AJ72: 0.75 | AK72: =AL72/(6.29287*E72) -> 33.9225 | AL72: =(AJ72*D72)*6.29287*E72 -> 279.83767 | AR72: 0 | AS72: 0 | AT72: =AU72/($E72*6.29287) -> 45.23 | AU72: =(($D72+AR72)*6.29287*$E72)+AS72 -> 373.11689 | AV72: =AU72-AS72 -> 373.11689 | AX72: 0 | AY72: 0 | AZ72: =BA72/($E72*6.29287) -> 45.23 | BA72: =(($D72+AX72)*6.29287*$E72)+AY72 -> 373.11689 | BB72: =BA72-AY72 -> 373.11689 | BD72: 0 | BE72: 0 | BF72: =BG72/($E72*6.29287) -> 45.23 | BG72: =(($D72+BD72)*6.29287*$E72)+BE72 -> 373.11689 | BH72: =BG72-BE72 -> 373.11689 | BJ72: 0 | BK72: 0 | BL72: =BM72/($E72*6.29287) -> 45.23 | BM72: =(($D72+BJ72)*6.29287*$E72)+BK72 -> 373.11689 | BN72: =BM72-BK72 -> 373.11689 | BP72: =AA72+0.25 -> -14.36 | BS72: N/A | BT72: N/A | BU72: N/A | BY72: N/A | BZ72: N/A | CA72: N/A
B73: 42644 | C73: =C61 -> 31 | D73: 49.94 | E73: 1.3251 | F73: -2.43 | G73: 0.5506 | H73: =I73/(E73*6.29287) -> 47.57603 | I73: =((D73+F73)*6.29287*E73)+G73 -> 396.72138 | J73: =I73-G73 -> 396.17078 | K73: =(D73+F73)/D73 -> 0.95134161 | L73: =M73-F73 -> 1.38 | M73: -1.05 | N73: =O73/(E73*6.29287) -> 48.00763 | O73: =((D73+M73)*6.29287*E73)+X73 -> 400.32036 | P73: =O73-X73 -> 407.67816 | Q73: =(D73+M73)/D73 -> 0.97897477 | T73: =(($D73+R73)*$E73*6.29287)+X73 -> 409.07598 | U73: =T73-X73 -> 416.43378 | X73: -7.3578 | Y73: 0.26 | AA73: -14.11 | AB73: =(D73+AA73)*E73*6.2898105 -> 298.62972 | AC73: =D73+AA73 -> 35.83 | AG73: =F73-AA73 -> 11.68 | AH73: =(D73+AA73)/D73 -> 0.71746095 | AJ73: 0.75 | AK73: =AL73/(6.29287*E73) -> 37.455 | AL73: =(AJ73*D73)*6.29287*E73 -> 312.32534 | AR73: 0 | AS73: 0 | AT73: =AU73/($E73*6.29287) -> 49.94 | AU73: =(($D73+AR73)*6.29287*$E73)+AS73 -> 416.43378 | AV73: =AU73-AS73 -> 416.43378 | AX73: 0 | AY73: 0 | AZ73: =BA73/($E73*6.29287) -> 49.94 | BA73: =(($D73+AX73)*6.29287*$E73)+AY73 -> 416.43378 | BB73: =BA73-AY73 -> 416.43378 | BD73: 0 | BE73: 0 | BF73: =BG73/($E73*6.29287) -> 49.94 | BG73: =(($D73+BD73)*6.29287*$E73)+BE73 -> 416.43378 | BH73: =BG73-BE73 -> 416.43378 | BJ73: 0 | BK73: 0 | BL73: =BM73/($E73*6.29287) -> 49.94 | BM73: =(($D73+BJ73)*6.29287*$E73)+BK73 -> 416.43378 | BN73: =BM73-BK73 -> 416.43378 | BP73: =AA73+0.25 -> -13.86 | BS73: N/A | BT73: N/A | BU73: N/A | BY73: N/A | BZ73: N/A | CA73: N/A
B74: 42675 | C74: =C62 -> 30 | D74: 45.76 | E74: 1.3438 | F74: -2.95 | G74: -0.3044 | H74: =I74/(E74*6.29287) -> 42.774003 | I74: =((D74+F74)*6.29287*E74)+G74 -> 361.71232 | J74: =I74-G74 -> 362.01672 | K74: =(D74+F74)/D74 -> 0.93553322 | L74: =M74-F74 -> 1.97 | M74: -0.98 | N74: =O74/(E74*6.29287) -> 43.799826 | O74: =((D74+M74)*6.29287*E74)+X74 -> 370.38704 | P74: =O74-X74 -> 378.67574 | Q74: =(D74+M74)/D74 -> 0.97858392 | T74: =(($D74+R74)*$E74*6.29287)+X74 -> 378.67427 | U74: =T74-X74 -> 386.96297 | X74: -8.2887 | Y74: 0.28 | AA74: -13.87 | AB74: =(D74+AA74)*E74*6.2898105 -> 269.54217 | AC74: =D74+AA74 -> 31.89 | AG74: =F74-AA74 -> 10.92 | AH74: =(D74+AA74)/D74 -> 0.69689685 | AJ74: 0.75 | AK74: =AL74/(6.29287*E74) -> 34.32 | AL74: =(AJ74*D74)*6.29287*E74 -> 290.22223 | AR74: 0 | AS74: 0 | AT74: =AU74/($E74*6.29287) -> 45.76 | AU74: =(($D74+AR74)*6.29287*$E74)+AS74 -> 386.96297 | AV74: =AU74-AS74 -> 386.96297 | AX74: 0 | AY74: 0 | AZ74: =BA74/($E74*6.29287) -> 45.76 | BA74: =(($D74+AX74)*6.29287*$E74)+AY74 -> 386.96297 | BB74: =BA74-AY74 -> 386.96297 | BD74: 0 | BE74: 0 | BF74: =BG74/($E74*6.29287) -> 45.76 | BG74: =(($D74+BD74)*6.29287*$E74)+BE74 -> 386.96297 | BH74: =BG74-BE74 -> 386.96297 | BJ74: 0 | BK74: 0 | BL74: =BM74/($E74*6.29287) -> 45.76 | BM74: =(($D74+BJ74)*6.29287*$E74)+BK74 -> 386.96297 | BN74: =BM74-BK74 -> 386.96297 | BP74: =AA74+0.25 -> -13.62 | BS74: N/A | BT74: N/A | BU74: N/A | BY74: N/A | BZ74: N/A | CA74: N/A
B75: 42705 | C75: =C63 -> 31 | D75: 52.17 | E75: 1.3329 | F75: -3.96 | G75: -0.0324 | H75: =I75/(E75*6.29287) -> 48.206137 | I75: =((D75+F75)*6.29287*E75)+G75 -> 404.34182 | J75: =I75-G75 -> 404.37422 | K75: =(D75+F75)/D75 -> 0.92409431 | L75: =M75-F75 -> 3.12 | M75: -0.84 | N75: =O75/(E75*6.29287) -> 50.771627 | O75: =((D75+M75)*6.29287*E75)+X75 -> 425.86055 | P75: =O75-X75 -> 430.54405 | Q75: =(D75+M75)/D75 -> 0.98389879 | T75: =(($D75+R75)*$E75*6.29287)+X75 -> 432.90627 | U75: =T75-X75 -> 437.58977 | X75: -4.6835 | Y75: 0.31 | AA75: -14.99 | AB75: =(D75+AA75)*E75*6.2898105 -> 311.70554 | AC75: =D75+AA75 -> 37.18 | AG75: =F75-AA75 -> 11.03 | AH75: =(D75+AA75)/D75 -> 0.71267012 | AJ75: 0.75 | AK75: =AL75/(6.29287*E75) -> 39.1275 | AL75: =(AJ75*D75)*6.29287*E75 -> 328.19233 | AR75: 0 | AS75: 0 | AT75: =AU75/($E75*6.29287) -> 52.17 | AU75: =(($D75+AR75)*6.29287*$E75)+AS75 -> 437.58977 | AV75: =AU75-AS75 -> 437.58977 | AX75: 0 | AY75: 0 | AZ75: =BA75/($E75*6.29287) -> 52.17 | BA75: =(($D75+AX75)*6.29287*$E75)+AY75 -> 437.58977 | BB75: =BA75-AY75 -> 437.58977 | BD75: 0 | BE75: 0 | BF75: =BG75/($E75*6.29287) -> 52.17 | BG75: =(($D75+BD75)*6.29287*$E75)+BE75 -> 437.58977 | BH75: =BG75-BE75 -> 437.58977 | BJ75: 0 | BK75: 0 | BL75: =BM75/($E75*6.29287) -> 52.17 | BM75: =(($D75+BJ75)*6.29287*$E75)+BK75 -> 437.58977 | BN75: =BM75-BK75 -> 437.58977 | BP75: =AA75+0.25 -> -14.74 | BS75: N/A | BT75: N/A | BU75: N/A | BY75: N/A | BZ75: N/A | CA75: N/A
B76: 42736 | C76: =C64 -> 31 | D76: 52.61 | E76: 1.3191 | F76: -4.25 | G76: 0.2613 | H76: =I76/(E76*6.29287) -> 48.391478 | I76: =((D76+F76)*6.29287*E76)+G76 -> 401.69402 | J76: =I76-G76 -> 401.43272 | K76: =(D76+F76)/D76 -> 0.91921688 | L76: =M76-F76 -> 3.86 | M76: -0.39 | N76: =O76/(E76*6.29287) -> 51.935706 | O76: =((D76+M76)*6.29287*E76)+X76 -> 431.11439 | P76: =O76-X76 -> 433.47429 | Q76: =(D76+M76)/D76 -> 0.99258696 | T76: =(($D76+R76)*$E76*6.29287)+X76 -> 434.35175 | U76: =T76-X76 -> 436.71165 | X76: -2.3599 | Y76: 0.31 | AA76: -15.42 | AB76: =(D76+AA76)*E76*6.2898105 -> 308.5613 | AC76: =D76+AA76 -> 37.19 | AG76: =F76-AA76 -> 11.17 | AH76: =(D76+AA76)/D76 -> 0.70689983 | AJ76: 0.75 | AK76: =AL76/(6.29287*E76) -> 39.4575 | AL76: =(AJ76*D76)*6.29287*E76 -> 327.53374 | AR76: 0 | AS76: 0 | AT76: =AU76/($E76*6.29287) -> 52.61 | AU76: =(($D76+AR76)*6.29287*$E76)+AS76 -> 436.71165 | AV76: =AU76-AS76 -> 436.71165 | AX76: 0 | AY76: 0 | AZ76: =BA76/($E76*6.29287) -> 52.61 | BA76: =(($D76+AX76)*6.29287*$E76)+AY76 -> 436.71165 | BB76: =BA76-AY76 -> 436.71165 | BD76: 0 | BE76: 0 | BF76: =BG76/($E76*6.29287) -> 52.61 | BG76: =(($D76+BD76)*6.29287*$E76)+BE76 -> 436.71165 | BH76: =BG76-BE76 -> 436.71165 | BJ76: 0 | BK76: 0 | BL76: =BM76/($E76*6.29287) -> 52.61 | BM76: =(($D76+BJ76)*6.29287*$E76)+BK76 -> 436.71165 | BN76: =BM76-BK76 -> 436.71165 | BP76: =AA76+0.25 -> -15.17 | BS76: N/A | BT76: N/A | BU76: N/A | BY76: N/A | BZ76: N/A | CA76: N/A
B77: 42767 | C77: 28 | D77: 53.46 | E77: 1.311 | F77: -3.14 | G77: -1.1548 | H77: =I77/(E77*6.29287) -> 50.180023 | I77: =((D77+F77)*6.29287*E77)+G77 -> 413.98281 | J77: =I77-G77 -> 415.13761 | K77: =(D77+F77)/D77 -> 0.9412645 | L77: =M77-F77 -> 3.73 | M77: 0.59 | N77: =O77/(E77*6.29287) -> 53.695307 | O77: =((D77+M77)*6.29287*E77)+X77 -> 442.98374 | P77: =O77-X77 -> 445.90994 | Q77: =(D77+M77)/D77 -> 1.0110363 | T77: =(($D77+R77)*$E77*6.29287)+X77 -> 438.11626 | U77: =T77-X77 -> 441.04246 | X77: -2.9262 | Y77: 0.31 | AA77: -14.32 | AB77: =(D77+AA77)*E77*6.2898105 -> 322.74615 | AC77: =D77+AA77 -> 39.14 | AG77: =F77-AA77 -> 11.18 | AH77: =(D77+AA77)/D77 -> 0.73213618 | AJ77: 0.75 | AK77: =AL77/(6.29287*E77) -> 40.095 | AL77: =(AJ77*D77)*6.29287*E77 -> 330.78185 | AR77: 0 | AS77: 0 | AT77: =AU77/($E77*6.29287) -> 53.46 | AU77: =(($D77+AR77)*6.29287*$E77)+AS77 -> 441.04246 | AV77: =AU77-AS77 -> 441.04246 | AX77: 0 | AY77: 0 | AZ77: =BA77/($E77*6.29287) -> 53.46 | BA77: =(($D77+AX77)*6.29287*$E77)+AY77 -> 441.04246 | BB77: =BA77-AY77 -> 441.04246 | BD77: 0 | BE77: 0 | BF77: =BG77/($E77*6.29287) -> 53.46 | BG77: =(($D77+BD77)*6.29287*$E77)+BE77 -> 441.04246 | BH77: =BG77-BE77 -> 441.04246 | BJ77: 0 | BK77: 0 | BL77: =BM77/($E77*6.29287) -> 53.46 | BM77: =(($D77+BJ77)*6.29287*$E77)+BK77 -> 441.04246 | BN77: =BM77-BK77 -> 441.04246 | BP77: =AA77+0.25 -> -14.07 | BS77: N/A | BT77: N/A | BU77: N/A | BY77: N/A | BZ77: N/A | CA77: N/A
B78: 42795 | C78: =C66 -> 31 | D78: 49.67 | E78: 1.3388 | F78: -3.24 | G78: -1.0738 | H78: =I78/(E78*6.29287) -> 46.302544 | I78: =((D78+F78)*6.29287*E78)+G78 -> 390.09404 | J78: =I78-G78 -> 391.16784 | K78: =(D78+F78)/D78 -> 0.93476948 | L78: =M78-F78 -> 4.1 | M78: 0.86 | N78: =O78/(E78*6.29287) -> 50.271291 | O78: =((D78+M78)*6.29287*E78)+X78 -> 423.53031 | P78: =O78-X78 -> 425.70991 | Q78: =(D78+M78)/D78 -> 1.0173143 | T78: =(($D78+R78)*$E78*6.29287)+X78 -> 416.2849 | U78: =T78-X78 -> 418.4645 | X78: -2.1796 | Y78: 0.32 | AA78: -14.28 | AB78: =(D78+AA78)*E78*6.2898105 -> 298.01205 | AC78: =D78+AA78 -> 35.39 | AG78: =F78-AA78 -> 11.04 | AH78: =(D78+AA78)/D78 -> 0.71250252 | AJ78: 0.75 | AK78: =AL78/(6.29287*E78) -> 37.2525 | AL78: =(AJ78*D78)*6.29287*E78 -> 313.84838 | AR78: 0 | AS78: 0 | AT78: =AU78/($E78*6.29287) -> 49.67 | AU78: =(($D78+AR78)*6.29287*$E78)+AS78 -> 418.4645 | AV78: =AU78-AS78 -> 418.4645 | AX78: 0 | AY78: 0 | AZ78: =BA78/($E78*6.29287) -> 49.67 | BA78: =(($D78+AX78)*6.29287*$E78)+AY78 -> 418.4645 | BB78: =BA78-AY78 -> 418.4645 | BD78: 0 | BE78: 0 | BF78: =BG78/($E78*6.29287) -> 49.67 | BG78: =(($D78+BD78)*6.29287*$E78)+BE78 -> 418.4645 | BH78: =BG78-BE78 -> 418.4645 | BJ78: 0 | BK78: 0 | BL78: =BM78/($E78*6.29287) -> 49.67 | BM78: =(($D78+BJ78)*6.29287*$E78)+BK78 -> 418.4645 | BN78: =BM78-BK78 -> 418.4645 | BP78: =AA78+0.25 -> -14.03 | BS78: N/A | BT78: N/A | BU78: N/A | BY78: N/A | BZ78: N/A | CA78: N/A
